Workbook

Sheet Sheet1
A1: Code | B1: Sub-category | C1: Սեռ(կանացի,տղամարդ,աղջիկ,տղա) | D1: Բրուտտո քաշ | E1: Նետտո քաշ | G1: Քանակ հատ | H1: Բրենդ | I1: Ծագման երկիր | J1: Ապրանքի մատերիալ
A2: 40000001111 | B2: հուդի | C2: տղամարդու | D2: 55 | E2: 55 | F2: =E2/1000 -> 0.055 | G2: 1 | H2: PETROL | I2: Bangladesh | J2: բամբակ/պոլիեսթեր
A3: 40000001112 | B3: բլուզ | C3: տղամարդու | D3: 334 | E3: 334 | F3: =E3/1000 -> 0.334 | G3: 1 | H3: PETROL | I3: Bangladesh | J3: ակրիլ/բամբակ
A4: 40000001113 | B4: 35-ից բաձր կոշիկ | C4: տղամարդու | D4: 1086 | E4: 1086 | F4: =E4/1000 -> 1.086 | G4: 1 | H4: REGATTA | I4: China | J4: տակը ռետին, վրան կտոր
A5: 40000001114 | B5: 35-ից բաձր կոշիկ | C5: կին | D5: 42 | E5: 42 | F5: =E5/1000 -> 0.042 | G5: 1 | H5: REEBOK | I5: China | J5: տակը ռետին, վրան կտոր
A6: 40000001110 | B6: տաբատ | C6: տղայի | D6: 304 | E6: 304 | F6: =E6/1000 -> 0.304 | G6: 1 | H6: S.OLIVER | I6: Bangladesh | J6: բամբակ
A7: 40000001109 | B7: 35-ից բաձր կոշիկ | C7: կին | D7: 850 | E7: 1418 | F7: =E7/1000 -> 1.418 | G7: 1 | H7: RAGE AGE | I7: Poland | J7: տակը պոլիմեր, վրան զամշ
A8: 40000001108 | B8: 35-ից բարձր հողաթափ | C8: յունիսեքս | D8: 388 | E8: 582 | F8: =E8/1000 -> 0.582 | G8: 1 | H8: UGG | I8: Vietnam | J8: բուրդ/լիոցել
A9: 40000001107 | B9: վերարկու | C9: կին | D9: 1102 | E9: 1102 | F9: =E9/1000 -> 1.102 | G9: 1 | H9: TOMTAILOR | I9: Vietnam | J9: պոլիեսթեր
A10: 40000001106 | B10: բլուզ | C10: տղամարդու | D10: 344 | E10: 344 | F10: =E10/1000 -> 0.344 | G10: 1 | H10: PETROL | I10: Bangladesh | J10: բամբակ/ակրիլ
A11: 40000001105 | B11: վերարկու | C11: տղամարդու | D11: 1136 | E11: 1136 | F11: =E11/1000 -> 1.136 | G11: 1 | H11: PETROL | I11: China | J11: պոլիեսթեր
A12: 40000001104 | B12: վերարկու | C12: տղամարդու | D12: 1194 | E12: 1194 | F12: =E12/1000 -> 1.194 | G12: 1 | H12: PETROL | I12: China | J12: պոլիեսթեր
A13: 40000001103 | B13: վերարկու | C13: տղամարդու | D13: 1076 | E13: 1076 | F13: =E13/1000 -> 1.076 | G13: 1 | H13: PETROL | I13: China | J13: պոլիեսթեր
... A841: 40000000277 | B841: բլուզ | C841: կին | D841: 160 | E841: 160 | F841: =E841/1000 -> 0.16 | G841: 1 | H841: DE FACTO | I841: Turkey | J841: պոլիեսթեր
A842: 40000000276 | B842: սեթ 3 շապիկ + տաբատ + գլխարկ | C842: կին | D842: 404 | E842: 404 | F842: =E842/1000 -> 0.404 | G842: 3 set | H842: DE FACTO | I842: Turkey | J842: պոլիեսթեր
A843: 40000000275 | B843: վերնաշապիկ | C843: կին | D843: 248 | E843: 248 | F843: =E843/1000 -> 0.248 | G843: 1 | H843: DE FACTO | I843: Bangladesh | J843: բամբակ
A844: 40000000274 | B844: մինչև 1 կոմբինեզոն | C844: տղայի | D844: 98 | E844: 98 | F844: =E844/1000 -> 0.098 | G844: 1 | H844: DE FACTO | I844: Turkey | J844: բամբակ
A845: 40000000273 | B845: Տաբատ | C845: կին | D845: 354 | E845: 354 | F845: =E845/1000 -> 0.354 | G845: 1 | H845: DE FACTO | I845: Turkey | J845: վիսկոզ/բամբակ
A846: 40000000272 | B846: բլուզ | C846: կին | D846: 86 | E846: 86 | F846: =E846/1000 -> 0.086 | G846: 1 | H846: DE FACTO | I846: Turkey | J846: պոլիեսթեր
A847: 40000000271 | B847: բլուզ | C847: կին | D847: 260 | E847: 260 | F847: =E847/1000 -> 0.26 | G847: 1 | H847: DE FACTO | I847: Turkey | J847: բամբակ
A848: 40000000270 | B848: շապիկ | C848: տղամարդու | D848: 178 | E848: 178 | F848: =E848/1000 -> 0.178 | G848: 1 | H848: DE FACTO | I848: Turkey | J848: բամբակ
A849: 40000000269 | B849: ջինսե տաբատ | C849: կին | D849: 510 | E849: 510 | F849: =E849/1000 -> 0.51 | G849: 1 | H849: DE FACTO | I849: Bangladesh | J849: բամբակ
A850: 40000000268 | B850: շապիկ | C850: տղամարդու | D850: 126 | E850: 126 | F850: =E850/1000 -> 0.126 | G850: 1 | H850: DE FACTO | I850: Turkey | J850: բամբակ
A851: 40000000267 | B851: ջինսե տաբատ | C851: կին | D851: 676 | E851: 676 | F851: =E851/1000 -> 0.676 | G851: 1 | H851: DE FACTO | I851: Turkey | J851: բամբակ
A852: 40000000266 | B852: սվիտեր | C852: կին | D852: 266 | E852: 266 | F852: =E852/1000 -> 0.266 | G852: 1 | H852: DE FACTO | I852: Turkey | J852: պոլիեսթեր
A853: 40000000265 | B853: բլուզ | C853: կին | D853: 142 | E853: 142 | F853: =E853/1000 -> 0.142 | G853: 1 | H853: DE FACTO | I853: Bangladesh | J853: բամբակ
A854: 40000000264 | B854: ջինսե տաբատ | C854: կին | D854: 544 | E854: 544 | F854: =E854/1000 -> 0.544 | G854: 1 | H854: DE FACTO | I854: Bangladesh | J854: բամբակ
... A948: 60000000469 | B948: լողազգեստ | C948: կին | D948: 214 | E948: 214 | F948: =E948/1000 -> 0.214 | G948: 1 | H948: ASOS | I948: Albania | J948: պոլիեսթեր
A949: 60000000468 | B949: տոպ | C949: կին | D949: 0.056 | E949: 0.056 | F949: =E949 -> 0.056 | G949: 1 | H949: COLLUSION | I949: Bangladesh | J949: բամբակ
A950: 60000000467 | B950: տոպ | C950: կին | D950: 0.056 | E950: 0.056 | F950: =E950 -> 0.056 | G950: 1 | H950: COLLUSION | I950: Bangladesh | J950: բամբակ
A951: 60000000466 | B951: տոպ | C951: կին | D951: 0.056 | E951: 0.056 | F951: =E951 -> 0.056 | G951: 1 | H951: COLLUSION | I951: Bangladesh | J951: բամբակ
A952: 60000000465 | B952: տոպ | C952: կին | D952: 0.04 | E952: 0.04 | F952: =E952 -> 0.04 | G952: 1 | H952: COLLUSION | I952: Bangladesh | J952: բամբակ
A953: 60000000464 | B953: տոպ | C953: կին | D953: 0.04 | E953: 0.04 | F953: =E953 -> 0.04 | G953: 1 | H953: COLLUSION | I953: Bangladesh | J953: բամբակ
A954: 60000000463 | B954: տոպ | C954: կին | D954: 0.04 | E954: 0.04 | F954: =E954 -> 0.04 | G954: 1 | H954: COLLUSION | I954: Bangladesh | J954: բամբակ
A955: 60000000462 | B955: տոպ | C955: կին | D955: 0.04 | E955: 0.04 | F955: =E955 -> 0.04 | G955: 1 | H955: COLLUSION | I955: Bangladesh | J955: բամբակ
A956: 60000000461 | B956: տոպ | C956: կին | D956: 0.04 | E956: 0.04 | F956: =E956 -> 0.04 | G956: 1 | H956: COLLUSION | I956: Bangladesh | J956: բամբակ
A957: 60000000460 | B957: կիսաշրջազգեստ | C957: կին | D957: 226 | E957: 226 | F957: =E957/1000 -> 0.226 | G957: 1 | H957: ASOS | I957: India | J957: բամբակ
A958: 60000000459 | B958: կիսաշրջազգեստ | C958: կին | D958: 226 | E958: 226 | F958: =E958/1000 -> 0.226 | G958: 1 | H958: ASOS | I958: India | J958: բամբակ
A959: 60000000458 | B959: շապիկ | C959: տղամարդու | D959: 118 | E959: 118 | F959: =E959/1000 -> 0.118 | G959: 1 | H959: VANS | I959: Georgia | J959: բամբակ
A960: 60000000457 | B960: Տաբատ | C960: կին | D960: 184 | E960: 184 | F960: =E960/1000 -> 0.184 | G960: 1 | H960: ASOS | I960: Bangladesh | J960: բամբակ
A961: 60000000456 | B961: շապիկ | C961: տղամարդու | D961: 200 | E961: 200 | F961: =E961/1000 -> 0.2 | G961: 1 | H961: ASOS | I961: Madagaskar | J961: բամբակ
A962: 60000000455 | B962: շապիկ | C962: տղամարդու | D962: 200 | E962: 200 | F962: =E962/1000 -> 0.2 | G962: 1 | H962: ASOS | I962: Madagaskar | J962: բամբակ
A963: 60000000454 | B963: տոպ | C963: կին | D963: 46 | E963: 46 | F963: =E963/1000 -> 0.046 | G963: 1 | H963: ASOS | I963: Bulgaria | J963: պոլիեսթեր
A964: 60000000453 | B964: զգեստ | C964: կին | D964: 250 | E964: 250 | F964: =E964/1000 -> 0.25 | G964: 1 | H964: ASOS | I964: India | J964: պոլիեսթեր
A965: 60000000452 | B965: կիսաշրջազգեստ | C965: կին | D965: 88 | E965: 88 | F965: =E965/1000 -> 0.088 | G965: 1 | H965: ASOS | I965: India | J965: պոլիեսթեր
A966: 60000000451 | B966: զգեստ | C966: կին | D966: 318 | E966: 318 | F966: =E966/1000 -> 0.318 | G966: 1 | H966: ASOS | I966: Turkey | J966: պոլիեսթեր
A967: 60000000450 | B967: լողազգեստ | C967: կին | D967: 0.058 | E967: 0.058 | F967: =E967 -> 0.058 | G967: 1 | H967: COLLUSION | I967: Bangladesh | J967: բամբակ
A968: 60000000449 | B968: զգեստ | C968: կին | D968: 318 | E968: 318 | F968: =E968/1000 -> 0.318 | G968: 1 | H968: ASOS | I968: Turkey | J968: պոլիեսթեր
A969: 60000000448 | B969: զգեստ | C969: կին | D969: 188 | E969: 188 | F969: =E969/1000 -> 0.188 | G969: 1 | H969: ASOS | I969: India | J969: բամբակ
A970: 60000000446 | B970: զգեստ | C970: կին | D970: 214 | E970: 214 | F970: =E970/1000 -> 0.214 | G970: 1 | H970: BRAVE SOUL | I970: China | J970: պոլիեսթեր
A971: 60000000445 | B971: զգեստ | C971: կին | D971: 214 | E971: 214 | F971: =E971/1000 -> 0.214 | G971: 1 | H971: BRAVE SOUL | I971: China | J971: պոլիեսթեր
A972: 60000000444 | B972: զգեստ | C972: կին | D972: 144 | E972: 144 | F972: =E972/1000 -> 0.144 | G972: 1 | H972: COLLUSION | I972: Bangladesh | J972: բամբակ
A973: 60000000443 | B973: զգեստ | C973: կին | D973: 144 | E973: 144 | F973: =E973/1000 -> 0.144 | G973: 1 | H973: COLLUSION | I973: Bangladesh | J973: բամբակ
A974: 60000000447 | B974: զգեստ | C974: կին | D974: 334 | E974: 334 | F974: =E974/1000 -> 0.334 | G974: 1 | H974: ASOS | I974: Romania | J974: պոլիեսթեր
A975: 60000000439 | B975: զգեստ | C975: կին | D975: 244 | E975: 244 | F975: =E975/1000 -> 0.244 | G975: 1 | H975: ASOS | I975: Bangladesh | J975: բամբակ
A976: 60000000440 | B976: զգեստ | C976: կին | D976: 244 | E976: 244 | F976: =E976/1000 -> 0.244 | G976: 1 | H976: ASOS | I976: Bangladesh | J976: բամբակ
A977: 60000000438 | B977: զգեստ | C977: կին | D977: 248 | E977: 248 | F977: =E977/1000 -> 0.248 | G977: 1 | H977: ASOS | I977: India | J977: պոլիեսթեր
A978: 60000000437 | B978: զգեստ | C978: կին | D978: 214 | E978: 214 | F978: =E978/1000 -> 0.214 | G978: 1 | H978: MISSGUIDED | I978: China | J978: պոլիեսթեր
A979: 60000000436 | B979: զգեստ | C979: կին | D979: 214 | E979: 214 | F979: =E979/1000 -> 0.214 | G979: 1 | H979: MISSGUIDED | I979: China | J979: պոլիեսթեր
... A996: 60000000418 | B996: վերնաշապիկ | C996: կին | D996: 256 | E996: 256 | F996: =E996/1000 -> 0.256 | G996: 1 | H996: ASOS | I996: Turkey | J996: բամբակ
A997: 60000000412 | B997: կրծկալ | C997: կին | D997: 0.07 | E997: 0.07 | F997: =E997 -> 0.07 | G997: 1 | H997: ANN SUMMERS | I997: China | J997: պոլիեսթեր
A998: 60000000421 | B998: զգեստ | C998: կին | D998: 206 | E998: 206 | F998: =E998/1000 -> 0.206 | G998: 1 | H998: VOILET ROMANCE | I998: India | J998: պոլիեսթեր
A999: 60000000422 | B999: զգեստ | C999: կին | D999: 206 | E999: 206 | F999: =E999/1000 -> 0.206 | G999: 1 | H999: VOILET ROMANCE | I999: India | J999: պոլիեսթեր
A1000: 60000000411 | B1000: տոպ | C1000: կին | D1000: 0.058 | E1000: 0.058 | F1000: =E1000 -> 0.058 | G1000: 1 | H1000: ASOS | I1000: Turkey | J1000: պոլիեսթեր
A1001: 60000000410 | B1001: տոպ | C1001: կին | D1001: 0.058 | E1001: 0.058 | F1001: =E1001 -> 0.058 | G1001: 1 | H1001: ASOS | I1001: Turkey | J1001: պոլիեսթեր
A1002: 60000000413 | B1002: զգեստ | C1002: կին | D1002: 342 | E1002: 342 | F1002: =E1002/1000 -> 0.342 | G1002: 1 | H1002: MANGO | I1002: Morocco | J1002: վիսկոզ
A1003: 60000000414 | B1003: զգեստ | C1003: կին | D1003: 342 | E1003: 342 | F1003: =E1003/1000 -> 0.342 | G1003: 1 | H1003: MANGO | I1003: Morocco | J1003: վիսկոզ
A1004: 60000000404 | B1004: զգեստ | C1004: կին | D1004: 220 | E1004: 220 | F1004: =E1004/1000 -> 0.22 | G1004: 1 | H1004: WEDNESDAY'S GIRL | I1004: Turkey | J1004: պոլիեսթեր
A1005: 60000000405 | B1005: զգեստ | C1005: կին | D1005: 220 | E1005: 220 | F1005: =E1005/1000 -> 0.22 | G1005: 1 | H1005: WEDNESDAY'S GIRL | I1005: Turkey | J1005: պոլիեսթեր
A1006: 60000000406 | B1006: զգեստ | C1006: կին | D1006: 220 | E1006: 220 | F1006: =E1006/1000 -> 0.22 | G1006: 1 | H1006: WEDNESDAY'S GIRL | I1006: Turkey | J1006: պոլիեսթեր
A1007: 60000000403 | B1007: անթև շապիկ | C1007: կին | D1007: 0.094 | E1007: 0.094 | F1007: =E1007 -> 0.094 | G1007: 1 | H1007: HIIT | I1007: Bulgaria | J1007: բամբակ
A1008: 60000000402 | B1008: անթև շապիկ | C1008: կին | D1008: 0.094 | E1008: 0.094 | F1008: =E1008 -> 0.094 | G1008: 1 | H1008: HIIT | I1008: Bulgaria | J1008: բամբակ
A1009: 60000000425 | B1009: զգեստ | C1009: կին | D1009: 336 | E1009: 336 | F1009: =E1009/1000 -> 0.336 | G1009: 1 | H1009: LIQUORISH | I1009: China | J1009: պոլիեսթեր
A1010: 60000000426 | B1010: զգեստ | C1010: կին | D1010: 336 | E1010: 336 | F1010: =E1010/1000 -> 0.336 | G1010: 1 | H1010: LIQUORISH | I1010: China | J1010: պոլիեսթեր
A1011: 60000000391 | B1011: անթև շապիկ | C1011: կին | D1011: 0.094 | E1011: 0.094 | F1011: =E1011 -> 0.094 | G1011: 1 | H1011: HIIT | I1011: Bulgaria | J1011: բամբակ
A1012: 60000000392 | B1012: անթև շապիկ | C1012: կին | D1012: 0.094 | E1012: 0.094 | F1012: =E1012 -> 0.094 | G1012: 1 | H1012: HIIT | I1012: Bulgaria | J1012: բամբակ
A1013: 60000000393 | B1013: անթև շապիկ | C1013: կին | D1013: 0.094 | E1013: 0.094 | F1013: =E1013 -> 0.094 | G1013: 1 | H1013: HIIT | I1013: Bulgaria | J1013: բամբակ
A1014: 60000000401 | B1014: կիսաշրջազգեստ | C1014: կին | D1014: 206 | E1014: 206 | F1014: =E1014/1000 -> 0.206 | G1014: 1 | H1014: URBAN REVIVO | I1014: China | J1014: պոլիեսթեր
A1015: 60000000400 | B1015: կիսաշրջազգեստ | C1015: կին | D1015: 206 | E1015: 206 | F1015: =E1015/1000 -> 0.206 | G1015: 1 | H1015: URBAN REVIVO | I1015: China | J1015: պոլիեսթեր
A1016: 60000000399 | B1016: զգեստ | C1016: կին | D1016: 218 | E1016: 218 | F1016: =E1016/1000 -> 0.218 | G1016: 1 | H1016: TWISTED WUNDER | I1016: Britania | J1016: պոլիեսթեր
A1017: 60000000398 | B1017: զգեստ | C1017: կին | D1017: 218 | E1017: 218 | F1017: =E1017/1000 -> 0.218 | G1017: 1 | H1017: TWISTED WUNDER | I1017: Britania | J1017: պոլիեսթեր
A1018: 60000000380 | B1018: տոպ | C1018: կին | D1018: 108 | E1018: 108 | F1018: =E1018/1000 -> 0.108 | G1018: 1 | H1018: HIIT | I1018: Bulgaria | J1018: բամբակ
A1019: 60000000383 | B1019: զգեստ | C1019: կին | D1019: 192 | E1019: 192 | F1019: =E1019/1000 -> 0.192 | G1019: 1 | H1019: INFLUENCE | I1019: India | J1019: պոլիեսթեր
A1020: 60000000382 | B1020: Տաբատ | C1020: կին | D1020: 144 | E1020: 144 | F1020: =E1020/1000 -> 0.144 | G1020: 1 | H1020: LOLA MAY | I1020: China | J1020: պոլիեսթեր
A1021: 60000000379 | B1021: շորտ | C1021: կին | D1021: 236 | E1021: 236 | F1021: =E1021/1000 -> 0.236 | G1021: 1 | H1021: ASYOU | I1021: Turkey | J1021: բամբակ
A1022: 60000000372 | B1022: բլուզ | C1022: կին | D1022: 176 | E1022: 176 | F1022: =E1022/1000 -> 0.176 | G1022: 1 | H1022: MISS SELFRIDGE | I1022: Morocco | J1022: վիսկոզ
A1023: 60000000368 | B1023: ակնոց | C1023: յունիսեքս | D1023: 0.034 | E1023: 0.034 | F1023: =E1023 -> 0.034 | G1023: 1 | H1023: ASOS | I1023: China | J1023: պլաստմաս
A1024: 60000000409 | B1024: վերնաշապիկ | C1024: տղամարդու | D1024: 178 | E1024: 178 | F1024: =E1024/1000 -> 0.178 | G1024: 1 | H1024: ASOS | I1024: Turkey | J1024: վիսկոզ
A1025: 60000000395 | B1025: զգեստ | C1025: կին | D1025: 0.096 | E1025: 0.096 | F1025: =E1025 -> 0.096 | G1025: 1 | H1025: COLLUSION | I1025: Britania | J1025: նիլոն
A1026: 60000000394 | B1026: զգեստ | C1026: կին | D1026: 244 | E1026: 244 | F1026: =E1026/1000 -> 0.244 | G1026: 1 | H1026: ASOS | I1026: Tunis | J1026: պոլիեսթեր
A1027: 60000000367 | B1027: վերնաշապիկ | C1027: տղամարդու | D1027: 222 | E1027: 222 | F1027: =E1027/1000 -> 0.222 | G1027: 1 | H1027: COLLUSION | I1027: Turkey | J1027: բամբակ
A1028: 60000000365 | B1028: տոպ | C1028: կին | D1028: 0.086 | E1028: 0.086 | F1028: =E1028 -> 0.086 | G1028: 1 | H1028: PUMA | I1028: China | J1028: բամբակ
A1029: 60000000362 | B1029: զգեստ | C1029: կին | D1029: 200 | E1029: 200 | F1029: =E1029/1000 -> 0.2 | G1029: 1 | H1029: ASOS | I1029: India | J1029: պոլիեսթեր
A1030: 60000000363 | B1030: զգեստ | C1030: կին | D1030: 196 | E1030: 196 | F1030: =E1030/1000 -> 0.196 | G1030: 1 | H1030: INFLUENCE | I1030: India | J1030: բամբակ
A1031: 60000000366 | B1031: պայուսակ | C1031: կին | D1031: 312 | E1031: 312 | F1031: =E1031/1000 -> 0.312 | G1031: 1 | H1031: MANGO | I1031: China | J1031: պոլիուրեթան
A1032: 60000000371 | B1032: վերնաշապիկ | C1032: տղամարդու | D1032: 154 | E1032: 154 | F1032: =E1032/1000 -> 0.154 | G1032: 1 | H1032: COLLUSION | I1032: China | J1032: վիսկոզ
A1033: 60000000370 | B1033: զգեստ | C1033: կին | D1033: 206 | E1033: 206 | F1033: =E1033/1000 -> 0.206 | G1033: 1 | H1033: MOTEL | I1033: China | J1033: պոլիեսթեր
A1034: 60000000416 | B1034: բաճկոն | C1034: կին | D1034: 876 | E1034: 876 | F1034: =E1034/1000 -> 0.876 | G1034: 1 | H1034: COLLUSION | I1034: Turkey | J1034: բամբակ
A1035: 60000000369 | B1035: զգեստ | C1035: կին | D1035: 178 | E1035: 178 | F1035: =E1035/1000 -> 0.178 | G1035: 1 | H1035: VIOLET ROMANCE | I1035: India | J1035: պոլիեսթեր
A1036: 60000000397 | B1036: զգեստ | C1036: կին | D1036: 424 | E1036: 424 | F1036: =E1036/1000 -> 0.424 | G1036: 1 | H1036: ASOS | I1036: India | J1036: բամբակ
...

Sheet Sheet2
B1: N | C1: Code | D1: HS code | E1: name | F1: Sub-category | G1: Սեռ(կանացի,տղամարդ,աղջիկ,տղա) | H1: Բրուտտո քաշ | I1: Նետտո քաշ | J1: Net kg | K1: Քանակ հատ | L1: Բրենդ | M1: Ծագման երկիր | N1: Ապրանքի մատերիալ
B2: 1 | C2: 40000001111 | D2: 61102091000 | E2: ՏՂԱՄԱՐԴՈՒ ՀՈՒԴԻՆԵՐ ԲԱՄԲԱԿԵ ՄԱՆՎԱԾՔԻՑ | F2: հուդի | G2: տղամարդու | H2: 55 | I2: 55 | J2: =I2/1000 -> 0.055 | K2: 1 | L2: PETROL | M2: Bangladesh | N2: բամբակ/պոլիեսթեր | O2: =VLOOKUP(C2,#REF!,#REF!) -> #REF!
B3: 2 | C3: 40000001112 | D3: 61103091000 | E3: ՏՂԱՄԱՐԴՈՒ ՍՎԻՏՐԵՐ ՔԻՄԻԱԿԱՆ ԹԵԼԵՐԻՑ | F3: սվիտեր | G3: տղամարդու | H3: 334 | I3: 334 | J3: =I3/1000 -> 0.334 | K3: 1 | L3: PETROL | M3: Bangladesh | N3: ակրիլ/բամբակ | O3: =VLOOKUP(C:C,#REF!,#REF!) -> #REF!
B4: 3 | C4: 40000001113 | D4: 64041990000 | E4: ՏՂԱՄԱՐԴՈՒ ԿՈՇԻԿ ՏԵՔՍԻԼԵ ԵՐԵՍԱՄԱՍՈՎ ՌԵՏԻՆԵ ԿՈՇԿԱՏԱԿՈՎ | F4: 35-ից բաձր կոշիկ | G4: տղամարդու | H4: 1086 | I4: 1086 | J4: =I4/1000 -> 1.086 | K4: 1 | L4: REGATTA | M4: China | N4: տակը ռետին, վրան կտոր | O4: =VLOOKUP(C:C,#REF!,#REF!) -> #REF!
B5: 4 | C5: 40000001114 | D5: 64041990000 | E5: ԿԱՆԱՑԻ ԿՈՇԻԿ ՏԵՔՍԻԼԵ ԵՐԵՍԱՄԱՍՈՎ ՌԵՏԻՆԵ ԿՈՇԿԱՏԱԿՈՎ | F5: 35-ից բաձր կոշիկ | G5: կին | H5: 42 | I5: 42 | J5: =I5/1000 -> 0.042 | K5: 1 | L5: REEBOK | M5: China | N5: տակը ռետին, վրան կտոր
B6: 5 | C6: 40000001110 | D6: 62034235000 | E6: ՏՂԱՅԻ ՏԱԲԱՏՆԵՐ ԲԱՄԲԱԿԵ ՄԱՆՎԱԾՔԻՑ | F6: տաբատ | G6: տղայի | H6: 304 | I6: 304 | J6: =I6/1000 -> 0.304 | K6: 1 | L6: S.OLIVER | M6: Bangladesh | N6: բամբակ
B7: 6 | C7: 40000001109 | D7: 64039998000 | E7: ԿԱՆԱՑԻ ԿՈՇԻԿ ԲՆԱԿԱՆ ԿԱՇՎԵ ԵՐԵՍԱՄԱՍՈՎ , ՊՈԼԻՄԵՐԱՅԻՆ ԿՈՇԿԱՏԱԿՈՎ | F7: 35-ից բաձր կոշիկ | G7: կին | H7: 1418 | I7: 850 | J7: =I7/1000 -> 0.85 | K7: 1 | L7: RAGE AGE | M7: Poland | N7: տակը պոլիմեր, վրան զամշ
B8: 7 | C8: 40000001108 | D8: 64041910000 | E8: ՏՂԱՄԱՐԴՈՒ ՀՈՂԱԹԱՓ ՏԵՔՍՏԻԼԵ ԵՐԵՍԱՄԱՍՈՎ , ՊՈԼԻՄԵՐԱՅԻՆ ԿՈՇԿԱՏՈՎ | F8: 35-ից բարձր հողաթափ | G8: յունիսեքս | H8: 582 | I8: 388 | J8: =I8/1000 -> 0.388 | K8: 1 | L8: UGG | M8: Vietnam | N8: բուրդ/լիոցել
B9: 8 | C9: 40000001107 | D9: 62024000010 | E9: ԿԱՆԱՑԻ ՎԵՐԱՐԿՈՒ ՔԻՄԻԱԿԱՆ ԹԵԼԵՐԻՑ | F9: վերարկու | G9: կին | H9: 1102 | I9: 1102 | J9: =I9/1000 -> 1.102 | K9: 1 | L9: TOMTAILOR | M9: Vietnam | N9: պոլիեսթեր
B10: 9 | C10: 40000001106 | D10: 61102091000 | E10: ՏՂԱՄԱՐԴՈՒ ՍՎԻՏՐԵՐ ԲԱՄԲԱԿԵ ՄԱՆՎԱԾՔԻՑ | F10: սվիտեր | G10: տղամարդու | H10: 344 | I10: 344 | J10: =I10/1000 -> 0.344 | K10: 1 | L10: PETROL | M10: Bangladesh | N10: բամբակ/ակրիլ
B11: 10 | C11: 40000001105 | D11: 62014000000 | E11: ՏՂԱՄԱՐԴՈՒ ՎԵՐԱՐԿՈՒ ՔԻՄԻԱԿԱՆ ԹԵԼԵՐԻՑ | F11: վերարկու | G11: տղամարդու | H11: 1136 | I11: 1136 | J11: =I11/1000 -> 1.136 | K11: 1 | L11: PETROL | M11: China | N11: պոլիեսթեր
B12: 11 | C12: 40000001104 | D12: 62014000000 | E12: ՏՂԱՄԱՐԴՈՒ ՎԵՐԱՐԿՈՒ ՔԻՄԻԱԿԱՆ ԹԵԼԵՐԻՑ | F12: վերարկու | G12: տղամարդու | H12: 1194 | I12: 1194 | J12: =I12/1000 -> 1.194 | K12: 1 | L12: PETROL | M12: China | N12: պոլիեսթեր
B13: 12 | C13: 40000001103 | D13: 62014000000 | E13: ՏՂԱՄԱՐԴՈՒ ՎԵՐԱՐԿՈՒ ՔԻՄԻԱԿԱՆ ԹԵԼԵՐԻՑ | F13: վերարկու | G13: տղամարդու | H13: 1076 | I13: 1076 | J13: =I13/1000 -> 1.076 | K13: 1 | L13: PETROL | M13: China | N13: պոլիեսթեր
B14: 13 | C14: 40000001102 | D14: 62014000000 | E14: ՏՂԱՄԱՐԴՈՒ ՎԵՐԱՐԿՈՒ ՔԻՄԻԱԿԱՆ ԹԵԼԵՐԻՑ | F14: վերարկու | G14: տղամարդու | H14: 1038 | I14: 1038 | J14: =I14/1000 -> 1.038 | K14: 1 | L14: PETROL | M14: China | N14: պոլիեսթեր
B15: 14 | C15: 40000001101 | D15: 62024000010 | E15: ԿԱՆԱՑԻ ՎԵՐԱՐԿՈՒ ՔԻՄԻԱԿԱՆ ԹԵԼԵՐԻՑ | F15: վերարկու | G15: կին | H15: 1060 | I15: 1060 | J15: =I15/1000 -> 1.06 | K15: 1 | L15: TOMTAILOR | M15: Vietnam | N15: պոլիեսթեր
B16: 15 | C16: 40000001100 | D16: 61102091000 | E16: ՏՂԱՄԱՐԴՈՒ ՀՈՒԴԻՆԵՐ ԲԱՄԲԱԿԵ ՄԱՆՎԱԾՔԻՑ | F16: հուդի | G16: տղամարդու | H16: 926 | I16: 926 | J16: =I16/1000 -> 0.926 | K16: 1 | L16: CARHARTT | M16: Pakistan | N16: բամբակ/պոլիեսթեր
... B211: 210 | C211: 40000000905 | D211: 64039991000 | E211: ԱՂՋԿԱ ԲՈԿՈՏԻԿՆԵՐ ԲՆԱԿԱՆ ԿԱՇՎԵ ԵՐԵՍԱՄԱՍՈՎ , ՌԵՏԻՆԵ ԿՈՇԿԱՏԱԿՈՎ ՄԻՆՉԵՎ 24ՍՄ ՆԵՐԲԱՆԻ ԵՐԿԱՐՈՒԹՅԱՄԲ | F211: սանդալ մինչև 35 | G211: մանկական | H211: 256 | I211: 160 | J211: =I211/1000 -> 0.16 | K211: 1 | L211: CHICCO | M211: China | N211: տակը ռետին, վրան կաշի
B212: 211 | C212: 40000000904 | D212: 90041091000 | E212: ԱՐԵՎԱՊԱՇՏՊԱՆ ԱԿՆՈՑՆԵՐ ՏԵՍՈՂՈՒԹՅՈՒՆԸ ՉՇՏԿՈՂ ՈՉ ԹԱՆԿԱՐԺԵՔ ՄԵՏԱՂՆԵՐԻՑ, ՊԼԱՍՍՏՄԱՍՍԱՅԻՑ ՈՍՊՆՅԱԿՆԵՐՈՎ | F212: ակնոց | G212: կին | H212: 86 | I212: 86 | J212: =I212/1000 -> 0.086 | K212: 1 | L212: MONCLER | M212: Italy | N212: պլաստմաս
B213: 212 | C213: 40000000903 | D213: 61091000000 | E213: ԿԱՆԱՑԻ ՇԱՊԻԿՆԵՐ ԲԱՄԲԱԿԵ ՄԱՆՎԱԾՔԻՑ | F213: շապիկ | G213: կին | H213: 120 | I213: 120 | J213: =I213/1000 -> 0.12 | K213: 1 | L213: CAVALLI CLASS | M213: Bangladesh | N213: բամբակ
B214: 213 | C214: 40000000902 | D214: 61112090000 | E214: ՏՂԱ ԵՐԵԽԱՅԻ ԲՈԴԻ ԲԱՄԲԱԿԵ ՄԱՆՎԱԾՔԻՑ ՄԻՆՉԵՎ 86 ՍՄ ՀԱՍԱԿ ՈՒՆԵՑՈՂ 1 ՀԱՎԱՔԱԾՈՒ 2 ՀԱՏԻՑ | F214: բոդի մինչև 1 սեթ 2 | G214: մանկական | H214: 68 | I214: 68 | J214: =I214/1000 -> 0.068 | K214: 1 | L214: CHICCO | M214: India | N214: բամբակ
B215: 214 | C215: 40000000901 | D215: 61091000000 | E215: ԿԱՆԱՑԻ ՇԱՊԻԿՆԵՐ ԲԱՄԲԱԿԵ ՄԱՆՎԱԾՔԻՑ | F215: շապիկ | G215: կին | H215: 110 | I215: 110 | J215: =I215/1000 -> 0.11 | K215: 1 | L215: CAVALLI CLASS | M215: Bangladesh | N215: բամբակ
B216: 215 | C216: 40000000900 | D216: 64039991000 | E216: ՏՂԱՅԻ ՍՊՈՐՏԱՅԻՆ ՈՃԻ ԿՈՇԻԿ ԲՆԱԿԱՆ ԿԱՇՎԵ ԵՐԵՍԱՄԱՍՈՎ , ՌԵՏԻՆԵ ԿՈՇԿԱՏԱԿՈՎ ՄԻՆՉԵՎ 24ՍՄ ՆԵՐԲԱՆԻ ԵՐԿԱՐՈՒԹՅԱՄԲ | F216: կեդ մինչև 35 | G216: տղայի | H216: 278 | I216: 184 | J216: =I216/1000 -> 0.184 | K216: 1 | L216: CHICCO | M216: China | N216: տակը ռետին, վրան կաշի
B217: 216 | C217: 40000000899 | D217: 64039991000 | E217: ԱՂՋԿԱ ԿՈՇԻԿ ԲՆԱԿԱՆ ԿԱՇՎԵ ԵՐԵՍԱՄԱՍՈՎ , ՊՈԼԻՄԵՐԱՅԻՆ ԿՈՇԿԱՏԱԿՈՎ ՄԻՆՉԵՎ 24ՍՄ ՆԵՐԲԱՆԻ ԵՐԿԱՐՈՒԹՅԱՄԲ | F217: կոշիկ մինչև 35 | G217: աղջկա | H217: 30 | I217: 30 | J217: =I217/1000 -> 0.03 | K217: 1 | L217: CHICCO | M217: China | N217: տակը տեքստիլ, վրան կաշի
B218: 217 | C218: 40000000898 | D218: 64052099000 | E218: ՏՂԱՅԻ ԲՈԿՈՏԻԿ ՏԵՔՍԻԼԵ | F218: սանդալ մինչև 35 | G218: մանկական | H218: 36 | I218: 36 | J218: =I218/1000 -> 0.036 | K218: 1 | L218: CHICCO | M218: China | N218: կտոր
B219: 218 | C219: 40000000897 | D219: 64041990000 | E219: ԱՂՋԿԱ ԲՈԿՈՏԻԿՆԵՐ ՏԵՔՍԻԼԵ ԵՐԵՍԱՄԱՍՈՎ ՌԵՏԻՆԵ ԿՈՇԿԱՏԱԿՈՎ | F219: սանդալ մինչև 35 | G219: մանկական | H219: 332 | I219: 332 | J219: =I219/1000 -> 0.332 | K219: 1 | L219: CHICCO | M219: China | N219: տակը ռետին, վրան կտոր
B220: 219 | C220: 40000000896 | D220: 64041990000 | E220: ԱՂՋԿԱ ԲՈԿՈՏԻԿՆԵՐ ՏԵՔՍԻԼԵ ԵՐԵՍԱՄԱՍՈՎ ՌԵՏԻՆԵ ԿՈՇԿԱՏԱԿՈՎ | F220: սանդալ մինչև 35 | G220: մանկական | H220: 332 | I220: 332 | J220: =I220/1000 -> 0.332 | K220: 1 | L220: CHICCO | M220: China | N220: տակը ռետին, վրան կտոր
B221: 220 | C221: 40000000895 | D221: 64039116000 | E221: ՏՂԱՄԱՐԴՈՒ ԿԻՍԱՃՏՔԱՎՈՐ ԿՈՇԻԿՆԵՐ ԲՆԱԿԱՆ ԿԱՇՎԵ ԵՐԵՍԱՄԱՍՈՎ ՌԵՏԻՆԵ ԿՈՇԿԱՏԱԿՈՎ | F221: 35-ից բարձր կիսաճտքավոր կոշիկ | G221: տղամարդու | H221: 1650 | I221: 1340 | J221: =I221/1000 -> 1.34 | K221: 1 | L221: SALEVA | M221: Vietnam | N221: տակը ռետին, վրան կաշի
B222: 221 | C222: 40000000894 | D222: 64029998000 | E222: ԿԱՆԱՑԻ ՍՊՈՐՏԱՅԻՆ ՈՃԻ ԿՈՇԻԿ ԱՐՀԵՍՏԱԿԱՆ ԿԱՇՎԵ ԵՐԵՍԱՄԱՍՈՎ , ՊՈԼԻՄԵՐԱՅԻՆ ԿՈՇԿԱՏԱԿՈՎ | F222: կեդ 35-ից բարձր | G222: կին | H222: 684 | I222: 550 | J222: =I222/1000 -> 0.55 | K222: 1 | L222: KAPPA | M222: China | N222: տակը պոլիմեր, վրան արհեստական կաշի
B223: 222 | C223: 40000000893 | D223: 90041091000 | E223: ԱՐԵՎԱՊԱՇՏՊԱՆ ԱԿՆՈՑՆԵՐ ՏԵՍՈՂՈՒԹՅՈՒՆԸ ՉՇՏԿՈՂ ՈՉ ԹԱՆԿԱՐԺԵՔ ՄԵՏԱՂՆԵՐԻՑ, ՊԼԱՍՍՏՄԱՍՍԱՅԻՑ ՈՍՊՆՅԱԿՆԵՐՈՎ | F223: ակնոց | G223: կին | H223: 366 | I223: 366 | J223: =I223/1000 -> 0.366 | K223: 1 | L223: VIVIENNE WESTWOOD | M223: UK | N223: պլաստմաս
B224: 223 | C224: 40000000892 | D224: 90041091000 | E224: ԱՐԵՎԱՊԱՇՏՊԱՆ ԱԿՆՈՑՆԵՐ ՏԵՍՈՂՈՒԹՅՈՒՆԸ ՉՇՏԿՈՂ ՈՉ ԹԱՆԿԱՐԺԵՔ ՄԵՏԱՂՆԵՐԻՑ, ՊԼԱՍՍՏՄԱՍՍԱՅԻՑ ՈՍՊՆՅԱԿՆԵՐՈՎ | F224: ակնոց | G224: կին | H224: 350 | I224: 350 | J224: =I224/1000 -> 0.35 | K224: 1 | L224: VIVIENNE WESTWOOD | M224: UK | N224: պլաստմաս
B225: 224 | C225: 40000000891 | D225: 62023000000 | E225: ԿԱՆԱՑԻ ԲԱՃԿՈՆՆԵՐ ԲԱՄԲԱԿԵ ՄԱՆՎԱԾՔԻՑ | F225: բաճկոն | G225: կին | H225: 1238 | I225: 1238 | J225: =I225/1000 -> 1.238 | K225: 1 | L225: LIU.JO | M225: China | N225: բամբակ
B226: 225 | C226: 40000000890 | D226: 62014000000 | E226: ՏՂԱՄԱՐԴՈՒ ԲԱՃԿՈՆՆԵՐ ՔԻՄԻԱԿԱՆ ԹԵԼԵՐԻՑ | F226: բաճկոն | G226: տղամարդու | H226: 884 | I226: 884 | J226: =I226/1000 -> 0.884 | K226: 1 | L226: LIU.JO | M226: China | N226: պոլիեսթեր
B227: 226 | C227: 40000000889 | D227: 62014000000 | E227: ՏՂԱՄԱՐԴՈՒ ԲԱՃԿՈՆՆԵՐ ՔԻՄԻԱԿԱՆ ԹԵԼԵՐԻՑ | F227: բաճկոն | G227: տղամարդու | H227: 960 | I227: 960 | J227: =I227/1000 -> 0.96 | K227: 1 | L227: LIU.JO | M227: China | N227: պոլիեսթեր
B228: 227 | C228: 40000000888 | D228: 62014000000 | E228: ՏՂԱՄԱՐԴՈՒ ԲԱՃԿՈՆՆԵՐ ՔԻՄԻԱԿԱՆ ԹԵԼԵՐԻՑ | F228: բաճկոն | G228: տղամարդու | H228: 1044 | I228: 1044 | J228: =I228/1000 -> 1.044 | K228: 1 | L228: LIU.JO | M228: China | N228: պոլիեսթեր
B229: 228 | C229: 40000000887 | D229: 62014000000 | E229: ՏՂԱՄԱՐԴՈՒ ԲԱՃԿՈՆՆԵՐ ՔԻՄԻԱԿԱՆ ԹԵԼԵՐԻՑ | F229: բաճկոն | G229: տղամարդու | H229: 1010 | I229: 1010 | J229: =I229/1000 -> 1.01 | K229: 1 | L229: LIU.JO | M229: China | N229: պոլիեսթեր
B230: 229 | C230: 40000000886 | D230: 62014000000 | E230: ՏՂԱՄԱՐԴՈՒ ԲԱՃԿՈՆՆԵՐ ՔԻՄԻԱԿԱՆ ԹԵԼԵՐԻՑ | F230: բաճկոն | G230: տղամարդու | H230: 1088 | I230: 1088 | J230: =I230/1000 -> 1.088 | K230: 1 | L230: LIU.JO | M230: China | N230: պոլիեսթեր
B231: 230 | C231: 40000000885 | D231: 62014000000 | E231: ՏՂԱՄԱՐԴՈՒ ԲԱՃԿՈՆՆԵՐ ՔԻՄԻԱԿԱՆ ԹԵԼԵՐԻՑ | F231: բաճկոն | G231: տղամարդու | H231: 748 | I231: 748 | J231: =I231/1000 -> 0.748 | K231: 1 | L231: LIU.JO | M231: China | N231: պոլիեսթեր
B232: 231 | C232: 40000000884 | D232: 62014000000 | E232: ՏՂԱՄԱՐԴՈՒ ԲԱՃԿՈՆՆԵՐ ՔԻՄԻԱԿԱՆ ԹԵԼԵՐԻՑ | F232: բաճկոն | G232: տղամարդու | H232: 752 | I232: 752 | J232: =I232/1000 -> 0.752 | K232: 1 | L232: LIU.JO | M232: China | N232: պոլիեսթեր
B233: 232 | C233: 40000000883 | D233: 62014000000 | E233: ՏՂԱՄԱՐԴՈՒ ԲԱՃԿՈՆՆԵՐ ՔԻՄԻԱԿԱՆ ԹԵԼԵՐԻՑ | F233: բաճկոն | G233: տղամարդու | H233: 706 | I233: 706 | J233: =I233/1000 -> 0.706 | K233: 1 | L233: LIU.JO | M233: China | N233: պոլիեսթեր
B234: 233 | C234: 40000000882 | D234: 62023000000 | E234: ԿԱՆԱՑԻ ԲԱՃԿՈՆՆԵՐ ԲԱՄԲԱԿԵ ՄԱՆՎԱԾՔԻՑ | F234: բաճկոն | G234: կին | H234: 1148 | I234: 1148 | J234: =I234/1000 -> 1.148 | K234: 1 | L234: LIU.JO | M234: China | N234: բամբակ
B235: 234 | C235: 40000000881 | D235: 62023000000 | E235: ԿԱՆԱՑԻ ԲԱՃԿՈՆՆԵՐ ԲԱՄԲԱԿԵ ՄԱՆՎԱԾՔԻՑ | F235: բաճկոն | G235: կին | H235: 1148 | I235: 1148 | J235: =I235/1000 -> 1.148 | K235: 1 | L235: LIU.JO | M235: China | N235: բամբակ
B236: 235 | C236: 40000000880 | D236: 61102091000 | E236: ՏՂԱՄԱՐԴՈՒ ՍՎԻՏՐԵՐ ԲԱՄԲԱԿԵ ՄԱՆՎԱԾՔԻՑ | F236: սվիտեր | G236: տղամարդու | H236: 638 | I236: 638 | J236: =I236/1000 -> 0.638 | K236: 1 | L236: LIU.JO | M236: China | N236: բամբակ
... B841: 840 | C841: 40000000277 | D841: 61062000000 | E841: ԿԱՆԱՑԻ ԲԼՈՒԶՆԵՐ ՔԻՄԻԱԿԱՆ ԹԵԼԵՐԻՑ | F841: բլուզ | G841: կին | H841: 160 | I841: 160 | J841: =I841/1000 -> 0.16 | K841: 1 | L841: DE FACTO | M841: Turkey | N841: պոլիեսթեր
B842: 841 | C842: 40000000276 | D842: 61042300000 | E842: ԿԱՆԱՑԻ ՇԱՊԻԿ, ՏԱԲԱՏ ԵՎ ԳԼԽԱՐԿ ՍԻՆԹԵՏԻԿ ԹԵԼԵՐԻՑ | F842: սեթ 3 շապիկ + տաբատ + գլխարկ | G842: կին | H842: 404 | I842: 404 | J842: =I842/1000 -> 0.404 | K842: 3 set | L842: DE FACTO | M842: Turkey | N842: պոլիեսթեր
B843: 842 | C843: 40000000275 | D843: 61061000000 | E843: ԿԱՆԱՑԻ ՎԵՐՆԱՇԱՊԻԿՆԵՐ ԲԱՄԲԱԿԵ ՄԱՆՎԱԾՔԻՑ | F843: վերնաշապիկ | G843: կին | H843: 248 | I843: 248 | J843: =I843/1000 -> 0.248 | K843: 1 | L843: DE FACTO | M843: Bangladesh | N843: բամբակ
B844: 843 | C844: 40000000274 | D844: 61112090000 | E844: ՏՂԱ ԵՐԵԽԱՅԻ ԿԱՄԲԻՆԻԶՈՆՆԵՐ ԲԱՄԲԱԿԵ ՄԱՆՎԱԾՔԻՑ ՄԻՆՉԵՎ 86 ՍՄ ՀԱՍԱԿ ՈՒՆԵՑՈՂ | F844: մինչև 1 կոմբինեզոն | G844: տղայի | H844: 98 | I844: 98 | J844: =I844/1000 -> 0.098 | K844: 1 | L844: DE FACTO | M844: Turkey | N844: բամբակ
B845: 844 | C845: 40000000273 | D845: 62046990000 | E845: ԿԱՆԱՑԻ ՏԱԲԱՏՆԵՐ ԱՅԼ ՄԱՆԱԾԱԳՈՐԾԱԿԱՆ ՆՅՈՒԹԵՐԻՑ | F845: Տաբատ | G845: կին | H845: 354 | I845: 354 | J845: =I845/1000 -> 0.354 | K845: 1 | L845: DE FACTO | M845: Turkey | N845: վիսկոզ/բամբակ
B846: 845 | C846: 40000000272 | D846: 61062000000 | E846: ԿԱՆԱՑԻ ԲԼՈՒԶՆԵՐ ՔԻՄԻԱԿԱՆ ԹԵԼԵՐԻՑ | F846: բլուզ | G846: կին | H846: 86 | I846: 86 | J846: =I846/1000 -> 0.086 | K846: 1 | L846: DE FACTO | M846: Turkey | N846: պոլիեսթեր
B847: 846 | C847: 40000000271 | D847: 61061000000 | E847: ԿԱՆԱՑԻ ԲԼՈՒԶՆԵՐ ԲԱՄԲԱԿԵ ՄԱՆՎԱԾՔԻՑ | F847: բլուզ | G847: կին | H847: 260 | I847: 260 | J847: =I847/1000 -> 0.26 | K847: 1 | L847: DE FACTO | M847: Turkey | N847: բամբակ
B848: 847 | C848: 40000000270 | D848: 61091000000 | E848: ՏՂԱՄԱՐԴՈՒ ՇԱՊԻԿՆԵՐ ԲԱՄԲԱԿԵ ՄԱՆՎԱԾՔԻՑ | F848: շապիկ | G848: տղամարդու | H848: 178 | I848: 178 | J848: =I848/1000 -> 0.178 | K848: 1 | L848: DE FACTO | M848: Turkey | N848: բամբակ
B849: 848 | C849: 40000000269 | D849: 62046231000 | E849: ԿԱՆԱՑԻ ՋԻՆՍԵ ՏԱԲԱՏՆԵՐ ԲԱՄԲԱԿԵ ՄԱՆՎԱԾՔԻՑ | F849: ջինսե տաբատ | G849: կին | H849: 510 | I849: 510 | J849: =I849/1000 -> 0.51 | K849: 1 | L849: DE FACTO | M849: Bangladesh | N849: բամբակ
B850: 849 | C850: 40000000268 | D850: 61091000000 | E850: ՏՂԱՄԱՐԴՈՒ ՇԱՊԻԿՆԵՐ ԲԱՄԲԱԿԵ ՄԱՆՎԱԾՔԻՑ | F850: շապիկ | G850: տղամարդու | H850: 126 | I850: 126 | J850: =I850/1000 -> 0.126 | K850: 1 | L850: DE FACTO | M850: Turkey | N850: բամբակ
B851: 850 | C851: 40000000267 | D851: 62046231000 | E851: ԿԱՆԱՑԻ ՋԻՆՍԵ ՏԱԲԱՏՆԵՐ ԲԱՄԲԱԿԵ ՄԱՆՎԱԾՔԻՑ | F851: ջինսե տաբատ | G851: կին | H851: 676 | I851: 676 | J851: =I851/1000 -> 0.676 | K851: 1 | L851: DE FACTO | M851: Turkey | N851: բամբակ
B852: 851 | C852: 40000000266 | D852: 61103099000 | E852: ԿԱՆԱՑԻ ՍՎԻՏՐԵՐ ՔԻՄԱԿԱՆ ԹԵԼԵՐԻՑ | F852: սվիտեր | G852: կին | H852: 266 | I852: 266 | J852: =I852/1000 -> 0.266 | K852: 1 | L852: DE FACTO | M852: Turkey | N852: պոլիեսթեր
B853: 852 | C853: 40000000265 | D853: 61061000000 | E853: ԿԱՆԱՑԻ ԲԼՈՒԶՆԵՐ ԲԱՄԲԱԿԵ ՄԱՆՎԱԾՔԻՑ | F853: բլուզ | G853: կին | H853: 142 | I853: 142 | J853: =I853/1000 -> 0.142 | K853: 1 | L853: DE FACTO | M853: Bangladesh | N853: բամբակ
B854: 853 | C854: 40000000264 | D854: 62046231000 | E854: ԿԱՆԱՑԻ ՋԻՆՍԵ ՏԱԲԱՏՆԵՐ ԲԱՄԲԱԿԵ ՄԱՆՎԱԾՔԻՑ | F854: ջինսե տաբատ | G854: կին | H854: 544 | I854: 544 | J854: =I854/1000 -> 0.544 | K854: 1 | L854: DE FACTO | M854: Bangladesh | N854: բամբակ
... B918: 917 | C918: 60000000503 | D918: 62121090000 | E918: ԿՐԾԿԱԼՆԵՐ ՍԻՆԹԵՏԻԿ ԹԵԼԵՐԻՑ | F918: կրծկալ | G918: կին | H918: 40 | I918: 40 | J918: =I918/1000 -> 0.04 | K918: 1 | L918: ASOS | M918: China | N918: էլաստան/պոլիեսթեր
B919: 918 | C919: 60000000504 | D919: 90041091000 | E919: ԱՐԵՎԱՊԱՇՏՊԱՆ ԱԿՆՈՑՆԵՐ ՏԵՍՈՂՈՒԹՅՈՒՆԸ ՉՇՏԿՈՂ ՈՉ ԹԱՆԿԱՐԺԵՔ ՄԵՏԱՂՆԵՐԻՑ, ՊԼԱՍՍՏՄԱՍՍԱՅԻՑ ՈՍՊՆՅԱԿՆԵՐՈՎ | F919: ակնոց | G919: յունիսեքս | H919: 28 | I919: 28 | J919: =I919/1000 -> 0.028 | K919: 1 | L919: ASOS | M919: China | N919: պլաստմաս
B920: 919 | C920: 60000000505 | D920: 61069090000 | E920: ԿԱՆԱՑԻ ԲԼՈՒԶՆԵՐ ԱՅԼ ՄԱՆԱԾԱԳՈՐԾԱԿԱՆ ՆՅՈՒԹԵՐԻՑ | F920: բլուզ | G920: կին | H920: 296 | I920: 296 | J920: =I920/1000 -> 0.296 | K920: 1 | L920: ASOS | M920: India | N920: վիսկոզ
B921: 920 | C921: 60000000506 | D921: 61044300000 | E921: ԿԱՆԱՑԻ ՇՐՋԱԶԳԵՍՏՆԵՐ ՍԻՆԹԵՏԻԿ ԹԵԼԵՐԻՑ | F921: զգեստ | G921: կին | H921: 182 | I921: 182 | J921: =I921/1000 -> 0.182 | K921: 1 | L921: ASOS | M921: India | N921: պոլիեսթեր
B922: 921 | C922: 60000000507 | D922: 61044200000 | E922: ԿԱՆԱՑԻ ՇՐՋԱԶԳԵՍՏՆԵՐ ԲԱՄԲԱԿԵ ՄԱՆՎԱԾՔԻՑ | F922: զգեստ | G922: կին | H922: 250 | I922: 250 | J922: =I922/1000 -> 0.25 | K922: 1 | L922: ASOS | M922: Turkey | N922: բամբակ
B923: 922 | C923: 60000000508 | D923: 61062000000 | E923: ԿԱՆԱՑԻ ԲԼՈՒԶՆԵՐ ՔԻՄԻԱԿԱՆ ԹԵԼԵՐԻՑ | F923: բլուզ | G923: կին | H923: 132 | I923: 132 | J923: =I923/1000 -> 0.132 | K923: 1 | L923: ASOS | M923: Romania | N923: պոլիեսթեր
B924: 923 | C924: 60000000509 | D924: 61062000000 | E924: ԿԱՆԱՑԻ ԲԼՈՒԶՆԵՐ ՔԻՄԻԱԿԱՆ ԹԵԼԵՐԻՑ | F924: բլուզ | G924: կին | H924: 138 | I924: 138 | J924: =I924/1000 -> 0.138 | K924: 1 | L924: ASOS | M924: Romania | N924: պոլիեսթեր/վիսկոզ
B925: 924 | C925: 60000000510 | D925: 61045300000 | E925: ԿԱՆԱՑԻ ԿԻՍԱՇՐՋԱԶԳԵՍՏՆԵՐ ՍԻՆԹԵՏԻԿ ԹԵԼԵՐԻՑ | F925: կիսաշրջազգեստ | G925: կին | H925: 96 | I925: 96 | J925: =I925/1000 -> 0.096 | K925: 1 | L925: ASOS | M925: Albania | N925: էլաստան/պոլիեսթեր
B926: 925 | C926: 60000000511 | D926: 61099020000 | E926: ԿԱՆԱՑԻ ՏՈՊ-ՇԱՊԻԿՆԵՐ ՔԻՄԻԱԿԱՆ ԹԵԼԵՐԻՑ | F926: տոպ | G926: կին | H926: 102 | I926: 102 | J926: =I926/1000 -> 0.102 | K926: 1 | L926: ASOS | M926: Turkey | N926: էլաստան/բամբուկ
B927: 926 | C927: 60000000512 | D927: 61044300000 | E927: ԿԱՆԱՑԻ ՇՐՋԱԶԳԵՍՏՆԵՐ ՍԻՆԹԵՏԻԿ ԹԵԼԵՐԻՑ | F927: զգեստ | G927: կին | H927: 214 | I927: 214 | J927: =I927/1000 -> 0.214 | K927: 1 | L927: ASOS | M927: India | N927: պոլիեսթեր
B928: 927 | C928: 60000000513 | D928: 61091000000 | E928: ԿԱՆԱՑԻ ՏՈՊ -ՇԱՊԻԿՆԵՐ ԲԱՄԲԱԿԵ ՄԱՆՎԱԾՔԻՑ | F928: տոպ | G928: կին | H928: 106 | I928: 106 | J928: =I928/1000 -> 0.106 | K928: 1 | L928: ASOS | M928: Turkey | N928: բամբակ
B929: 928 | C929: 60000000514 | D929: 61044300000 | E929: ԿԱՆԱՑԻ ՇՐՋԱԶԳԵՍՏՆԵՐ ՍԻՆԹԵՏԻԿ ԹԵԼԵՐԻՑ | F929: զգեստ | G929: կին | H929: 114 | I929: 114 | J929: =I929/1000 -> 0.114 | K929: 1 | L929: ASOS | M929: India | N929: պոլիեսթեր
B930: 929 | C930: 60000000515 | D930: 61046200000 | E930: ԿԱՆԱՑԻ ՇՈՐՏԵՐ ԲԱՄԲԱԿԵ ՄԱՆՎԱԾՔԻՑ | F930: շորտ | G930: կին | H930: 198 | I930: 198 | J930: =I930/1000 -> 0.198 | K930: 1 | L930: ASOS | M930: Turkey | N930: բամբակ
B931: 930 | C931: 60000000516 | D931: 61099020000 | E931: ԿԱՆԱՑԻ ՏՈՊ-ՇԱՊԻԿՆԵՐ ՔԻՄԻԱԿԱՆ ԹԵԼԵՐԻՑ | F931: տոպ | G931: կին | H931: 102 | I931: 102 | J931: =I931/1000 -> 0.102 | K931: 1 | L931: ASOS | M931: Romania | N931: էլաստան/պոլիեսթեր
... B1022: 1021 | C1022: 60000000372 | D1022: 61069090000 | E1022: ԿԱՆԱՑԻ ԲԼՈՒԶՆԵՐ ԱՅԼ ՄԱՆԱԾԱԳՈՐԾԱԿԱՆ ՆՅՈՒԹԵՐԻՑ | F1022: բլուզ | G1022: կին | H1022: 176 | I1022: 176 | J1022: =I1022/1000 -> 0.176 | K1022: 1 | L1022: MISS SELFRIDGE | M1022: Morocco | N1022: վիսկոզ
B1023: 1022 | C1023: 60000000368 | D1023: 90041091000 | E1023: ԱՐԵՎԱՊԱՇՏՊԱՆ ԱԿՆՈՑՆԵՐ ՏԵՍՈՂՈՒԹՅՈՒՆԸ ՉՇՏԿՈՂ ՈՉ ԹԱՆԿԱՐԺԵՔ ՄԵՏԱՂՆԵՐԻՑ, ՊԼԱՍՍՏՄԱՍՍԱՅԻՑ ՈՍՊՆՅԱԿՆԵՐՈՎ | F1023: ակնոց | G1023: յունիսեքս | H1023: 34 | I1023: 34 | J1023: =I1023/1000 -> 0.034 | K1023: 1 | L1023: ASOS | M1023: China | N1023: պլաստմաս
B1024: 1023 | C1024: 60000000409 | D1024: 61059090000 | E1024: ՏՂԱՄԱՐԴՈՒ ՎԵՐՆԱՇԱՊԻԿՆԵՐ ԱՅԼ ՄԱՆԱԾԱԳՈՐԾԱԿԱՆ ՆՅՈՒԹԵՐԻՑ | F1024: վերնաշապիկ | G1024: տղամարդու | H1024: 178 | I1024: 178 | J1024: =I1024/1000 -> 0.178 | K1024: 1 | L1024: ASOS | M1024: Turkey | N1024: վիսկոզ
B1025: 1024 | C1025: 60000000395 | D1025: 61044300000 | E1025: ԿԱՆԱՑԻ ՇՐՋԱԶԳԵՍՏՆԵՐ ՍԻՆԹԵՏԻԿ ԹԵԼԵՐԻՑ | F1025: զգեստ | G1025: կին | H1025: 96 | I1025: 96 | J1025: =I1025/1000 -> 0.096 | K1025: 1 | L1025: COLLUSION | M1025: UK | N1025: նիլոն
B1026: 1025 | C1026: 60000000394 | D1026: 61044300000 | E1026: ԿԱՆԱՑԻ ՇՐՋԱԶԳԵՍՏՆԵՐ ՍԻՆԹԵՏԻԿ ԹԵԼԵՐԻՑ | F1026: զգեստ | G1026: կին | H1026: 244 | I1026: 244 | J1026: =I1026/1000 -> 0.244 | K1026: 1 | L1026: ASOS | M1026: Tunis | N1026: պոլիեսթեր
B1027: 1026 | C1027: 60000000367 | D1027: 61051000000 | E1027: ՏՂԱՄԱՐԴՈՒ ՎԵՐՆԱՇԱՊԻԿՆԵՐ ԲԱՄԲԱԿԵ ՄԱՆՎԱԾՔԻՑ | F1027: վերնաշապիկ | G1027: տղամարդու | H1027: 222 | I1027: 222 | J1027: =I1027/1000 -> 0.222 | K1027: 1 | L1027: COLLUSION | M1027: Turkey | N1027: բամբակ
B1028: 1027 | C1028: 60000000365 | D1028: 61091000000 | E1028: ԿԱՆԱՑԻ ՏՈՊ -ՇԱՊԻԿՆԵՐ ԲԱՄԲԱԿԵ ՄԱՆՎԱԾՔԻՑ | F1028: տոպ | G1028: կին | H1028: 86 | I1028: 86 | J1028: =I1028/1000 -> 0.086 | K1028: 1 | L1028: PUMA | M1028: China | N1028: բամբակ
B1029: 1028 | C1029: 60000000362 | D1029: 61044300000 | E1029: ԿԱՆԱՑԻ ՇՐՋԱԶԳԵՍՏՆԵՐ ՍԻՆԹԵՏԻԿ ԹԵԼԵՐԻՑ | F1029: զգեստ | G1029: կին | H1029: 200 | I1029: 200 | J1029: =I1029/1000 -> 0.2 | K1029: 1 | L1029: ASOS | M1029: India | N1029: պոլիեսթեր
B1030: 1029 | C1030: 60000000363 | D1030: 61044200000 | E1030: ԿԱՆԱՑԻ ՇՐՋԱԶԳԵՍՏՆԵՐ ԲԱՄԲԱԿԵ ՄԱՆՎԱԾՔԻՑ | F1030: զգեստ | G1030: կին | H1030: 196 | I1030: 196 | J1030: =I1030/1000 -> 0.196 | K1030: 1 | L1030: INFLUENCE | M1030: India | N1030: բամբակ
B1031: 1030 | C1031: 60000000366 | D1031: 42022210000 | E1031: ԿԱՆԱՑԻ ՊԱՅՈՒՍԱԿ ԱՐՀԵՍՏԱԿԱՆ ԿԱՇՎԻՑ | F1031: պայուսակ | G1031: կին | H1031: 312 | I1031: 312 | J1031: =I1031/1000 -> 0.312 | K1031: 1 | L1031: MANGO | M1031: China | N1031: պոլիուրեթան
B1032: 1031 | C1032: 60000000371 | D1032: 61059090000 | E1032: ՏՂԱՄԱՐԴՈՒ ՎԵՐՆԱՇԱՊԻԿՆԵՐ ԱՅԼ ՄԱՆԱԾԱԳՈՐԾԱԿԱՆ ՆՅՈՒԹԵՐԻՑ | F1032: վերնաշապիկ | G1032: տղամարդու | H1032: 154 | I1032: 154 | J1032: =I1032/1000 -> 0.154 | K1032: 1 | L1032: COLLUSION | M1032: China | N1032: վիսկոզ
B1033: 1032 | C1033: 60000000370 | D1033: 61044300000 | E1033: ԿԱՆԱՑԻ ՇՐՋԱԶԳԵՍՏՆԵՐ ՍԻՆԹԵՏԻԿ ԹԵԼԵՐԻՑ | F1033: զգեստ | G1033: կին | H1033: 206 | I1033: 206 | J1033: =I1033/1000 -> 0.206 | K1033: 1 | L1033: MOTEL | M1033: China | N1033: պոլիեսթեր
B1034: 1033 | C1034: 60000000416 | D1034: 62023000000 | E1034: ԿԱՆԱՑԻ ԲԱՃԿՈՆՆԵՐ ԲԱՄԲԱԿԵ ՄԱՆՎԱԾՔԻՑ | F1034: բաճկոն | G1034: կին | H1034: 876 | I1034: 876 | J1034: =I1034/1000 -> 0.876 | K1034: 1 | L1034: COLLUSION | M1034: Turkey | N1034: բամբակ
B1035: 1034 | C1035: 60000000369 | D1035: 61044300000 | E1035: ԿԱՆԱՑԻ ՇՐՋԱԶԳԵՍՏՆԵՐ ՍԻՆԹԵՏԻԿ ԹԵԼԵՐԻՑ | F1035: զգեստ | G1035: կին | H1035: 178 | I1035: 178 | J1035: =I1035/1000 -> 0.178 | K1035: 1 | L1035: VIOLET ROMANCE | M1035: India | N1035: պոլիեսթեր
... B1089: 1088 | C1089: 60000000319 | D1089: 61044300000 | E1089: ԿԱՆԱՑԻ ՇՐՋԱԶԳԵՍՏՆԵՐ ՍԻՆԹԵՏԻԿ ԹԵԼԵՐԻՑ | F1089: զգեստ | G1089: կին | H1089: 200 | I1089: 200 | J1089: =I1089/1000 -> 0.2 | K1089: 1 | L1089: INFLUENCE | M1089: India | N1089: պոլիեսթեր
B1090: 1089 | C1090: 60000000320 | D1090: 90041091000 | E1090: ԱՐԵՎԱՊԱՇՏՊԱՆ ԱԿՆՈՑՆԵՐ ՏԵՍՈՂՈՒԹՅՈՒՆԸ ՉՇՏԿՈՂ ՈՉ ԹԱՆԿԱՐԺԵՔ ՄԵՏԱՂՆԵՐԻՑ, ՊԼԱՍՍՏՄԱՍՍԱՅԻՑ ՈՍՊՆՅԱԿՆԵՐՈՎ | F1090: արևային ակնոց | G1090: յունիսեքս | H1090: 30 | I1090: 30 | J1090: =I1090/1000 -> 0.03 | K1090: 1 | L1090: ASOS | M1090: China | N1090: պլաստմաս
B1091: 1090 | C1091: 60000000318 | D1091: 61124190000 | E1091: ԿԱՆԱՑԻ ԼՈՂԱԶԳԵՍՏՆԵՐ ՍԻՆԹԵՏԻԿ ԹԵԼԵՐԻՑ | F1091: լողազգեստ | G1091: կին | H1091: 86 | I1091: 86 | J1091: =I1091/1000 -> 0.086 | K1091: 1 | L1091: THREADBARE | M1091: Bangladesh | N1091: պոլիամիդ
B1092: 1091 | C1092: 60000000317 | D1092: 61099020000 | E1092: ԿԱՆԱՑԻ ՏՈՊ-ՇԱՊԻԿՆԵՐ ՔԻՄԻԱԿԱՆ ԹԵԼԵՐԻՑ | F1092: տոպ | G1092: կին | H1092: 80 | I1092: 80 | J1092: =I1092/1000 -> 0.08 | K1092: 1 | L1092: LALA MAY | M1092: China | N1092: պոլիեսթեր
B1093: 1092 | C1093: 60000000316 | D1093: 61083200000 | E1093: ԿԱՆԱՑԻ ԳԻՇԵՐԱԶԳԵՍՏ ՔԻՄԻԱԿԱՆ ԹԵԼԵՐԻՑ | F1093: գիշերազգեստ | G1093: կին | H1093: 122 | I1093: 122 | J1093: =I1093/1000 -> 0.122 | K1093: 1 | L1093: FRECNH CONNECTION | M1093: China | N1093: պոլիեսթեր
B1094: 1093 | C1094: 60000000315 | D1094: 61124190000 | E1094: ԿԱՆԱՑԻ ԼՈՂԱԶԳԵՍՏՆԵՐ ՍԻՆԹԵՏԻԿ ԹԵԼԵՐԻՑ | F1094: լողազգեստ | G1094: կին | H1094: 98 | I1094: 98 | J1094: =I1094/1000 -> 0.098 | K1094: 1 | L1094: THREADBARE | M1094: Bangladesh | N1094: պոլիամիդ
B1095: 1094 | C1095: 60000000314 | D1095: 61044200000 | E1095: ԿԱՆԱՑԻ ՇՐՋԱԶԳԵՍՏՆԵՐ ԲԱՄԲԱԿԵ ՄԱՆՎԱԾՔԻՑ | F1095: զգեստ | G1095: կին | H1095: 240 | I1095: 240 | J1095: =I1095/1000 -> 0.24 | K1095: 1 | L1095: ASOS | M1095: India | N1095: բամբակ
B1096: 1095 | C1096: 60000000313 | D1096: 61044200000 | E1096: ԿԱՆԱՑԻ ՇՐՋԱԶԳԵՍՏՆԵՐ ԲԱՄԲԱԿԵ ՄԱՆՎԱԾՔԻՑ | F1096: զգեստ | G1096: կին | H1096: 264 | I1096: 264 | J1096: =I1096/1000 -> 0.264 | K1096: 1 | L1096: ASOS | M1096: India | N1096: բամբակ
B1097: 1096 | C1097: 60000000312 | D1097: 61044300000 | E1097: ԿԱՆԱՑԻ ՇՐՋԱԶԳԵՍՏՆԵՐ ՍԻՆԹԵՏԻԿ ԹԵԼԵՐԻՑ | F1097: զգեստ | G1097: կին | H1097: 88 | I1097: 88 | J1097: =I1097/1000 -> 0.088 | K1097: 1 | L1097: COLLUSION | M1097: UK | N1097: նիլոն
B1098: 1097 | C1098: 60000000311 | D1098: 61044300000 | E1098: ԿԱՆԱՑԻ ՇՐՋԱԶԳԵՍՏՆԵՐ ՍԻՆԹԵՏԻԿ ԹԵԼԵՐԻՑ | F1098: զգեստ | G1098: կին | H1098: 202 | I1098: 202 | J1098: =I1098/1000 -> 0.202 | K1098: 1 | L1098: BRAVE SOUL | M1098: China | N1098: պոլիեսթեր
B1099: 1098 | C1099: 60000000310 | D1099: 61045200000 | E1099: ԿԱՆԱՑԻ ԿԻՍԱՇՐՋԱԶԳԵՍՏՆԵՐ ԲԱՄԲԱԿԵ ՄԱՆՎԱԾՔԻՑ | F1099: կիսաշրջազգեստ | G1099: կին | H1099: 60 | I1099: 60 | J1099: =I1099/1000 -> 0.06 | K1099: 1 | L1099: ASOS | M1099: India | N1099: բամբակ
B1100: 1099 | C1100: 60000000309 | D1100: 61044300000 | E1100: ԿԱՆԱՑԻ ՇՐՋԱԶԳԵՍՏՆԵՐ ՍԻՆԹԵՏԻԿ ԹԵԼԵՐԻՑ | F1100: զգեստ | G1100: կին | H1100: 110 | I1100: 110 | J1100: =I1100/1000 -> 0.11 | K1100: 1 | L1100: WILD LOVERS | M1100: China | N1100: պոլիեսթեր
B1101: 1100 | C1101: 60000000308 | D1101: 61091000000 | E1101: ԿԱՆԱՑԻ ՏՈՊ -ՇԱՊԻԿՆԵՐ ԲԱՄԲԱԿԵ ՄԱՆՎԱԾՔԻՑ | F1101: տոպ | G1101: կին | H1101: 56 | I1101: 56 | J1101: =I1101/1000 -> 0.056 | K1101: 1 | L1101: COLLUSION | M1101: Bangladesh | N1101: բամբակ
B1102: 1101 | C1102: 60000000307 | D1102: 61091000000 | E1102: ԿԱՆԱՑԻ ՏՈՊ -ՇԱՊԻԿՆԵՐ ԲԱՄԲԱԿԵ ՄԱՆՎԱԾՔԻՑ | F1102: տոպ | G1102: կին | H1102: 58 | I1102: 58 | J1102: =I1102/1000 -> 0.058 | K1102: 1 | L1102: COLLUSION | M1102: Bangladesh | N1102: բամբակ
... B1319: 1318 | C1319: 60000000668 | D1319: 64029998000 | E1319: ԿԱՆԱՑԻ ԲՈԿՈՏԻԿ ԱՐՀԵՍՏԱԿԱՆ ԿԱՇՎԵ ԵՐԵՍԱՄԱՍՈՎ , ՊՈԼԻՄԵՐԱՅԻՆ ԿՈՇԿԱՏԱԿՈՎ | F1319: 35-ից բարձր սանդալ | G1319: կին | H1319: 660 | I1319: 660 | J1319: =I1319/1000 -> 0.66 | K1319: 1 | L1319: ASOS | M1319: China | N1319: ակացու պոլիմեր
B1320: 1319 | C1320: 60000000669 | D1320: 90041091000 | E1320: ԱՐԵՎԱՊԱՇՏՊԱՆ ԱԿՆՈՑՆԵՐ ՏԵՍՈՂՈՒԹՅՈՒՆԸ ՉՇՏԿՈՂ ՈՉ ԹԱՆԿԱՐԺԵՔ ՄԵՏԱՂՆԵՐԻՑ, ՊԼԱՍՍՏՄԱՍՍԱՅԻՑ ՈՍՊՆՅԱԿՆԵՐՈՎ | F1320: արևային ակնոց | G1320: կին | H1320: 44 | I1320: 44 | J1320: =I1320/1000 -> 0.044 | K1320: 1 | L1320: ASOS | M1320: EU | N1320: պլաստմաս
...

Sheet RE (2)
A1: N | B1: Code | C1: HS code | D1: name | E1: Sub-category | F1: Sub-category | G1: Sub-category id | H1: Gender | I1: Gender id | J1: Netto | K1: Brutto | L1: pc | M1: Brand | N1: Brand id | O1: Country | P1: Country id | Q1: Country | R1: Material | S1: Material | T1: Material id | U1: Package | V1: Package Id | W1: Size | X1: Size id | Y1: Original price | Z1: Color | AA1: Color id
A2: 1 | B2: 60000001980 | C2: 62046239000 | D2: ԿԱՆԱՑԻ ԵՎ ԱՂՋԿԱ ՏԱԲԱՏՆԵՐ ԲԱՄԲԱԿԵ ՄԱՆՎԱԾՔԻՑ | E2: =PROPER(F2) -> Տաբատներ | F2: տաբատներ | G2: =VLOOKUP(E2,subcategory!A:B,2,0) -> 93 | H2: աղջկա | I2: =VLOOKUP(H2,gender!A:B,2,0) -> #N/A | J2: 125 | K2: 125 | L2: 1 | M2: CHICCO | N2: =VLOOKUP(M2,brand!A:B,2,0) -> 608 | O2: =UPPER(Q2) -> BANGLADESH | P2: =VLOOKUP(O2,country!A:B,2,0) -> 7485 | Q2: BANGLADESH | R2: =PROPER(S2) -> Բամբակ | S2: բամբակ | T2: =VLOOKUP(R2,material!A:B,2,0) -> 9 | U2: chicco | W2: 6տ. | X2: =VLOOKUP(W2,SIZE!A:B,2,0) -> #N/A | Y2: 10,99 | Z2: կապույտ | AA2: =VLOOKUP(Z2,COLOR!A:B,2,0) -> 5
A3: 2 | B3: 60000001978 | C3: 61046200000 | D3: ԱՂՋԿԱ ՇՈՐՏԵՐ ԲԱՄԲԱԿԵ ՄԱՆՎԱԾՔԻՑ | E3: =PROPER(F3) -> Շորտ | F3: շորտ | G3: =VLOOKUP(E3,subcategory!A:B,2,0) -> 24 | H3: աղջկա | I3: =VLOOKUP(H3,gender!A:B,2,0) -> #N/A | J3: 55 | K3: 55 | L3: 1 | M3: CHICCO | N3: =VLOOKUP(M3,brand!A:B,2,0) -> 608 | O3: =UPPER(Q3) -> BANGLADESH | P3: =VLOOKUP(O3,country!A:B,2,0) -> 7485 | Q3: BANGLADESH | R3: =PROPER(S3) -> Բամբակ | S3: բամբակ | T3: =VLOOKUP(R3,material!A:B,2,0) -> 9 | U3: chicco | W3: 4տ. | X3: =VLOOKUP(W3,SIZE!A:B,2,0) -> #N/A | Y3: 9,99 | Z3: սև | AA3: =VLOOKUP(Z3,COLOR!A:B,2,0) -> 20
A4: 3 | B4: 40000001949 | C4: 64041990000 | D4: ՏՂԱՅԻ ԿԻՍԱՃՏՔԱՎՈՐ ԿՈՇԻԿՆԵՐ ՏԵՔՏՍԻԼԵ ԵՐԵՍԱՄԱՍՈՎ ՌԵՏԻՆԵ ԿՈՇԿԱՏԱԿՈՎ | E4: =PROPER(F4) -> Սպորտ Կիսաճտքավոր | F4: սպորտ կիսաճտքավոր | G4: =VLOOKUP(E4,subcategory!A:B,2,0) -> #N/A | H4: տղա | I4: =VLOOKUP(H4,gender!A:B,2,0) -> #N/A | J4: 735 | K4: 735 | L4: 1 | M4: LD | N4: =VLOOKUP(M4,brand!A:B,2,0) -> #N/A | O4: =UPPER(Q4) -> GERMANY | P4: =VLOOKUP(O4,country!A:B,2,0) -> 1725 | Q4: GERMANY | R4: =PROPER(S4) -> Ռեզին, Պոլիեսթեր | S4: ռեզին, պոլիեսթեր | T4: =VLOOKUP(R4,material!A:B,2,0) -> #N/A | U4: ALDY | W4: 35 | X4: =VLOOKUP(W4,SIZE!A:B,2,0) -> 217 | Y4: 0 | Z4: կապույտ | AA4: =VLOOKUP(Z4,COLOR!A:B,2,0) -> 5
A5: 4 | B5: 40000001947 | C5: 64041990000 | D5: ՏՂԱՅԻ ԿԻՍԱՃՏՔԱՎՈՐ ԿՈՇԻԿՆԵՐ ՏԵՔՏՍԻԼԵ ԵՐԵՍԱՄԱՍՈՎ ՌԵՏԻՆԵ ԿՈՇԿԱՏԱԿՈՎ | E5: =PROPER(F5) -> Սպորտ Կիսաճտքավոր | F5: սպորտ կիսաճտքավոր | G5: =VLOOKUP(E5,subcategory!A:B,2,0) -> #N/A | H5: տղա | I5: =VLOOKUP(H5,gender!A:B,2,0) -> #N/A | J5: 460 | K5: 460 | L5: 1 | M5: LILY & DAN | N5: =VLOOKUP(M5,brand!A:B,2,0) -> #N/A | O5: =UPPER(Q5) -> GERMANY | P5: =VLOOKUP(O5,country!A:B,2,0) -> 1725 | Q5: GERMANY | R5: =PROPER(S5) -> Ռեզին, Պոլիեսթեր | S5: ռեզին, պոլիեսթեր | T5: =VLOOKUP(R5,material!A:B,2,0) -> #N/A | U5: ALDY | W5: 26 | X5: =VLOOKUP(W5,SIZE!A:B,2,0) -> 484 | Y5: 0 | Z5: կապույտ | AA5: =VLOOKUP(Z5,COLOR!A:B,2,0) -> 5
A6: 5 | B6: 60000004127 | C6: 61103099000 | D6: ԿԱՆԱՑԻ ՍՎԻՏՐԵՐ ՔԻՄԱԿԱՆ ԹԵԼԵՐԻՑ | E6: =PROPER(F6) -> Սվիտրեր | F6: Սվիտրեր | G6: =VLOOKUP(E6,subcategory!A:B,2,0) -> 88 | H6: կին | I6: =VLOOKUP(H6,gender!A:B,2,0) -> #N/A | J6: 434 | K6: 434 | L6: 1 | M6: DEFACTO | N6: =VLOOKUP(M6,brand!A:B,2,0) -> 823 | O6: =UPPER(Q6) -> TURKEY | P6: =VLOOKUP(O6,country!A:B,2,0) -> 1840 | Q6: TURKEY | R6: =PROPER(S6) -> 72% Ակրիլ, 24% Պոլիեսթեր, 4% Վիսկոզ | S6: 72% ակրիլ, 24% պոլիեսթեր, 4% վիսկոզ | T6: =VLOOKUP(R6,material!A:B,2,0) -> #N/A | U6: DEFACTO | W6: XL | X6: =VLOOKUP(W6,SIZE!A:B,2,0) -> 124 | Y6: 0 | Z6: բեժ | AA6: =VLOOKUP(Z6,COLOR!A:B,2,0) -> #N/A
A7: 6 | B7: 60000004105 | C7: 61044300000 | D7: ԿԱՆԱՑԻ ԵՎ ԱՂՋԿԱ ՇՐՋԱԶԳԵՍՏՆԵՐ ՍԻՆԹԵՏԻԿ ԹԵԼԵՐԻՑ | E7: =PROPER(F7) -> Զգեստ | F7: զգեստ | G7: =VLOOKUP(E7,subcategory!A:B,2,0) -> 43 | H7: կին | I7: =VLOOKUP(H7,gender!A:B,2,0) -> #N/A | J7: 448 | K7: 448 | L7: 1 | M7: DEFACTO | N7: =VLOOKUP(M7,brand!A:B,2,0) -> 823 | O7: =UPPER(Q7) -> TURKEY | P7: =VLOOKUP(O7,country!A:B,2,0) -> 1840 | Q7: TURKEY | R7: =PROPER(S7) -> 76% Պոլիեսթեր, 24% Բամբակ | S7: 76% պոլիեսթեր, 24% բամբակ | T7: =VLOOKUP(R7,material!A:B,2,0) -> #N/A | U7: DEFACTO | W7: XL | X7: =VLOOKUP(W7,SIZE!A:B,2,0) -> 124 | Y7: 0 | Z7: բեժ | AA7: =VLOOKUP(Z7,COLOR!A:B,2,0) -> #N/A
A8: 7 | B8: 60000003774 | C8: 61061000000 | D8: ԿԱՆԱՑԻ ԵՎ ԱՂՋԿԱ ԲԼՈՒԶՆԵՐ ԲԱՄԲԱԿԵ ՄԱՆՎԱԾՔԻՑ | E8: =PROPER(F8) -> Բլուզ | F8: բլուզ | G8: =VLOOKUP(E8,subcategory!A:B,2,0) -> 77 | H8: կին | I8: =VLOOKUP(H8,gender!A:B,2,0) -> #N/A | J8: 172 | K8: 172 | L8: 1 | M8: DEFACTO | N8: =VLOOKUP(M8,brand!A:B,2,0) -> 823 | O8: =UPPER(Q8) -> TURKEY | P8: =VLOOKUP(O8,country!A:B,2,0) -> 1840 | Q8: TURKEY | R8: =PROPER(S8) -> 53% Պոլիեսթեր, 27% Վիսկոզա | S8: 53% պոլիեսթեր, 27% վիսկոզա | T8: =VLOOKUP(R8,material!A:B,2,0) -> #N/A | U8: DEFACTO | W8: S | X8: =VLOOKUP(W8,SIZE!A:B,2,0) -> 122 | Y8: 0 | Z8: սև | AA8: =VLOOKUP(Z8,COLOR!A:B,2,0) -> 20
A9: 8 | B9: 60000003786 | C9: 62034319000 | D9: ՏՂԱՄԱՐԴՈՒ ԵՎ ՏՂԱՅԻ ՏԱԲԱՏՆԵՐ ՍԻՆԹԵՏԻԿ ԹԵԼԵՐԻՑ | E9: =PROPER(F9) -> Տաբատներ | F9: տաբատներ | G9: =VLOOKUP(E9,subcategory!A:B,2,0) -> 93 | H9: տղամարդու | I9: =VLOOKUP(H9,gender!A:B,2,0) -> #N/A | J9: 490 | K9: 490 | L9: 1 | M9: DEFACTO | N9: =VLOOKUP(M9,brand!A:B,2,0) -> 823 | O9: =UPPER(Q9) -> TURKEY | P9: =VLOOKUP(O9,country!A:B,2,0) -> 1840 | Q9: TURKEY | R9: =PROPER(S9) -> 55% Պոլիամիդ, 45% Բամբակ | S9: 55% պոլիամիդ, 45% բամբակ | T9: =VLOOKUP(R9,material!A:B,2,0) -> #N/A | U9: DEFACTO | W9: S | X9: =VLOOKUP(W9,SIZE!A:B,2,0) -> 122 | Y9: 0 | Z9: մուգ կապույտ | AA9: =VLOOKUP(Z9,COLOR!A:B,2,0) -> 25
A10: 9 | B10: 60000003754 | C10: 61042300000 | D10: ԿԱՆԱՑԻ ՏՈՊ ԻՐ ԳԼԽԱՐԿՈՎ ՍԻՆԹԵՏԻԿ ԹԵԼԵՐԻՑ | E10: =PROPER(F10) -> Տոպ+Գլխարկ | F10: տոպ+գլխարկ | G10: =VLOOKUP(E10,subcategory!A:B,2,0) -> 481 | H10: կին | I10: =VLOOKUP(H10,gender!A:B,2,0) -> #N/A | J10: 102 | K10: 102 | L10: 1 | M10: DEFACTO | N10: =VLOOKUP(M10,brand!A:B,2,0) -> 823 | O10: =UPPER(Q10) -> TURKEY | P10: =VLOOKUP(O10,country!A:B,2,0) -> 1840 | Q10: TURKEY | R10: =PROPER(S10) -> 100% Պոլիեսթեր | S10: 100% պոլիեսթեր | T10: =VLOOKUP(R10,material!A:B,2,0) -> #N/A | U10: DEFACTO | W10: S | X10: =VLOOKUP(W10,SIZE!A:B,2,0) -> 122 | Y10: 0 | Z10: մուգ կապույտ | AA10: =VLOOKUP(Z10,COLOR!A:B,2,0) -> 25
A11: 10 | B11: 60000003792 | C11: 61103091000 | D11: ՏՂԱՄԱՐԴՈՒ ՍՎԻՏԵՐ-ՎՈԴՈԼԱԶԿԱ ՍԻՆԹԵՏԻԿ ԹԵԼԵՐԻՑ | E11: =PROPER(F11) -> Սվիտեր Վդ․ | F11: սվիտեր վդ․ | G11: =VLOOKUP(E11,subcategory!A:B,2,0) -> #N/A | H11: տղամարդու | I11: =VLOOKUP(H11,gender!A:B,2,0) -> #N/A | J11: 296 | K11: 296 | L11: 1 | M11: DEFACTO | N11: =VLOOKUP(M11,brand!A:B,2,0) -> 823 | O11: =UPPER(Q11) -> TURKEY | P11: =VLOOKUP(O11,country!A:B,2,0) -> 1840 | Q11: TURKEY | R11: =PROPER(S11) -> 100% Ակրիլ | S11: 100% ակրիլ | T11: =VLOOKUP(R11,material!A:B,2,0) -> #N/A | U11: DEFACTO | W11: XL | X11: =VLOOKUP(W11,SIZE!A:B,2,0) -> 124 | Y11: 0 | Z11: բեժ | AA11: =VLOOKUP(Z11,COLOR!A:B,2,0) -> #N/A
A12: 11 | B12: 60000003788 | C12: 62071100000 | D12: ՏՂԱՄԱՐԴՈՒ ՎԱՐՏԻՔՆԵՐ ԲԱՄԲԱԿԵ ՄԱՆՎԱԾՔԻՑ ՀԱՎԱՔԱԾՈՒ 3 ՀԱՏԻՑ | E12: =PROPER(F12) -> Վարտիկ Սեթ 3Հատ | F12: վարտիկ սեթ 3հատ | G12: =VLOOKUP(E12,subcategory!A:B,2,0) -> #N/A | H12: տղամարդու | I12: =VLOOKUP(H12,gender!A:B,2,0) -> #N/A | J12: 224 | K12: 224 | L12: 1 | M12: DEFACTO | N12: =VLOOKUP(M12,brand!A:B,2,0) -> 823 | O12: =UPPER(Q12) -> BANGLADESH | P12: =VLOOKUP(O12,country!A:B,2,0) -> 7485 | Q12: BANGLADESH | R12: =PROPER(S12) -> 100% Բամբակ | S12: 100% բամբակ | T12: =VLOOKUP(R12,material!A:B,2,0) -> #N/A | U12: DEFACTO | W12: XL | X12: =VLOOKUP(W12,SIZE!A:B,2,0) -> 124 | Y12: 0 | Z12: գույնզգույն | AA12: =VLOOKUP(Z12,COLOR!A:B,2,0) -> 17
A13: 12 | B13: 60000003797 | C13: 62024000010 | D13: ԿԱՆԱՑԻ ՎԵՐԱՐԿՈՒ ՔԻՄԻԱԿԱՆ ԹԵԼԵՐԻՑ | E13: =PROPER(F13) -> Վերարկու | F13: վերարկու | G13: =VLOOKUP(E13,subcategory!A:B,2,0) -> 92 | H13: կին | I13: =VLOOKUP(H13,gender!A:B,2,0) -> #N/A | J13: 1534 | K13: 1534 | L13: 1 | M13: DEFACTO | N13: =VLOOKUP(M13,brand!A:B,2,0) -> 823 | O13: =UPPER(Q13) -> MYANMAR | P13: =VLOOKUP(O13,country!A:B,2,0) -> 7495 | Q13: MYANMAR | R13: =PROPER(S13) -> 100% Պոլիեսթեր | S13: 100% պոլիեսթեր | T13: =VLOOKUP(R13,material!A:B,2,0) -> #N/A | U13: DEFACTO | W13: XL | X13: =VLOOKUP(W13,SIZE!A:B,2,0) -> 124 | Y13: 0 | Z13: սև | AA13: =VLOOKUP(Z13,COLOR!A:B,2,0) -> 20
A14: 13 | B14: 40000001659 | C14: 61091000000 | D14: ԿԱՆԱՑԻ ԵՎ ԱՂՋԿԱ ՇԱՊԻԿՆԵՐ ԲԱՄԲԱԿԵ ՄԱՆՎԱԾՔԻՑ | E14: =PROPER(F14) -> Կարճաթև Շապիկ | F14: Կարճաթև շապիկ | G14: =VLOOKUP(E14,subcategory!A:B,2,0) -> 22 | H14: կին | I14: =VLOOKUP(H14,gender!A:B,2,0) -> #N/A | J14: 135 | K14: 135 | L14: 1 | M14: DEFACTO | N14: =VLOOKUP(M14,brand!A:B,2,0) -> 823 | O14: =UPPER(Q14) -> TURKEY | P14: =VLOOKUP(O14,country!A:B,2,0) -> 1840 | Q14: TURKEY | R14: =PROPER(S14) -> 100% Բամբակ | S14: 100% բամբակ | T14: =VLOOKUP(R14,material!A:B,2,0) -> #N/A | U14: DEFACTO | W14: M | X14: =VLOOKUP(W14,SIZE!A:B,2,0) -> 119 | Y14: 0 | Z14: սև | AA14: =VLOOKUP(Z14,COLOR!A:B,2,0) -> 20
A15: 14 | B15: 40000001654 | C15: 62034235000 | D15: ՏՂԱՄԱՐԴՈՒ ՏԱԲԱՏՆԵՐ ԲԱՄԲԱԿԵ ՄԱՆՎԱԾՔԻՑ | E15: =PROPER(F15) -> Տաբատներ | F15: տաբատներ | G15: =VLOOKUP(E15,subcategory!A:B,2,0) -> 93 | H15: տղամարդու | I15: =VLOOKUP(H15,gender!A:B,2,0) -> #N/A | J15: 245 | K15: 245 | L15: 1 | M15: DEFACTO | N15: =VLOOKUP(M15,brand!A:B,2,0) -> 823 | O15: =UPPER(Q15) -> TURKEY | P15: =VLOOKUP(O15,country!A:B,2,0) -> 1840 | Q15: TURKEY | R15: =PROPER(S15) -> 100% Բամբակ | S15: 100% բամբակ | T15: =VLOOKUP(R15,material!A:B,2,0) -> #N/A | U15: DEFACTO | W15: 30 | X15: =VLOOKUP(W15,SIZE!A:B,2,0) -> 22 | Y15: 0 | Z15: կրեմագույն | AA15: =VLOOKUP(Z15,COLOR!A:B,2,0) -> 16
A16: 15 | B16: 40000001636 | C16: 61091000000 | D16: ԿԱՆԱՑԻ ԵՎ ԱՂՋԿԱ ԵՐԿԱՐԱԹԵՎ ՇԱՊԻԿՆԵՐ ԲԱՄԲԱԿԵ ՄԱՆՎԱԾՔԻՑ | E16: =PROPER(F16) -> Երկարաթև Շապիկ | F16: երկարաթև շապիկ | G16: =VLOOKUP(E16,subcategory!A:B,2,0) -> 21 | H16: կին | I16: =VLOOKUP(H16,gender!A:B,2,0) -> #N/A | J16: 130 | K16: 130 | L16: 1 | M16: DEFACTO | N16: =VLOOKUP(M16,brand!A:B,2,0) -> 823 | O16: =UPPER(Q16) -> BANGLADESH | P16: =VLOOKUP(O16,country!A:B,2,0) -> 7485 | Q16: BANGLADESH | R16: =PROPER(S16) -> 95% Բամբակ, 5% Էլաստան | S16: 95% բամբակ, 5% էլաստան | T16: =VLOOKUP(R16,material!A:B,2,0) -> #N/A | U16: DEFACTO | W16: S | X16: =VLOOKUP(W16,SIZE!A:B,2,0) -> 122 | Y16: 0 | Z16: մոխրագույն | AA16: =VLOOKUP(Z16,COLOR!A:B,2,0) -> 8
A17: 16 | B17: 40000001632 | C17: 62046239000 | D17: ԿԱՆԱՑԻ ՏԱԲԱՏՆԵՐ ԲԱՄԲԱԿԵ ՄԱՆՎԱԾՔԻՑ | E17: =PROPER(F17) -> Տաբատներ | F17: տաբատներ | G17: =VLOOKUP(E17,subcategory!A:B,2,0) -> 93 | H17: կին | I17: =VLOOKUP(H17,gender!A:B,2,0) -> #N/A | J17: 255 | K17: 255 | L17: 1 | M17: DEFACTO | N17: =VLOOKUP(M17,brand!A:B,2,0) -> 823 | O17: =UPPER(Q17) -> TURKEY | P17: =VLOOKUP(O17,country!A:B,2,0) -> 1840 | Q17: TURKEY | R17: =PROPER(S17) -> 26% Պոլիեսթեր, 70% Բամբակ | S17: 26% պոլիեսթեր, 70% բամբակ | T17: =VLOOKUP(R17,material!A:B,2,0) -> #N/A | U17: DEFACTO | W17: 36 | X17: =VLOOKUP(W17,SIZE!A:B,2,0) -> 52 | Y17: 0 | Z17: երկանգույն | AA17: =VLOOKUP(Z17,COLOR!A:B,2,0) -> #N/A
A18: 17 | B18: 40000002134 | C18: 61112090000 | D18: ՏՂԱ ԵՐԵԽԱՅԻ ՇԱՊԻԿ ԻՐ ՏԱԲԱՏՈՎ ԲԱՄԲԱԿԵ ՄԱՆՎԱԾՔԻՑ ՄԻՆՉԵՎ 86 ՍՄ ՀԱՍԱԿ ՈՒՆԵՑՈՂ | E18: =PROPER(F18) -> Շապիկ+Տաբատ | F18: շապիկ+տաբատ | G18: =VLOOKUP(E18,subcategory!A:B,2,0) -> #N/A | H18: նորածին տղա | I18: =VLOOKUP(H18,gender!A:B,2,0) -> 7 | J18: 100 | K18: 100 | L18: 1 | M18: CHICCO | N18: =VLOOKUP(M18,brand!A:B,2,0) -> 608 | O18: =UPPER(Q18) -> CHINA | P18: =VLOOKUP(O18,country!A:B,2,0) -> 7497 | Q18: CHINA | R18: =PROPER(S18) -> Բամբակ | S18: բամբակ | T18: =VLOOKUP(R18,material!A:B,2,0) -> 9 | U18: chicco | W18: 1ամիս | X18: =VLOOKUP(W18,SIZE!A:B,2,0) -> #N/A | Y18: 0 | Z18: սպիտակ | AA18: =VLOOKUP(Z18,COLOR!A:B,2,0) -> 12
A19: 18 | B19: 40000002133 | C19: 61112090000 | D19: ԱՂՋԻԿ ԵՐԵԽԱՅԻ ԲԱՃԿՈՆ ԲԱՄԲԱԿԵ ՄԱՆՎԱԾՔԻՑ ՄԻՆՉԵՎ 86 ՍՄ ՀԱՍԱԿ ՈՒՆԵՑՈՂ | E19: =PROPER(F19) -> Բաճկոն | F19: բաճկոն | G19: =VLOOKUP(E19,subcategory!A:B,2,0) -> 14 | H19: նորածին աղջկա | I19: =VLOOKUP(H19,gender!A:B,2,0) -> #N/A | J19: 115 | K19: 115 | L19: 1 | M19: CHICCO | N19: =VLOOKUP(M19,brand!A:B,2,0) -> 608 | O19: =UPPER(Q19) -> INDIA | P19: =VLOOKUP(O19,country!A:B,2,0) -> 7505 | Q19: INDIA | R19: =PROPER(S19) -> Բամբակ | S19: բամբակ | T19: =VLOOKUP(R19,material!A:B,2,0) -> 9 | U19: chicco | W19: 6ամիս | X19: =VLOOKUP(W19,SIZE!A:B,2,0) -> #N/A | Y19: 29.99 | Z19: Վարդագույն | AA19: =VLOOKUP(Z19,COLOR!A:B,2,0) -> 13
A20: 19 | B20: 40000002132 | C20: 61142000000 | D20: ՏՂԱՅԻ ԲՈԴԻՆԵՐ ԲԱՄԲԱԿԵ ՄԱՆՎԱԾՔԻՑ | E20: =PROPER(F20) -> Բոդի | F20: բոդի | G20: =VLOOKUP(E20,subcategory!A:B,2,0) -> 15 | H20: տղա | I20: =VLOOKUP(H20,gender!A:B,2,0) -> #N/A | J20: 235 | K20: 235 | L20: 1 | M20: CHICCO | N20: =VLOOKUP(M20,brand!A:B,2,0) -> 608 | O20: =UPPER(Q20) -> CHINA | P20: =VLOOKUP(O20,country!A:B,2,0) -> 7497 | Q20: CHINA | R20: =PROPER(S20) -> Բամբակ | S20: բամբակ | T20: =VLOOKUP(R20,material!A:B,2,0) -> 9 | U20: chicco | W20: 18ամիս | X20: =VLOOKUP(W20,SIZE!A:B,2,0) -> #N/A | Y20: 29.99 | Z20: կարմիր | AA20: =VLOOKUP(Z20,COLOR!A:B,2,0) -> 1
A21: 20 | B21: 40000002131 | C21: 62034235000 | D21: ՏՂԱՄԱՐԴՈՒ ԵՎ ՏՂԱՅԻ ՏԱԲԱՏՆԵՐ ԲԱՄԲԱԿԵ ՄԱՆՎԱԾՔԻՑ | E21: =PROPER(F21) -> Տաբատներ | F21: տաբատներ | G21: =VLOOKUP(E21,subcategory!A:B,2,0) -> 93 | H21: տղա | I21: =VLOOKUP(H21,gender!A:B,2,0) -> #N/A | J21: 115 | K21: 115 | L21: 1 | M21: CHICCO | N21: =VLOOKUP(M21,brand!A:B,2,0) -> 608 | O21: =UPPER(Q21) -> BANGLADESH | P21: =VLOOKUP(O21,country!A:B,2,0) -> 7485 | Q21: BANGLADESH | R21: =PROPER(S21) -> Բամբակ | S21: բամբակ | T21: =VLOOKUP(R21,material!A:B,2,0) -> 9 | U21: chicco | W21: 18ամիս | X21: =VLOOKUP(W21,SIZE!A:B,2,0) -> #N/A | Y21: 10.99 | Z21: կապույտ | AA21: =VLOOKUP(Z21,COLOR!A:B,2,0) -> 5
A22: 21 | B22: 40000002130 | C22: 61044200000 | D22: ԱՂՋԿԱ ՇՐՋԱԶԳԵՍՏՆԵՐ ԲԱՄԲԱԿԵ ՄԱՆՎԱԾՔԻՑ | E22: =PROPER(F22) -> Զգեստ | F22: զգեստ | G22: =VLOOKUP(E22,subcategory!A:B,2,0) -> 43 | H22: աղջկա | I22: =VLOOKUP(H22,gender!A:B,2,0) -> #N/A | J22: 110 | K22: 110 | L22: 1 | M22: CHICCO | N22: =VLOOKUP(M22,brand!A:B,2,0) -> 608 | O22: =UPPER(Q22) -> INDIA | P22: =VLOOKUP(O22,country!A:B,2,0) -> 7505 | Q22: INDIA | R22: =PROPER(S22) -> Բամբակ | S22: բամբակ | T22: =VLOOKUP(R22,material!A:B,2,0) -> 9 | U22: chicco | W22: 15ամիս | X22: =VLOOKUP(W22,SIZE!A:B,2,0) -> #N/A | Y22: 0 | Z22: սպիտակ | AA22: =VLOOKUP(Z22,COLOR!A:B,2,0) -> 12
A23: 22 | B23: 40000002129 | C23: 61091000000 | D23: ՏՂԱՅԻ ՇԱՊԻԿՆԵՐ ԲԱՄԲԱԿԵ ՄԱՆՎԱԾՔԻՑ | E23: =PROPER(F23) -> Շապիկ | F23: շապիկ | G23: =VLOOKUP(E23,subcategory!A:B,2,0) -> 73 | H23: տղա | I23: =VLOOKUP(H23,gender!A:B,2,0) -> #N/A | J23: 55 | K23: 55 | L23: 1 | M23: CHICCO | N23: =VLOOKUP(M23,brand!A:B,2,0) -> 608 | O23: =UPPER(Q23) -> BANGLADESH | P23: =VLOOKUP(O23,country!A:B,2,0) -> 7485 | Q23: BANGLADESH | R23: =PROPER(S23) -> Բամբակ | S23: բամբակ | T23: =VLOOKUP(R23,material!A:B,2,0) -> 9 | U23: chicco | W23: 18ամիս | X23: =VLOOKUP(W23,SIZE!A:B,2,0) -> #N/A | Y23: 12.99 | Z23: սպիտակ | AA23: =VLOOKUP(Z23,COLOR!A:B,2,0) -> 12
A24: 23 | B24: 40000002128 | C24: 61044200000 | D24: ԱՂՋԿԱ ՇՐՋԱԶԳԵՍՏՆԵՐ ԲԱՄԲԱԿԵ ՄԱՆՎԱԾՔԻՑ | E24: =PROPER(F24) -> Զգեստ | F24: զգեստ | G24: =VLOOKUP(E24,subcategory!A:B,2,0) -> 43 | H24: աղջկա | I24: =VLOOKUP(H24,gender!A:B,2,0) -> #N/A | J24: 140 | K24: 140 | L24: 1 | M24: CHICCO | N24: =VLOOKUP(M24,brand!A:B,2,0) -> 608 | O24: =UPPER(Q24) -> INDIA | P24: =VLOOKUP(O24,country!A:B,2,0) -> 7505 | Q24: INDIA | R24: =PROPER(S24) -> Բամբակ | S24: բամբակ | T24: =VLOOKUP(R24,material!A:B,2,0) -> 9 | U24: chicco | W24: 6տ | X24: =VLOOKUP(W24,SIZE!A:B,2,0) -> #N/A | Y24: 0 | Z24: սպիտակ | AA24: =VLOOKUP(Z24,COLOR!A:B,2,0) -> 12
A25: 24 | B25: 40000002127 | C25: 61112090000 | D25: ԱՂՋԻԿ ԵՐԵԽԱՅԻ ՇՐՋԱԶԳԵՍՏՆԵՐ ԲԱՄԲԱԿԵ ՄԱՆՎԱԾՔԻՑ ՄԻՆՉԵՎ 86 ՍՄ ՀԱՍԱԿ ՈՒՆԵՑՈՂ | E25: =PROPER(F25) -> Զգեստ | F25: զգեստ | G25: =VLOOKUP(E25,subcategory!A:B,2,0) -> 43 | H25: նորածին աղջկա | I25: =VLOOKUP(H25,gender!A:B,2,0) -> #N/A | J25: 95 | K25: 95 | L25: 1 | M25: CHICCO | N25: =VLOOKUP(M25,brand!A:B,2,0) -> 608 | O25: =UPPER(Q25) -> INDIA | P25: =VLOOKUP(O25,country!A:B,2,0) -> 7505 | Q25: INDIA | R25: =PROPER(S25) -> Բամբակ | S25: բամբակ | T25: =VLOOKUP(R25,material!A:B,2,0) -> 9 | U25: chicco | W25: 9ամիս | X25: =VLOOKUP(W25,SIZE!A:B,2,0) -> #N/A | Y25: 0 | Z25: սպիտակ | AA25: =VLOOKUP(Z25,COLOR!A:B,2,0) -> 12
A26: 25 | B26: 40000002126 | C26: 61112090000 | D26: ԱՂՋԻԿ ԵՐԵԽԱՅԻ ՇԱՊԻԿՆԵՐ ԲԱՄԲԱԿԵ ՄԱՆՎԱԾՔԻՑ ՄԻՆՉԵՎ 86 ՍՄ ՀԱՍԱԿ ՈՒՆԵՑՈՂ | E26: =PROPER(F26) -> Շապիկ | F26: շապիկ | G26: =VLOOKUP(E26,subcategory!A:B,2,0) -> 73 | H26: նորածին աղջկա | I26: =VLOOKUP(H26,gender!A:B,2,0) -> #N/A | J26: 59 | K26: 59 | L26: 1 | M26: CHICCO | N26: =VLOOKUP(M26,brand!A:B,2,0) -> 608 | O26: =UPPER(Q26) -> INDIA | P26: =VLOOKUP(O26,country!A:B,2,0) -> 7505 | Q26: INDIA | R26: =PROPER(S26) -> Բամբակ | S26: բամբակ | T26: =VLOOKUP(R26,material!A:B,2,0) -> 9 | U26: chicco | W26: 6ամիս | X26: =VLOOKUP(W26,SIZE!A:B,2,0) -> #N/A | Y26: 22.99 | Z26: սպիտակ | AA26: =VLOOKUP(Z26,COLOR!A:B,2,0) -> 12
A27: 26 | B27: 40000002125 | C27: 61102099000 | D27: ԱՂՋԿԱ ՍՎԻՏՉՐԵՐ ԲԱՄԲԱԿԵ ԱՆՎԱԾՔԻՑ | E27: =PROPER(F27) -> Սվիտեր | F27: սվիտեր | G27: =VLOOKUP(E27,subcategory!A:B,2,0) -> #N/A | H27: աղջկա | I27: =VLOOKUP(H27,gender!A:B,2,0) -> #N/A | J27: 240 | K27: 240 | L27: 1 | M27: CHICCO | N27: =VLOOKUP(M27,brand!A:B,2,0) -> 608 | O27: =UPPER(Q27) -> INDIA | P27: =VLOOKUP(O27,country!A:B,2,0) -> 7505 | Q27: INDIA | R27: =PROPER(S27) -> Բամբակ | S27: բամբակ | T27: =VLOOKUP(R27,material!A:B,2,0) -> 9 | U27: chicco | W27: 9-10տ | X27: =VLOOKUP(W27,SIZE!A:B,2,0) -> #N/A | Y27: 0 | Z27: Վարդագույն | AA27: =VLOOKUP(Z27,COLOR!A:B,2,0) -> 13
A28: 27 | B28: 40000002124 | C28: 62046239000 | D28: ԱՂՋԿԱ ՏԱԲԱՏՆԵՐ ԲԱՄԲԱԿԵ ՄԱՆՎԱԾՔԻՑ | E28: =PROPER(F28) -> Տաբատներ | F28: տաբատներ | G28: =VLOOKUP(E28,subcategory!A:B,2,0) -> 93 | H28: աղջկա | I28: =VLOOKUP(H28,gender!A:B,2,0) -> #N/A | J28: 140 | K28: 140 | L28: 1 | M28: CHICCO | N28: =VLOOKUP(M28,brand!A:B,2,0) -> 608 | O28: =UPPER(Q28) -> INDIA | P28: =VLOOKUP(O28,country!A:B,2,0) -> 7505 | Q28: INDIA | R28: =PROPER(S28) -> Բամբակ | S28: բամբակ | T28: =VLOOKUP(R28,material!A:B,2,0) -> 9 | U28: chicco | W28: 9-10տ | X28: =VLOOKUP(W28,SIZE!A:B,2,0) -> #N/A | Y28: 0 | Z28: կապույտ | AA28: =VLOOKUP(Z28,COLOR!A:B,2,0) -> 5
A29: 28 | B29: 40000002123 | C29: 61044200000 | D29: ԱՂՋԿԱ ՇՐՋԱԶԳԵՍՏՆԵՐ ԲԱՄԲԱԿԵ ՄԱՆՎԱԾՔԻՑ | E29: =PROPER(F29) -> Զգեստ | F29: զգեստ | G29: =VLOOKUP(E29,subcategory!A:B,2,0) -> 43 | H29: աղջկա | I29: =VLOOKUP(H29,gender!A:B,2,0) -> #N/A | J29: 105 | K29: 105 | L29: 1 | M29: CHICCO | N29: =VLOOKUP(M29,brand!A:B,2,0) -> 608 | O29: =UPPER(Q29) -> INDIA | P29: =VLOOKUP(O29,country!A:B,2,0) -> 7505 | Q29: INDIA | R29: =PROPER(S29) -> Բամբակ | S29: բամբակ | T29: =VLOOKUP(R29,material!A:B,2,0) -> 9 | U29: chicco | W29: 2տ | X29: =VLOOKUP(W29,SIZE!A:B,2,0) -> #N/A | Y29: 35.99 | Z29: սպիտակ | AA29: =VLOOKUP(Z29,COLOR!A:B,2,0) -> 12
... A103: 102 | B103: 60000002256 | C103: 62046239000 | D103: ԿԱՆԱՑԻ ԵՎ ԱՂՋԿԱ ՏԱԲԱՏՆԵՐ ԲԱՄԲԱԿԵ ՄԱՆՎԱԾՔԻՑ | E103: =PROPER(F103) -> Տաբատներ | F103: տաբատներ | G103: =VLOOKUP(E103,subcategory!A:B,2,0) -> 93 | H103: աղջկա | I103: =VLOOKUP(H103,gender!A:B,2,0) -> #N/A | J103: 105 | K103: 105 | L103: 1 | M103: CHICCO | N103: =VLOOKUP(M103,brand!A:B,2,0) -> 608 | O103: =UPPER(Q103) -> BANGLADESH | P103: =VLOOKUP(O103,country!A:B,2,0) -> 7485 | Q103: BANGLADESH | R103: =PROPER(S103) -> Բամբակ | S103: Բամբակ | T103: =VLOOKUP(R103,material!A:B,2,0) -> 9 | U103: chicco | W103: 2տ | X103: =VLOOKUP(W103,SIZE!A:B,2,0) -> #N/A | Y103: 0 | Z103: վարդագույն | AA103: =VLOOKUP(Z103,COLOR!A:B,2,0) -> 13
A104: 103 | B104: 60000002255 | C104: 62114210000 | D104: ԱՂՋԿԱ ԳՈԳՆՈՑՆԵՐ ԲԱՄԲԱԿԵ ՄԱՆՎԱԾՔԻՑ | E104: =PROPER(F104) -> Գոգնոց | F104: գոգնոց | G104: =VLOOKUP(E104,subcategory!A:B,2,0) -> 285 | H104: աղջկա | I104: =VLOOKUP(H104,gender!A:B,2,0) -> #N/A | J104: 90 | K104: 90 | L104: 1 | M104: CHICCO | N104: =VLOOKUP(M104,brand!A:B,2,0) -> 608 | O104: =UPPER(Q104) -> CHINA | P104: =VLOOKUP(O104,country!A:B,2,0) -> 7497 | Q104: CHINA | R104: =PROPER(S104) -> Բամբակ | S104: Բամբակ | T104: =VLOOKUP(R104,material!A:B,2,0) -> 9 | U104: chicco | W104: 0 | X104: =VLOOKUP(W104,SIZE!A:B,2,0) -> 4 | Y104: 9.99 | Z104: սպիտակ | AA104: =VLOOKUP(Z104,COLOR!A:B,2,0) -> 12
A105: 104 | B105: 60000002254 | C105: 61046200000 | D105: ԱՂՋԿԱ ՇՈՐՏԵՐ ԲԱՄԲԱԿԵ ՄԱՆՎԱԾՔԻՑ | E105: =PROPER(F105) -> Շորտ | F105: շորտ | G105: =VLOOKUP(E105,subcategory!A:B,2,0) -> 24 | H105: աղջկա | I105: =VLOOKUP(H105,gender!A:B,2,0) -> #N/A | J105: 60 | K105: 60 | L105: 1 | M105: CHICCO | N105: =VLOOKUP(M105,brand!A:B,2,0) -> 608 | O105: =UPPER(Q105) -> BANGLADESH | P105: =VLOOKUP(O105,country!A:B,2,0) -> 7485 | Q105: BANGLADESH | R105: =PROPER(S105) -> Բամբակ | S105: Բամբակ | T105: =VLOOKUP(R105,material!A:B,2,0) -> 9 | U105: chicco | W105: 4տ | X105: =VLOOKUP(W105,SIZE!A:B,2,0) -> #N/A | Y105: 9.99 | Z105: կանաչ | AA105: =VLOOKUP(Z105,COLOR!A:B,2,0) -> 4
A106: 105 | B106: 60000002253 | C106: 61046200000 | D106: ԱՂՋԿԱ ՇՈՐՏԵՐ ԲԱՄԲԱԿԵ ՄԱՆՎԱԾՔԻՑ | E106: =PROPER(F106) -> Շորտ | F106: շորտ | G106: =VLOOKUP(E106,subcategory!A:B,2,0) -> 24 | H106: աղջկա | I106: =VLOOKUP(H106,gender!A:B,2,0) -> #N/A | J106: 40 | K106: 40 | L106: 1 | M106: CHICCO | N106: =VLOOKUP(M106,brand!A:B,2,0) -> 608 | O106: =UPPER(Q106) -> BANGLADESH | P106: =VLOOKUP(O106,country!A:B,2,0) -> 7485 | Q106: BANGLADESH | R106: =PROPER(S106) -> Բամբակ | S106: Բամբակ | T106: =VLOOKUP(R106,material!A:B,2,0) -> 9 | U106: chicco | W106: 18ամիս | X106: =VLOOKUP(W106,SIZE!A:B,2,0) -> #N/A | Y106: 0 | Z106: վարդագույն | AA106: =VLOOKUP(Z106,COLOR!A:B,2,0) -> 13
A107: 106 | B107: 60000002252 | C107: 61159500000 | D107: ՏՂԱՅԻ ԳՈՒԼՊԱՆԵՐ ԲԱՄԲԱԿԵ ՄԱՆՎԱԾՔԻՑ ՀԱՎԱՔԱԾՈՒ 2 ԶՈՒՅԳԻՑ | E107: =PROPER(F107) -> Գուլպա 2Զույգ | F107: գուլպա 2զույգ | G107: =VLOOKUP(E107,subcategory!A:B,2,0) -> #N/A | H107: տղա | I107: =VLOOKUP(H107,gender!A:B,2,0) -> #N/A | J107: 25 | K107: 25 | L107: 1 | M107: CHICCO | N107: =VLOOKUP(M107,brand!A:B,2,0) -> 608 | O107: =UPPER(Q107) -> CHINA | P107: =VLOOKUP(O107,country!A:B,2,0) -> 7497 | Q107: CHINA | R107: =PROPER(S107) -> Բամբակ | S107: Բամբակ | T107: =VLOOKUP(R107,material!A:B,2,0) -> 9 | U107: chicco | W107: 1-3տ | X107: =VLOOKUP(W107,SIZE!A:B,2,0) -> #N/A | Y107: 9.99 | Z107: երկնագույն | AA107: =VLOOKUP(Z107,COLOR!A:B,2,0) -> #N/A
A108: 107 | B108: 60000002251 | C108: 61046200000 | D108: ԱՂՋԿԱ ՇՈՐՏԵՐ ԲԱՄԲԱԿԵ ՄԱՆՎԱԾՔԻՑ | E108: =PROPER(F108) -> Շորտ | F108: շորտ | G108: =VLOOKUP(E108,subcategory!A:B,2,0) -> 24 | H108: աղջկա | I108: =VLOOKUP(H108,gender!A:B,2,0) -> #N/A | J108: 50 | K108: 50 | L108: 1 | M108: CHICCO | N108: =VLOOKUP(M108,brand!A:B,2,0) -> 608 | O108: =UPPER(Q108) -> BANGLADESH | P108: =VLOOKUP(O108,country!A:B,2,0) -> 7485 | Q108: BANGLADESH | R108: =PROPER(S108) -> Բամբակ | S108: բամբակ | T108: =VLOOKUP(R108,material!A:B,2,0) -> 9 | U108: chicco | W108: 5տ | X108: =VLOOKUP(W108,SIZE!A:B,2,0) -> #N/A | Y108: 8.99 | Z108: վարդագույն | AA108: =VLOOKUP(Z108,COLOR!A:B,2,0) -> 13
A109: 108 | B109: 60000002250 | C109: 62024000090 | D109: ԿԱՆԱՑԻ ԵՎ ԱՂՋԿԱ ԲԱՃԿՈՆՆԵՐ ՔԻՄԻԱԿԱՆ ԹԵԼԵՐԻՑ | E109: =PROPER(F109) -> Բաճկոն | F109: բաճկոն | G109: =VLOOKUP(E109,subcategory!A:B,2,0) -> 14 | H109: աղջկա | I109: =VLOOKUP(H109,gender!A:B,2,0) -> #N/A | J109: 115 | K109: 115 | L109: 1 | M109: CHICCO | N109: =VLOOKUP(M109,brand!A:B,2,0) -> 608 | O109: =UPPER(Q109) -> MYANMAR | P109: =VLOOKUP(O109,country!A:B,2,0) -> 7495 | Q109: MYANMAR | R109: =PROPER(S109) -> Պոլիեսթեր | S109: պոլիեսթեր | T109: =VLOOKUP(R109,material!A:B,2,0) -> 37 | U109: chicco | W109: 3տ | X109: =VLOOKUP(W109,SIZE!A:B,2,0) -> #N/A | Y109: 19.99 | Z109: վարդագույն | AA109: =VLOOKUP(Z109,COLOR!A:B,2,0) -> 13
A110: 109 | B110: 60000002249 | C110: 61112090000 | D110: ԱՂՋԻԿ ԵՐԵԽԱՅԻ ՇՐՋԱԶԳԵՍՏՆԵՐ ԲԱՄԲԱԿԵ ՄԱՆՎԱԾՔԻՑ ՄԻՆՉԵՎ 86 ՍՄ ՀԱՍԱԿ ՈՒՆԵՑՈՂ | E110: =PROPER(F110) -> Զգեստ | F110: զգեստ | G110: =VLOOKUP(E110,subcategory!A:B,2,0) -> 43 | H110: նորածին աղջկա | I110: =VLOOKUP(H110,gender!A:B,2,0) -> #N/A | J110: 135 | K110: 135 | L110: 1 | M110: CHICCO | N110: =VLOOKUP(M110,brand!A:B,2,0) -> 608 | O110: =UPPER(Q110) -> INDIA | P110: =VLOOKUP(O110,country!A:B,2,0) -> 7505 | Q110: INDIA | R110: =PROPER(S110) -> Բամբակ | S110: բամբակ | T110: =VLOOKUP(R110,material!A:B,2,0) -> 9 | U110: chicco | W110: 9ամիս | X110: =VLOOKUP(W110,SIZE!A:B,2,0) -> #N/A | Y110: 27.99 | Z110: սև | AA110: =VLOOKUP(Z110,COLOR!A:B,2,0) -> 20
A111: 110 | B111: 60000002248 | C111: 61112090000 | D111: ՏՂԱ ԵՐԵԽԱՅԻ ԲՈԴԻՆԵՐ ԲԱՄԲԱԿԵ ՄԱՆՎԱԾՔԻՑ ՄԻՆՉԵՎ 86 ՍՄ ՀԱՍԱԿ ՈՒՆԵՑՈՂ | E111: =PROPER(F111) -> Բոդի | F111: բոդի | G111: =VLOOKUP(E111,subcategory!A:B,2,0) -> 15 | H111: նորածին տղա | I111: =VLOOKUP(H111,gender!A:B,2,0) -> 7 | J111: 65 | K111: 65 | L111: 1 | M111: CHICCO | N111: =VLOOKUP(M111,brand!A:B,2,0) -> 608 | O111: =UPPER(Q111) -> TURKEY | P111: =VLOOKUP(O111,country!A:B,2,0) -> 1840 | Q111: TURKEY | R111: =PROPER(S111) -> Բամբակ | S111: բամբակ | T111: =VLOOKUP(R111,material!A:B,2,0) -> 9 | U111: chicco | W111: 1ամիս | X111: =VLOOKUP(W111,SIZE!A:B,2,0) -> #N/A | Y111: 20.99 | Z111: դեղին | AA111: =VLOOKUP(Z111,COLOR!A:B,2,0) -> 3
A112: 111 | B112: 60000002247 | C112: 62034235000 | D112: ՏՂԱՅԻ ՏԱԲԱՏՆԵՐ ԲԱՄԲԱԿԵ ՄԱՆՎԱԾՔԻՑ | E112: =PROPER(F112) -> Տաբատներ | F112: տաբատներ | G112: =VLOOKUP(E112,subcategory!A:B,2,0) -> 93 | H112: տղա | I112: =VLOOKUP(H112,gender!A:B,2,0) -> #N/A | J112: 180 | K112: 180 | L112: 1 | M112: CHICCO | N112: =VLOOKUP(M112,brand!A:B,2,0) -> 608 | O112: =UPPER(Q112) -> INDIA | P112: =VLOOKUP(O112,country!A:B,2,0) -> 7505 | Q112: INDIA | R112: =PROPER(S112) -> Բամբակ | S112: բամբակ | T112: =VLOOKUP(R112,material!A:B,2,0) -> 9 | U112: chicco | W112: 4տ | X112: =VLOOKUP(W112,SIZE!A:B,2,0) -> #N/A | Y112: 25.99 | Z112: կապույտ | AA112: =VLOOKUP(Z112,COLOR!A:B,2,0) -> 5
A113: 112 | B113: 60000002246 | C113: 61113090000 | D113: ՏՂԱ ԵՐԵԽԱՅԻ ՇՈՐՏԵՐ ՍԻՆԹԵՏԻԿ ԹԵԼԵՐԻՑ ՄԻՆՉԵՎ 86 ՍՄ ՀԱՍԱԿ ՈՒՆԵՑՈՂ | E113: =PROPER(F113) -> Շորտ | F113: շորտ | G113: =VLOOKUP(E113,subcategory!A:B,2,0) -> 24 | H113: տղա | I113: =VLOOKUP(H113,gender!A:B,2,0) -> #N/A | J113: 70 | K113: 70 | L113: 1 | M113: CHICCO | N113: =VLOOKUP(M113,brand!A:B,2,0) -> 608 | O113: =UPPER(Q113) -> CHINA | P113: =VLOOKUP(O113,country!A:B,2,0) -> 7497 | Q113: CHINA | R113: =PROPER(S113) -> Պոլիեսթեր | S113: պոլիեսթեր | T113: =VLOOKUP(R113,material!A:B,2,0) -> 37 | U113: chicco | W113: 1տ | X113: =VLOOKUP(W113,SIZE!A:B,2,0) -> #N/A | Y113: 20.99 | Z113: կապույտ | AA113: =VLOOKUP(Z113,COLOR!A:B,2,0) -> 5
A114: 113 | B114: 60000002245 | C114: 61112090000 | D114: ԱՂՋԻԿ ԵՐԵԽԱՅԻ ՇՈՐՏԵՐ ԲԱՄԲԱԿԵ ՄԱՆՎԱԾՔԻՑ ՄԻՆՉԵՎ 86 ՍՄ ՀԱՍԱԿ ՈՒՆԵՑՈՂ | E114: =PROPER(F114) -> Շորտ | F114: շորտ | G114: =VLOOKUP(E114,subcategory!A:B,2,0) -> 24 | H114: նորածին աղջկա | I114: =VLOOKUP(H114,gender!A:B,2,0) -> #N/A | J114: 45 | K114: 45 | L114: 1 | M114: CHICCO | N114: =VLOOKUP(M114,brand!A:B,2,0) -> 608 | O114: =UPPER(Q114) -> CHINA | P114: =VLOOKUP(O114,country!A:B,2,0) -> 7497 | Q114: CHINA | R114: =PROPER(S114) -> Բամբակ | S114: բամբակ | T114: =VLOOKUP(R114,material!A:B,2,0) -> 9 | U114: chicco | W114: 6ամիս | X114: =VLOOKUP(W114,SIZE!A:B,2,0) -> #N/A | Y114: 24.99 | Z114: սպիտակ | AA114: =VLOOKUP(Z114,COLOR!A:B,2,0) -> 12
A115: 114 | B115: 60000002244 | C115: 61033200000 | D115: ՏՂԱՅԻ ԺԱԿԵՏՆԵՐ ԲԱՄԲԱԿԵ ՄԱՆՎԱԾՔԻՑ | E115: =PROPER(F115) -> Ժակետ | F115: Ժակետ | G115: =VLOOKUP(E115,subcategory!A:B,2,0) -> 466 | H115: տղա | I115: =VLOOKUP(H115,gender!A:B,2,0) -> #N/A | J115: 190 | K115: 190 | L115: 1 | M115: CHICCO | N115: =VLOOKUP(M115,brand!A:B,2,0) -> 608 | O115: =UPPER(Q115) -> BANGLADESH | P115: =VLOOKUP(O115,country!A:B,2,0) -> 7485 | Q115: BANGLADESH | R115: =PROPER(S115) -> Բամբակ | S115: բամբակ | T115: =VLOOKUP(R115,material!A:B,2,0) -> 9 | U115: chicco | W115: 3տ | X115: =VLOOKUP(W115,SIZE!A:B,2,0) -> #N/A | Y115: 0 | Z115: կապույտ | AA115: =VLOOKUP(Z115,COLOR!A:B,2,0) -> 5
A116: 115 | B116: 60000002243 | C116: 61112090000 | D116: ԱՂՋԻԿ ԵՐԵԽԱՅԻ ՇՈՐՏԵՐ ԲԱՄԲԱԿԵ ՄԱՆՎԱԾՔԻՑ ՄԻՆՉԵՎ 86 ՍՄ ՀԱՍԱԿ ՈՒՆԵՑՈՂ | E116: =PROPER(F116) -> Շորտ | F116: շորտ | G116: =VLOOKUP(E116,subcategory!A:B,2,0) -> 24 | H116: նորածին աղջկա | I116: =VLOOKUP(H116,gender!A:B,2,0) -> #N/A | J116: 25 | K116: 25 | L116: 1 | M116: CHICCO | N116: =VLOOKUP(M116,brand!A:B,2,0) -> 608 | O116: =UPPER(Q116) -> CHINA | P116: =VLOOKUP(O116,country!A:B,2,0) -> 7497 | Q116: CHINA | R116: =PROPER(S116) -> Բամբակ | S116: բամբակ | T116: =VLOOKUP(R116,material!A:B,2,0) -> 9 | U116: chicco | W116: 9ամիս | X116: =VLOOKUP(W116,SIZE!A:B,2,0) -> #N/A | Y116: 0 | Z116: կարմիր | AA116: =VLOOKUP(Z116,COLOR!A:B,2,0) -> 1
... A272: 271 | B272: 60000002102 | C272: 61043200000 | D272: ԱՂՋԿԱ ԺԱԿԵՏՆԵՐ ԲԱՄԲԱԿԵ ՄԱՆՎԱԾՔԻՑ | E272: =PROPER(F272) -> Ժակետ | F272: Ժակետ | G272: =VLOOKUP(E272,subcategory!A:B,2,0) -> 466 | H272: աղջկա | I272: =VLOOKUP(H272,gender!A:B,2,0) -> #N/A | J272: 95 | K272: 95 | L272: 1 | M272: CHICCO | N272: =VLOOKUP(M272,brand!A:B,2,0) -> 608 | O272: =UPPER(Q272) -> BANGLADESH | P272: =VLOOKUP(O272,country!A:B,2,0) -> 7485 | Q272: BANGLADESH | R272: =PROPER(S272) -> Բամբակ | S272: բամբակ | T272: =VLOOKUP(R272,material!A:B,2,0) -> 9 | U272: chicco | W272: 7տ. | X272: =VLOOKUP(W272,SIZE!A:B,2,0) -> #N/A | Y272: 22.99 | Z272: սպիտակ | AA272: =VLOOKUP(Z272,COLOR!A:B,2,0) -> 12
A273: 272 | B273: 60000002086 | C273: 61112090000 | D273: ԱՂՋԻԿ ԵՐԵԽԱՅԻ ՏԱԲԱՏ ԲԱՄԲԱԿԵ ՄԱՆՎԱԾՔԻՑ ՄԻՆՉԵՎ 86 ՍՄ ՀԱՍԱԿ ՈՒՆԵՑՈՂ | E273: =PROPER(F273) -> Տաբատներ | F273: տաբատներ | G273: =VLOOKUP(E273,subcategory!A:B,2,0) -> 93 | H273: նորածին աղջկա | I273: =VLOOKUP(H273,gender!A:B,2,0) -> #N/A | J273: 76 | K273: 76 | L273: 1 | M273: CHICCO | N273: =VLOOKUP(M273,brand!A:B,2,0) -> 608 | O273: =UPPER(Q273) -> INDIA | P273: =VLOOKUP(O273,country!A:B,2,0) -> 7505 | Q273: INDIA | R273: =PROPER(S273) -> Բամբակ | S273: բամբակ | T273: =VLOOKUP(R273,material!A:B,2,0) -> 9 | U273: chicco | W273: 9ամիս | X273: =VLOOKUP(W273,SIZE!A:B,2,0) -> #N/A | Y273: - | Z273: կապույտ | AA273: =VLOOKUP(Z273,COLOR!A:B,2,0) -> 5
A274: 273 | B274: 60000002085 | C274: 61112090000 | D274: ԱՂՋԻԿ ԵՐԵԽԱՅԻ ՏԱԲԱՏ ԲԱՄԲԱԿԵ ՄԱՆՎԱԾՔԻՑ ՄԻՆՉԵՎ 86 ՍՄ ՀԱՍԱԿ ՈՒՆԵՑՈՂ | E274: =PROPER(F274) -> Տաբատներ | F274: տաբատներ | G274: =VLOOKUP(E274,subcategory!A:B,2,0) -> 93 | H274: նորածին աղջկա | I274: =VLOOKUP(H274,gender!A:B,2,0) -> #N/A | J274: 65 | K274: 65 | L274: 1 | M274: CHICCO | N274: =VLOOKUP(M274,brand!A:B,2,0) -> 608 | O274: =UPPER(Q274) -> INDIA | P274: =VLOOKUP(O274,country!A:B,2,0) -> 7505 | Q274: INDIA | R274: =PROPER(S274) -> Բամբակ | S274: բամբակ | T274: =VLOOKUP(R274,material!A:B,2,0) -> 9 | U274: chicco | W274: 6ամիս | X274: =VLOOKUP(W274,SIZE!A:B,2,0) -> #N/A | Y274: - | Z274: կապույտ | AA274: =VLOOKUP(Z274,COLOR!A:B,2,0) -> 5
A275: 274 | B275: 60000002083 | C275: 61091000000 | D275: ՏՂԱՅԻ ՇԱՊԻԿՆԵՐ ԲԱՄԲԱԿԵ ՄԱՆՎԱԾՔԻՑ | E275: =PROPER(F275) -> Շապիկ | F275: շապիկ | G275: =VLOOKUP(E275,subcategory!A:B,2,0) -> 73 | H275: տղա | I275: =VLOOKUP(H275,gender!A:B,2,0) -> #N/A | J275: 40 | K275: 40 | L275: 1 | M275: CHICCO | N275: =VLOOKUP(M275,brand!A:B,2,0) -> 608 | O275: =UPPER(Q275) -> BANGLADESH | P275: =VLOOKUP(O275,country!A:B,2,0) -> 7485 | Q275: BANGLADESH | R275: =PROPER(S275) -> Բամբակ | S275: բամբակ | T275: =VLOOKUP(R275,material!A:B,2,0) -> 9 | U275: chicco | W275: 6տ. | X275: =VLOOKUP(W275,SIZE!A:B,2,0) -> #N/A | Y275: 10,99 | Z275: կանաչ | AA275: =VLOOKUP(Z275,COLOR!A:B,2,0) -> 4
A276: 275 | B276: 60000002084 | C276: 61091000000 | D276: ՏՂԱՅԻ ՇԱՊԻԿՆԵՐ ԲԱՄԲԱԿԵ ՄԱՆՎԱԾՔԻՑ | E276: =PROPER(F276) -> Շապիկ | F276: շապիկ | G276: =VLOOKUP(E276,subcategory!A:B,2,0) -> 73 | H276: տղա | I276: =VLOOKUP(H276,gender!A:B,2,0) -> #N/A | J276: 45 | K276: 45 | L276: 1 | M276: CHICCO | N276: =VLOOKUP(M276,brand!A:B,2,0) -> 608 | O276: =UPPER(Q276) -> BANGLADESH | P276: =VLOOKUP(O276,country!A:B,2,0) -> 7485 | Q276: BANGLADESH | R276: =PROPER(S276) -> Բամբակ | S276: բամբակ | T276: =VLOOKUP(R276,material!A:B,2,0) -> 9 | U276: chicco | W276: 6տ. | X276: =VLOOKUP(W276,SIZE!A:B,2,0) -> #N/A | Y276: 10,99 | Z276: կանաչ | AA276: =VLOOKUP(Z276,COLOR!A:B,2,0) -> 4
A277: 276 | B277: 60000002082 | C277: 61112090000 | D277: ՏՂԱ ԵՐԵԽԱՅԻ ԲՈԴԻՆԵՐ ԲԱՄԲԱԿԵ ՄԱՆՎԱԾՔԻՑ ՄԻՆՉԵՎ 86 ՍՄ ՀԱՍԱԿ ՈՒՆԵՑՈՂ | E277: =PROPER(F277) -> Բոդի | F277: բոդի | G277: =VLOOKUP(E277,subcategory!A:B,2,0) -> 15 | H277: նորածին տղա | I277: =VLOOKUP(H277,gender!A:B,2,0) -> 7 | J277: 100 | K277: 100 | L277: 1 | M277: CHICCO | N277: =VLOOKUP(M277,brand!A:B,2,0) -> 608 | O277: =UPPER(Q277) -> CHINA | P277: =VLOOKUP(O277,country!A:B,2,0) -> 7497 | Q277: CHINA | R277: =PROPER(S277) -> Բամբակ | S277: բամբակ | T277: =VLOOKUP(R277,material!A:B,2,0) -> 9 | U277: chicco | W277: 3ամիս | X277: =VLOOKUP(W277,SIZE!A:B,2,0) -> #N/A | Y277: - | Z277: սպիտակ | AA277: =VLOOKUP(Z277,COLOR!A:B,2,0) -> 12
A278: 277 | B278: 60000002081 | C278: 61112090000 | D278: ՏՂԱ ԵՐԵԽԱՅԻ ԲՈԴԻՆԵՐ ԲԱՄԲԱԿԵ ՄԱՆՎԱԾՔԻՑ ՄԻՆՉԵՎ 86 ՍՄ ՀԱՍԱԿ ՈՒՆԵՑՈՂ | E278: =PROPER(F278) -> Բոդի | F278: բոդի | G278: =VLOOKUP(E278,subcategory!A:B,2,0) -> 15 | H278: նորածին տղա | I278: =VLOOKUP(H278,gender!A:B,2,0) -> 7 | J278: 100 | K278: 100 | L278: 1 | M278: CHICCO | N278: =VLOOKUP(M278,brand!A:B,2,0) -> 608 | O278: =UPPER(Q278) -> CHINA | P278: =VLOOKUP(O278,country!A:B,2,0) -> 7497 | Q278: CHINA | R278: =PROPER(S278) -> Բամբակ | S278: բամբակ | T278: =VLOOKUP(R278,material!A:B,2,0) -> 9 | U278: chicco | W278: 3ամիս | X278: =VLOOKUP(W278,SIZE!A:B,2,0) -> #N/A | Y278: - | Z278: սպիտակ | AA278: =VLOOKUP(Z278,COLOR!A:B,2,0) -> 12
A279: 278 | B279: 60000002080 | C279: 61112090000 | D279: ԱՂՋԻԿ ԵՐԵԽԱՅԻ ԿԱՄԲԻՆԻԶՈՆՆԵՐ ԲԱՄԲԱԿԵ ՄԱՆՎԱԾՔԻՑ ՄԻՆՉԵՎ 86 ՍՄ ՀԱՍԱԿ ՈՒՆԵՑՈՂ | E279: =PROPER(F279) -> Կոմբինեզոն | F279: կոմբինեզոն | G279: =VLOOKUP(E279,subcategory!A:B,2,0) -> 54 | H279: նորածին աղջկա | I279: =VLOOKUP(H279,gender!A:B,2,0) -> #N/A | J279: 80 | K279: 80 | L279: 1 | M279: CHICCO | N279: =VLOOKUP(M279,brand!A:B,2,0) -> 608 | O279: =UPPER(Q279) -> INDIA | P279: =VLOOKUP(O279,country!A:B,2,0) -> 7505 | Q279: INDIA | R279: =PROPER(S279) -> Բամբակ | S279: բամբակ | T279: =VLOOKUP(R279,material!A:B,2,0) -> 9 | U279: chicco | W279: 6ամիս | X279: =VLOOKUP(W279,SIZE!A:B,2,0) -> #N/A | Y279: 35,99 | Z279: սպիտակ | AA279: =VLOOKUP(Z279,COLOR!A:B,2,0) -> 12
A280: 279 | B280: 60000002079 | C280: 61112090000 | D280: ՏՂԱ ԵՐԵԽԱՅԻ ԺԱԿԵՏ ԻՐ ՏԱԲԱՏՈՎ ԲԱՄԲԱԿԵ ՄԱՆՎԱԾՔԻՑ ՄԻՆՉԵՎ 86 ՍՄ ՀԱՍԱԿ ՈՒՆԵՑՈՂ | E280: =PROPER(F280) -> Ժակետ+Տաբատ | F280: Ժակետ+տաբատ | G280: =VLOOKUP(E280,subcategory!A:B,2,0) -> #N/A | H280: նորածին տղա | I280: =VLOOKUP(H280,gender!A:B,2,0) -> 7 | J280: 245 | K280: 245 | L280: 1 | M280: CHICCO | N280: =VLOOKUP(M280,brand!A:B,2,0) -> 608 | O280: =UPPER(Q280) -> INDIA | P280: =VLOOKUP(O280,country!A:B,2,0) -> 7505 | Q280: INDIA | R280: =PROPER(S280) -> Բամբակ | S280: բամբակ | T280: =VLOOKUP(R280,material!A:B,2,0) -> 9 | U280: chicco | W280: 12ամիս | X280: =VLOOKUP(W280,SIZE!A:B,2,0) -> #N/A | Y280: 32,99 | Z280: սև | AA280: =VLOOKUP(Z280,COLOR!A:B,2,0) -> 20
A281: 280 | B281: 60000002078 | C281: 62046239000 | D281: ԱՂՋԿԱ ՏԱԲԱՏՆԵՐ ԲԱՄԲԱԿԵ ՄԱՆՎԱԾՔԻՑ | E281: =PROPER(F281) -> Տաբատներ | F281: տաբատներ | G281: =VLOOKUP(E281,subcategory!A:B,2,0) -> 93 | H281: աղջկա | I281: =VLOOKUP(H281,gender!A:B,2,0) -> #N/A | J281: 105 | K281: 105 | L281: 1 | M281: CHICCO | N281: =VLOOKUP(M281,brand!A:B,2,0) -> 608 | O281: =UPPER(Q281) -> INDIA | P281: =VLOOKUP(O281,country!A:B,2,0) -> 7505 | Q281: INDIA | R281: =PROPER(S281) -> Բամբակ | S281: բամբակ | T281: =VLOOKUP(R281,material!A:B,2,0) -> 9 | U281: chicco | W281: 18ամիս | X281: =VLOOKUP(W281,SIZE!A:B,2,0) -> #N/A | Y281: 29,99 | Z281: կապույտ | AA281: =VLOOKUP(Z281,COLOR!A:B,2,0) -> 5
A282: 281 | B282: 60000002077 | C282: 62034235000 | D282: ՏՂԱՄԱՐԴՈՒ ԵՎ ՏՂԱՅԻ ՏԱԲԱՏՆԵՐ ԲԱՄԲԱԿԵ ՄԱՆՎԱԾՔԻՑ | E282: =PROPER(F282) -> Տաբատներ | F282: տաբատներ | G282: =VLOOKUP(E282,subcategory!A:B,2,0) -> 93 | H282: տղա | I282: =VLOOKUP(H282,gender!A:B,2,0) -> #N/A | J282: 125 | K282: 125 | L282: 1 | M282: CHICCO | N282: =VLOOKUP(M282,brand!A:B,2,0) -> 608 | O282: =UPPER(Q282) -> BANGLADESH | P282: =VLOOKUP(O282,country!A:B,2,0) -> 7485 | Q282: BANGLADESH | R282: =PROPER(S282) -> Բամբակ | S282: բամբակ | T282: =VLOOKUP(R282,material!A:B,2,0) -> 9 | U282: chicco | W282: 18ամիս | X282: =VLOOKUP(W282,SIZE!A:B,2,0) -> #N/A | Y282: 10,99 | Z282: սև | AA282: =VLOOKUP(Z282,COLOR!A:B,2,0) -> 20
A283: 282 | B283: 60000002075 | C283: 61112090000 | D283: ՏՂԱ ԵՐԵԽԱՅԻ ՏԱԲԱՏՆԵՐ ԲԱՄԲԱԿԵ ՄԱՆՎԱԾՔԻՑ ՄԻՆՉԵՎ 86 ՍՄ ՀԱՍԱԿ ՈՒՆԵՑՈՂ | E283: =PROPER(F283) -> Տաբատներ | F283: տաբատներ | G283: =VLOOKUP(E283,subcategory!A:B,2,0) -> 93 | H283: նորածին տղա | I283: =VLOOKUP(H283,gender!A:B,2,0) -> 7 | J283: 80 | K283: 80 | L283: 1 | M283: CHICCO | N283: =VLOOKUP(M283,brand!A:B,2,0) -> 608 | O283: =UPPER(Q283) -> INDIA | P283: =VLOOKUP(O283,country!A:B,2,0) -> 7505 | Q283: INDIA | R283: =PROPER(S283) -> Բամբակ | S283: բամբակ | T283: =VLOOKUP(R283,material!A:B,2,0) -> 9 | U283: chicco | W283: 6ամիս | X283: =VLOOKUP(W283,SIZE!A:B,2,0) -> #N/A | Y283: 10,99 | Z283: մոխրագույն | AA283: =VLOOKUP(Z283,COLOR!A:B,2,0) -> 8
A284: 283 | B284: 60000002076 | C284: 61112090000 | D284: ՏՂԱ ԵՐԵԽԱՅԻ ՇՈՐՏԵՐ ԲԱՄԲԱԿԵ ՄԱՆՎԱԾՔԻՑ ՄԻՆՉԵՎ 86 ՍՄ ՀԱՍԱԿ ՈՒՆԵՑՈՂ | E284: =PROPER(F284) -> Շորտ | F284: շորտ | G284: =VLOOKUP(E284,subcategory!A:B,2,0) -> 24 | H284: նորածին տղա | I284: =VLOOKUP(H284,gender!A:B,2,0) -> 7 | J284: 80 | K284: 80 | L284: 1 | M284: CHICCO | N284: =VLOOKUP(M284,brand!A:B,2,0) -> 608 | O284: =UPPER(Q284) -> INDIA | P284: =VLOOKUP(O284,country!A:B,2,0) -> 7505 | Q284: INDIA | R284: =PROPER(S284) -> Բամբակ | S284: բամբակ | T284: =VLOOKUP(R284,material!A:B,2,0) -> 9 | U284: chicco | W284: 3ամիս | X284: =VLOOKUP(W284,SIZE!A:B,2,0) -> #N/A | Y284: 27,99 | Z284: մոխրագույն | AA284: =VLOOKUP(Z284,COLOR!A:B,2,0) -> 8
... A288: 287 | B288: 60000002071 | C288: 62143000000 | D288: ՏՂԱՅԻ ՇԱՐՖԵՐ ՍԻՆԹԵՏԻԿ ԹԵԼԵՐԻՑ | E288: =PROPER(F288) -> Շարֆ | F288: շարֆ | G288: =VLOOKUP(E288,subcategory!A:B,2,0) -> 11 | H288: տղա | I288: =VLOOKUP(H288,gender!A:B,2,0) -> #N/A | J288: 110 | K288: 110 | L288: 1 | M288: CHICCO | N288: =VLOOKUP(M288,brand!A:B,2,0) -> 608 | O288: =UPPER(Q288) -> CHINA | P288: =VLOOKUP(O288,country!A:B,2,0) -> 7497 | Q288: CHINA | R288: =PROPER(S288) -> Պոլիեսթեր | S288: պոլիեսթեր | T288: =VLOOKUP(R288,material!A:B,2,0) -> 37 | U288: chicco | W288: one size | X288: =VLOOKUP(W288,SIZE!A:B,2,0) -> 311 | Y288: 7,39 | Z288: կապույտ | AA288: =VLOOKUP(Z288,COLOR!A:B,2,0) -> 5
A289: 288 | B289: 60000002070 | C289: 61042200000 | D289: ԱՂՋԿԱ ՏԱԲԱՏ ԻՐ ՇԱՊԻԿՈՎ ԲԱՄԲԱԿԵ ՄԱՆՎԱԾՔԻՑ | E289: =PROPER(F289) -> Շապիկ+Տաբատ | F289: շապիկ+տաբատ | G289: =VLOOKUP(E289,subcategory!A:B,2,0) -> #N/A | H289: աղջկա | I289: =VLOOKUP(H289,gender!A:B,2,0) -> #N/A | J289: 245 | K289: 245 | L289: 1 | M289: CHICCO | N289: =VLOOKUP(M289,brand!A:B,2,0) -> 608 | O289: =UPPER(Q289) -> INDIA | P289: =VLOOKUP(O289,country!A:B,2,0) -> 7505 | Q289: INDIA | R289: =PROPER(S289) -> Բամբակ | S289: բամբակ | T289: =VLOOKUP(R289,material!A:B,2,0) -> 9 | U289: chicco | W289: 4տ. | X289: =VLOOKUP(W289,SIZE!A:B,2,0) -> #N/A | Y289: 0 | Z289: վարդագույն | AA289: =VLOOKUP(Z289,COLOR!A:B,2,0) -> 13
A290: 289 | B290: 60000002069 | C290: 61091000000 | D290: ԱՂՋԿԱ ՇԱՊԻԿՆԵՐ ԲԱՄԲԱԿԵ ՄԱՆՎԱԾՔԻՑ | E290: =PROPER(F290) -> Շապիկ | F290: շապիկ | G290: =VLOOKUP(E290,subcategory!A:B,2,0) -> 73 | H290: աղջկա | I290: =VLOOKUP(H290,gender!A:B,2,0) -> #N/A | J290: 115 | K290: 115 | L290: 1 | M290: CHICCO | N290: =VLOOKUP(M290,brand!A:B,2,0) -> 608 | O290: =UPPER(Q290) -> INDIA | P290: =VLOOKUP(O290,country!A:B,2,0) -> 7505 | Q290: INDIA | R290: =PROPER(S290) -> Բամբակ | S290: բամբակ | T290: =VLOOKUP(R290,material!A:B,2,0) -> 9 | U290: chicco | W290: 3-4տ. | X290: =VLOOKUP(W290,SIZE!A:B,2,0) -> #N/A | Y290: 14,99 | Z290: վարդագույն | AA290: =VLOOKUP(Z290,COLOR!A:B,2,0) -> 13
A291: 290 | B291: 60000002068 | C291: 61059090000 | D291: ՏՂԱՅԻ ՎԵՐՆԱՇԱՊԻԿՆԵՐ ՎՈՒՇԵ ՄԱՆՎԱԾՔԻՑ | E291: =PROPER(F291) -> Վերնաշապիկ | F291: վերնաշապիկ | G291: =VLOOKUP(E291,subcategory!A:B,2,0) -> 82 | H291: տղա | I291: =VLOOKUP(H291,gender!A:B,2,0) -> #N/A | J291: 100 | K291: 100 | L291: 1 | M291: CHICCO | N291: =VLOOKUP(M291,brand!A:B,2,0) -> 608 | O291: =UPPER(Q291) -> INDIA | P291: =VLOOKUP(O291,country!A:B,2,0) -> 7505 | Q291: INDIA | R291: =PROPER(S291) -> Լիոն | S291: լիոն | T291: =VLOOKUP(R291,material!A:B,2,0) -> #N/A | U291: chicco | W291: 7տ. | X291: =VLOOKUP(W291,SIZE!A:B,2,0) -> #N/A | Y291: 29,99 | Z291: սպիտակ | AA291: =VLOOKUP(Z291,COLOR!A:B,2,0) -> 12
A292: 291 | B292: 60000002067 | C292: 61046200000 | D292: ԱՂՋԿԱ ՇՈՐՏԵՐ ԲԱՄԲԱԿԵ ՄԱՆՎԱԾՔԻՑ | E292: =PROPER(F292) -> Շորտ | F292: շորտ | G292: =VLOOKUP(E292,subcategory!A:B,2,0) -> 24 | H292: աղջկա | I292: =VLOOKUP(H292,gender!A:B,2,0) -> #N/A | J292: 110 | K292: 110 | L292: 1 | M292: CHICCO | N292: =VLOOKUP(M292,brand!A:B,2,0) -> 608 | O292: =UPPER(Q292) -> BANGLADESH | P292: =VLOOKUP(O292,country!A:B,2,0) -> 7485 | Q292: BANGLADESH | R292: =PROPER(S292) -> Բամբակ | S292: բամբակ | T292: =VLOOKUP(R292,material!A:B,2,0) -> 9 | U292: chicco | W292: 5տ. | X292: =VLOOKUP(W292,SIZE!A:B,2,0) -> #N/A | Y292: 26,99 | Z292: սպիտակ | AA292: =VLOOKUP(Z292,COLOR!A:B,2,0) -> 12
A293: 292 | B293: 60000002066 | C293: 61043200000 | D293: ԱՂՋԿԱ ԺԱԿԵՏՆԵՐ ԲԱՄԲԱԿԵ ՄԱՆՎԱԾՔԻՑ | E293: =PROPER(F293) -> Ժակետ | F293: ժակետ | G293: =VLOOKUP(E293,subcategory!A:B,2,0) -> 466 | H293: աղջկա | I293: =VLOOKUP(H293,gender!A:B,2,0) -> #N/A | J293: 245 | K293: 245 | L293: 1 | M293: CHICCO | N293: =VLOOKUP(M293,brand!A:B,2,0) -> 608 | O293: =UPPER(Q293) -> BANGLADESH | P293: =VLOOKUP(O293,country!A:B,2,0) -> 7485 | Q293: BANGLADESH | R293: =PROPER(S293) -> Բամբակ/Պոլիեսթեր | S293: բամբակ/պոլիեսթեր | T293: =VLOOKUP(R293,material!A:B,2,0) -> 9-37 | U293: chicco | W293: 11-12տ. | X293: =VLOOKUP(W293,SIZE!A:B,2,0) -> #N/A | Y293: 20,99 | Z293: սպիտակ | AA293: =VLOOKUP(Z293,COLOR!A:B,2,0) -> 12
A294: 293 | B294: 60000002065 | C294: 61112090000 | D294: ՏՂԱ ԵՐԵԽԱՅԻ ՇԱՊԻԿՆԵՐ ԲԱՄԲԱԿԵ ՄԱՆՎԱԾՔԻՑ ՄԻՆՉԵՎ 86 ՍՄ ՀԱՍԱԿ ՈՒՆԵՑՈՂ | E294: =PROPER(F294) -> Շապիկ | F294: շապիկ | G294: =VLOOKUP(E294,subcategory!A:B,2,0) -> 73 | H294: նորածին տղա | I294: =VLOOKUP(H294,gender!A:B,2,0) -> 7 | J294: 50 | K294: 50 | L294: 1 | M294: CHICCO | N294: =VLOOKUP(M294,brand!A:B,2,0) -> 608 | O294: =UPPER(Q294) -> BANGLADESH | P294: =VLOOKUP(O294,country!A:B,2,0) -> 7485 | Q294: BANGLADESH | R294: =PROPER(S294) -> Բամբակ | S294: բամբակ | T294: =VLOOKUP(R294,material!A:B,2,0) -> 9 | U294: chicco | W294: 6ամիս | X294: =VLOOKUP(W294,SIZE!A:B,2,0) -> #N/A | Y294: 10,99 | Z294: սպիտակ | AA294: =VLOOKUP(Z294,COLOR!A:B,2,0) -> 12
A295: 294 | B295: 60000002064 | C295: 62071100000 | D295: ՏՂԱՅԻ ՎԱՐՏԻՔՆԵՐ ԲԱՄԲԱԿԵ ՄԱՆՎԱԾՔԻՑ ՀԱՎԱՔԱԾՈՒ 2 ՀԱՏԻՑ | E295: =PROPER(F295) -> Վարտիկ 2 Հատ Սեթ | F295: վարտիկ 2 հատ սեթ | G295: =VLOOKUP(E295,subcategory!A:B,2,0) -> #N/A | H295: տղա | I295: =VLOOKUP(H295,gender!A:B,2,0) -> #N/A | J295: 90 | K295: 90 | L295: 1 | M295: CHICCO | N295: =VLOOKUP(M295,brand!A:B,2,0) -> 608 | O295: =UPPER(Q295) -> INDIA | P295: =VLOOKUP(O295,country!A:B,2,0) -> 7505 | Q295: INDIA | R295: =PROPER(S295) -> Բամբակ | S295: բամբակ | T295: =VLOOKUP(R295,material!A:B,2,0) -> 9 | U295: chicco | W295: 9-10տ. | X295: =VLOOKUP(W295,SIZE!A:B,2,0) -> #N/A | Y295: 12,99 | Z295: սպիտակ | AA295: =VLOOKUP(Z295,COLOR!A:B,2,0) -> 12
A296: 295 | B296: 60000002063 | C296: 61112090000 | D296: ԱՂՋԻԿ ԵՐԵԽԱՅԻ ՇՐՋԱԶԳԵՍՏՆԵՐ ԲԱՄԲԱԿԵ ՄԱՆՎԱԾՔԻՑ ՄԻՆՉԵՎ 86 ՍՄ ՀԱՍԱԿ ՈՒՆԵՑՈՂ | E296: =PROPER(F296) -> Զգեստ | F296: զգեստ | G296: =VLOOKUP(E296,subcategory!A:B,2,0) -> 43 | H296: նորածին աղջկա | I296: =VLOOKUP(H296,gender!A:B,2,0) -> #N/A | J296: 115 | K296: 115 | L296: 1 | M296: CHICCO | N296: =VLOOKUP(M296,brand!A:B,2,0) -> 608 | O296: =UPPER(Q296) -> CHINA | P296: =VLOOKUP(O296,country!A:B,2,0) -> 7497 | Q296: CHINA | R296: =PROPER(S296) -> Բամբակ | S296: բամբակ | T296: =VLOOKUP(R296,material!A:B,2,0) -> 9 | U296: chicco | W296: 6ամիս | X296: =VLOOKUP(W296,SIZE!A:B,2,0) -> #N/A | Y296: - | Z296: վարդագույն | AA296: =VLOOKUP(Z296,COLOR!A:B,2,0) -> 13
A297: 296 | B297: 60000002062 | E297: =PROPER(F297) | G297: =VLOOKUP(E297,subcategory!A:B,2,0) -> #N/A | H297: աղջկա | I297: =VLOOKUP(H297,gender!A:B,2,0) -> #N/A | J297: 95 | K297: 95 | L297: 1 | M297: CHICCO | N297: =VLOOKUP(M297,brand!A:B,2,0) -> 608 | O297: =UPPER(Q297) -> TURKEY | P297: =VLOOKUP(O297,country!A:B,2,0) -> 1840 | Q297: TURKEY | R297: =PROPER(S297) -> Բամբակ | S297: բամբակ | T297: =VLOOKUP(R297,material!A:B,2,0) -> 9 | U297: chicco | W297: one size | X297: =VLOOKUP(W297,SIZE!A:B,2,0) -> 311 | Y297: 9,99 | Z297: սպիտակ | AA297: =VLOOKUP(Z297,COLOR!A:B,2,0) -> 12
A298: 297 | B298: 60000002060 | C298: 61159699000 | D298: ԱՂՋԿԱ ԳՈՒԼՊԱՆԵՐ ՍԻՆԹԵՏԻԿ ԹԵԼԵՐԻՑ | E298: =PROPER(F298) -> Գուլպա | F298: գուլպա | G298: =VLOOKUP(E298,subcategory!A:B,2,0) -> #N/A | H298: աղջկա | I298: =VLOOKUP(H298,gender!A:B,2,0) -> #N/A | J298: 25 | K298: 25 | L298: 1 | M298: CHICCO | N298: =VLOOKUP(M298,brand!A:B,2,0) -> 608 | O298: =UPPER(Q298) -> ITALY | P298: =VLOOKUP(O298,country!A:B,2,0) -> 1760 | Q298: ITALY | R298: =PROPER(S298) -> Պոլիամիդ | S298: պոլիամիդ | T298: =VLOOKUP(R298,material!A:B,2,0) -> 56 | U298: chicco | W298: 6-9տ. | X298: =VLOOKUP(W298,SIZE!A:B,2,0) -> #N/A | Y298: 4,99 | Z298: սպիտակ | AA298: =VLOOKUP(Z298,COLOR!A:B,2,0) -> 12
A299: 298 | B299: 60000002061 | C299: 61159699000 | D299: ԱՂՋԿԱ ԳՈՒԼՊԱՆԵՐ ՍԻՆԹԵՏԻԿ ԹԵԼԵՐԻՑ | E299: =PROPER(F299) -> Գուլպա | F299: գուլպա | G299: =VLOOKUP(E299,subcategory!A:B,2,0) -> #N/A | H299: աղջկա | I299: =VLOOKUP(H299,gender!A:B,2,0) -> #N/A | J299: 25 | K299: 25 | L299: 1 | M299: CHICCO | N299: =VLOOKUP(M299,brand!A:B,2,0) -> 608 | O299: =UPPER(Q299) -> ITALY | P299: =VLOOKUP(O299,country!A:B,2,0) -> 1760 | Q299: ITALY | R299: =PROPER(S299) -> Պոլիամիդ | S299: պոլիամիդ | T299: =VLOOKUP(R299,material!A:B,2,0) -> 56 | U299: chicco | W299: 6-9տ. | X299: =VLOOKUP(W299,SIZE!A:B,2,0) -> #N/A | Y299: 4,99 | Z299: սպիտակ | AA299: =VLOOKUP(Z299,COLOR!A:B,2,0) -> 12
A300: 299 | B300: 60000002059 | C300: 61112090000 | D300: ՏՂԱ ԵՐԵԽԱՅԻ ՇԱՊԻԿ ԻՐ ՏԱԲԱՏՈՎ ԲԱՄԲԱԿԵ ՄԱՆՎԱԾՔԻՑ ՄԻՆՉԵՎ 86 ՍՄ ՀԱՍԱԿ ՈՒՆԵՑՈՂ | E300: =PROPER(F300) -> Շապիկ+Տաբատ | F300: շապիկ+տաբատ | G300: =VLOOKUP(E300,subcategory!A:B,2,0) -> #N/A | H300: նորածին տղա | I300: =VLOOKUP(H300,gender!A:B,2,0) -> 7 | J300: 85 | K300: 85 | L300: 1 | M300: CHICCO | N300: =VLOOKUP(M300,brand!A:B,2,0) -> 608 | O300: =UPPER(Q300) -> BANGLADESH | P300: =VLOOKUP(O300,country!A:B,2,0) -> 7485 | Q300: BANGLADESH | R300: =PROPER(S300) -> Բամբակ | S300: բամբակ | T300: =VLOOKUP(R300,material!A:B,2,0) -> 9 | U300: chicco | W300: 9ամիս | X300: =VLOOKUP(W300,SIZE!A:B,2,0) -> #N/A | Y300: 22,99 | Z300: սպիտակ | AA300: =VLOOKUP(Z300,COLOR!A:B,2,0) -> 12
A301: 300 | B301: 60000002058 | C301: 61112090000 | D301: ԱՂՋԻԿ ԵՐԵԽԱՅԻ ԼՈՂԱԶԳԵՍՏ ԲԱՄԲԱԿԵ ՄԱՆՎԱԾՔԻՑ ՄԻՆՉԵՎ 86 ՍՄ ՀԱՍԱԿ ՈՒՆԵՑՈՂ | E301: =PROPER(F301) -> Լողազգեստ | F301: լողազգեստ | G301: =VLOOKUP(E301,subcategory!A:B,2,0) -> #N/A | H301: նորածին աղջկա | I301: =VLOOKUP(H301,gender!A:B,2,0) -> #N/A | J301: 55 | K301: 55 | L301: 1 | M301: CHICCO | N301: =VLOOKUP(M301,brand!A:B,2,0) -> 608 | O301: =UPPER(Q301) -> CHINA | P301: =VLOOKUP(O301,country!A:B,2,0) -> 7497 | Q301: CHINA | R301: =PROPER(S301) -> Բամբակ | S301: բամբակ | T301: =VLOOKUP(R301,material!A:B,2,0) -> 9 | U301: chicco | W301: 6ամիս | X301: =VLOOKUP(W301,SIZE!A:B,2,0) -> #N/A | Y301: 19,99 | Z301: կապույտ | AA301: =VLOOKUP(Z301,COLOR!A:B,2,0) -> 5
A302: 301 | B302: 60000002057 | C302: 62113290000 | D302: ՏՂԱՅԻ ԳՈԳՆՈՑՆԵՐ ԲԱՄԲԱԿԵ ՄԱՆՎԱԾՔԻՑ | E302: =PROPER(F302) -> Գոգնոց | F302: գոգնոց | G302: =VLOOKUP(E302,subcategory!A:B,2,0) -> 285 | H302: տղա | I302: =VLOOKUP(H302,gender!A:B,2,0) -> #N/A | J302: 75 | K302: 75 | L302: 1 | M302: CHICCO | N302: =VLOOKUP(M302,brand!A:B,2,0) -> 608 | O302: =UPPER(Q302) -> CHINA | P302: =VLOOKUP(O302,country!A:B,2,0) -> 7497 | Q302: CHINA | R302: =PROPER(S302) -> Բամբակ | S302: բամբակ | T302: =VLOOKUP(R302,material!A:B,2,0) -> 9 | U302: chicco | W302: one size | X302: =VLOOKUP(W302,SIZE!A:B,2,0) -> 311 | Y302: 9,99 | Z302: կապույտ | AA302: =VLOOKUP(Z302,COLOR!A:B,2,0) -> 5
A303: 302 | B303: 60000002056 | C303: 61112090000 | D303: ԱՂՋԻԿ ԵՐԵԽԱՅԻ ԲՈԴԻՆԵՐ ԲԱՄԲԱԿԵ ՄԱՆՎԱԾՔԻՑ ՄԻՆՉԵՎ 86 ՍՄ ՀԱՍԱԿ ՈՒՆԵՑՈՂ | E303: =PROPER(F303) -> Բոդի | F303: բոդի | G303: =VLOOKUP(E303,subcategory!A:B,2,0) -> 15 | H303: նորածին աղջկա | I303: =VLOOKUP(H303,gender!A:B,2,0) -> #N/A | J303: 170 | K303: 170 | L303: 1 | M303: CHICCO | N303: =VLOOKUP(M303,brand!A:B,2,0) -> 608 | O303: =UPPER(Q303) -> CHINA | P303: =VLOOKUP(O303,country!A:B,2,0) -> 7497 | Q303: CHINA | R303: =PROPER(S303) -> Բամբակ | S303: բամբակ | T303: =VLOOKUP(R303,material!A:B,2,0) -> 9 | U303: chicco | W303: 6ամիս | X303: =VLOOKUP(W303,SIZE!A:B,2,0) -> #N/A | Y303: 29,99 | Z303: սպիտակ | AA303: =VLOOKUP(Z303,COLOR!A:B,2,0) -> 12
A304: 303 | B304: 60000002055 | C304: 61102099000 | D304: ԱՂՋԿԱ ԿԱՐԴԻԳԱՆ ԲԱՄԲԱԿԵ ՄԱՆՎԱԾՔԻՑ | E304: =PROPER(F304) -> Կարդիգան | F304: կարդիգան | G304: =VLOOKUP(E304,subcategory!A:B,2,0) -> 89 | H304: աղջկա | I304: =VLOOKUP(H304,gender!A:B,2,0) -> #N/A | J304: 180 | K304: 180 | L304: 1 | M304: CHICCO | N304: =VLOOKUP(M304,brand!A:B,2,0) -> 608 | O304: =UPPER(Q304) -> INDIA | P304: =VLOOKUP(O304,country!A:B,2,0) -> 7505 | Q304: INDIA | R304: =PROPER(S304) -> Բամբակ | S304: բամբակ | T304: =VLOOKUP(R304,material!A:B,2,0) -> 9 | U304: chicco | W304: 6տ. | X304: =VLOOKUP(W304,SIZE!A:B,2,0) -> #N/A | Y304: 22,99 | Z304: սպիտակ | AA304: =VLOOKUP(Z304,COLOR!A:B,2,0) -> 12
A305: 304 | B305: 60000002054 | C305: 62024000090 | D305: ԿԱՆԱՑԻ ԵՎ ԱՂՋԿԱ ԲԱՃԿՈՆՆԵՐ ՔԻՄԻԱԿԱՆ ԹԵԼԵՐԻՑ | E305: =PROPER(F305) -> Բաճկոն | F305: բաճկոն | G305: =VLOOKUP(E305,subcategory!A:B,2,0) -> 14 | H305: աղջկա | I305: =VLOOKUP(H305,gender!A:B,2,0) -> #N/A | J305: 145 | K305: 145 | L305: 1 | M305: CHICCO | N305: =VLOOKUP(M305,brand!A:B,2,0) -> 608 | O305: =UPPER(Q305) -> CHINA | P305: =VLOOKUP(O305,country!A:B,2,0) -> 7497 | Q305: CHINA | R305: =PROPER(S305) -> Պոլիեսթեր | S305: պոլիեսթեր | T305: =VLOOKUP(R305,material!A:B,2,0) -> 37 | U305: chicco | W305: 18ամիս | X305: =VLOOKUP(W305,SIZE!A:B,2,0) -> #N/A | Y305: - | Z305: կապույտ | AA305: =VLOOKUP(Z305,COLOR!A:B,2,0) -> 5
A306: 305 | B306: 60000002053 | C306: 61044200000 | D306: ԱՂՋԿԱ ՇՐՋԱԶԳԵՍՏՆԵՐ ԲԱՄԲԱԿԵ ՄԱՆՎԱԾՔԻՑ | E306: =PROPER(F306) -> Զգեստ | F306: զգեստ | G306: =VLOOKUP(E306,subcategory!A:B,2,0) -> 43 | H306: աղջկա | I306: =VLOOKUP(H306,gender!A:B,2,0) -> #N/A | J306: 110 | K306: 110 | L306: 1 | M306: CHICCO | N306: =VLOOKUP(M306,brand!A:B,2,0) -> 608 | O306: =UPPER(Q306) -> INDIA | P306: =VLOOKUP(O306,country!A:B,2,0) -> 7505 | Q306: INDIA | R306: =PROPER(S306) -> Բամբակ | S306: բամբակ | T306: =VLOOKUP(R306,material!A:B,2,0) -> 9 | U306: chicco | W306: 15ամիս | X306: =VLOOKUP(W306,SIZE!A:B,2,0) -> #N/A | Y306: - | Z306: սպիտակ | AA306: =VLOOKUP(Z306,COLOR!A:B,2,0) -> 12
A307: 306 | B307: 60000002052 | C307: 61044200000 | D307: ԱՂՋԿԱ ՇՐՋԱԶԳԵՍՏՆԵՐ ԲԱՄԲԱԿԵ ՄԱՆՎԱԾՔԻՑ | E307: =PROPER(F307) -> Զգեստ | F307: զգեստ | G307: =VLOOKUP(E307,subcategory!A:B,2,0) -> 43 | H307: աղջկա | I307: =VLOOKUP(H307,gender!A:B,2,0) -> #N/A | J307: 145 | K307: 145 | L307: 1 | M307: CHICCO | N307: =VLOOKUP(M307,brand!A:B,2,0) -> 608 | O307: =UPPER(Q307) -> CHINA | P307: =VLOOKUP(O307,country!A:B,2,0) -> 7497 | Q307: CHINA | R307: =PROPER(S307) -> Բամբակ | S307: բամբակ | T307: =VLOOKUP(R307,material!A:B,2,0) -> 9 | U307: chicco | W307: 18ամիս | X307: =VLOOKUP(W307,SIZE!A:B,2,0) -> #N/A | Y307: 39,99 | Z307: սպիտակ | AA307: =VLOOKUP(Z307,COLOR!A:B,2,0) -> 12
A308: 307 | B308: 60000002051 | C308: 61112090000 | D308: ՏՂԱ ԵՐԵԽԱՅԻ ԲՈԴԻՆԵՐ ԲԱՄԲԱԿԵ ՄԱՆՎԱԾՔԻՑ ՄԻՆՉԵՎ 86 ՍՄ ՀԱՍԱԿ ՈՒՆԵՑՈՂ | E308: =PROPER(F308) -> Բոդի | F308: բոդի | G308: =VLOOKUP(E308,subcategory!A:B,2,0) -> 15 | H308: նորածին տղա | I308: =VLOOKUP(H308,gender!A:B,2,0) -> 7 | J308: 105 | K308: 105 | L308: 1 | M308: CHICCO | N308: =VLOOKUP(M308,brand!A:B,2,0) -> 608 | O308: =UPPER(Q308) -> PORTUGAL | P308: =VLOOKUP(O308,country!A:B,2,0) -> 1810 | Q308: PORTUGAL | R308: =PROPER(S308) -> Բամբակ | S308: բամբակ | T308: =VLOOKUP(R308,material!A:B,2,0) -> 9 | U308: chicco | W308: 1տ. | X308: =VLOOKUP(W308,SIZE!A:B,2,0) -> #N/A | Y308: - | Z308: կապույտ | AA308: =VLOOKUP(Z308,COLOR!A:B,2,0) -> 5
A309: 308 | B309: 60000002050 | C309: 61112090000 | D309: ՏՂԱ ԵՐԵԽԱՅԻ ՇՈՐՏ ԻՐ ՎԵՐՆԱՇԱՊԻԿՈՎ ԲԱՄԲԱԿԵ ՄԱՆՎԱԾՔԻՑ ՄԻՆՉԵՎ 86 ՍՄ ՀԱՍԱԿ ՈՒՆԵՑՈՂ ՀԱՎԱՔԱԾՈՒ 2 ՀԱՏԻՑ | E309: =PROPER(F309) -> Շորտ+Վերնաշապիկ | F309: շորտ+վերնաշապիկ | G309: =VLOOKUP(E309,subcategory!A:B,2,0) -> #N/A | H309: նորածին տղա | I309: =VLOOKUP(H309,gender!A:B,2,0) -> 7 | J309: 185 | K309: 185 | L309: 1 | M309: CHICCO | N309: =VLOOKUP(M309,brand!A:B,2,0) -> 608 | O309: =UPPER(Q309) -> INDIA | P309: =VLOOKUP(O309,country!A:B,2,0) -> 7505 | Q309: INDIA | R309: =PROPER(S309) -> Բամբակ | S309: բամբակ | T309: =VLOOKUP(R309,material!A:B,2,0) -> 9 | U309: chicco | W309: 6ամիս | X309: =VLOOKUP(W309,SIZE!A:B,2,0) -> #N/A | Y309: - | Z309: սպիտակ | AA309: =VLOOKUP(Z309,COLOR!A:B,2,0) -> 12
... A385: 384 | B385: 60000001972 | C385: 61034200090 | D385: ՏՂԱՅԻ ՇՈՐՏԵՐ ԲԱՄԲԱԿԵ ՄԱՆՎԱԾՔԻՑ | E385: =PROPER(F385) -> Շորտ | F385: շորտ | G385: =VLOOKUP(E385,subcategory!A:B,2,0) -> 24 | H385: տղա | I385: =VLOOKUP(H385,gender!A:B,2,0) -> #N/A | J385: 85 | K385: 85 | L385: 1 | M385: CHICCO | N385: =VLOOKUP(M385,brand!A:B,2,0) -> 608 | O385: =UPPER(Q385) -> INDIA | P385: =VLOOKUP(O385,country!A:B,2,0) -> 7505 | Q385: INDIA | R385: =PROPER(S385) -> Բամբակ | S385: բամբակ | T385: =VLOOKUP(R385,material!A:B,2,0) -> 9 | U385: chicco | W385: 3տ. | X385: =VLOOKUP(W385,SIZE!A:B,2,0) -> #N/A | Y385: 25,99 | Z385: կապույտ | AA385: =VLOOKUP(Z385,COLOR!A:B,2,0) -> 5
A386: 385 | B386: 60000001971 | C386: 61159500000 | D386: ՏՂԱՅԻ ԳՈՒԼՊԱՆԵՐ ԲԱՄԲԱԿԵ ՄԱՆՎԱԾՔԻՑ | E386: =PROPER(F386) -> Գուլպա | F386: գուլպա | G386: =VLOOKUP(E386,subcategory!A:B,2,0) -> #N/A | H386: տղա | I386: =VLOOKUP(H386,gender!A:B,2,0) -> #N/A | J386: 40 | K386: 40 | L386: 1 | M386: CHICCO | N386: =VLOOKUP(M386,brand!A:B,2,0) -> 608 | O386: =UPPER(Q386) -> ITALY | P386: =VLOOKUP(O386,country!A:B,2,0) -> 1760 | Q386: ITALY | R386: =PROPER(S386) -> Բամբակ | S386: բամբակ | T386: =VLOOKUP(R386,material!A:B,2,0) -> 9 | U386: chicco | W386: 22 | X386: =VLOOKUP(W386,SIZE!A:B,2,0) -> 14 | Y386: 6,99 | Z386: կարմիր | AA386: =VLOOKUP(Z386,COLOR!A:B,2,0) -> 1
A387: 386 | B387: 60000001970 | C387: 61112090000 | D387: ՏՂԱ ԵՐԵԽԱՅԻ ՏԱԲԱՏՆԵՐ ԲԱՄԲԱԿԵ ՄԱՆՎԱԾՔԻՑ ՄԻՆՉԵՎ 86 ՍՄ ՀԱՍԱԿ ՈՒՆԵՑՈՂ | E387: =PROPER(F387) -> Տաբատներ | F387: տաբատներ | G387: =VLOOKUP(E387,subcategory!A:B,2,0) -> 93 | H387: նորածին տղա | I387: =VLOOKUP(H387,gender!A:B,2,0) -> 7 | J387: 110 | K387: 110 | L387: 1 | M387: CHICCO | N387: =VLOOKUP(M387,brand!A:B,2,0) -> 608 | O387: =UPPER(Q387) -> INDIA | P387: =VLOOKUP(O387,country!A:B,2,0) -> 7505 | Q387: INDIA | R387: =PROPER(S387) -> Բամբակ | S387: բամբակ | T387: =VLOOKUP(R387,material!A:B,2,0) -> 9 | U387: chicco | W387: 9ամիս | X387: =VLOOKUP(W387,SIZE!A:B,2,0) -> #N/A | Y387: 25,99 | Z387: կապույտ | AA387: =VLOOKUP(Z387,COLOR!A:B,2,0) -> 5
A388: 387 | B388: 60000001969 | C388: 61112090000 | D388: ԱՂՋԻԿ ԵՐԵԽԱՅԻ ՇՐՋԱԶԳԵՍՏՆԵՐ ԲԱՄԲԱԿԵ ՄԱՆՎԱԾՔԻՑ ՄԻՆՉԵՎ 86 ՍՄ ՀԱՍԱԿ ՈՒՆԵՑՈՂ | E388: =PROPER(F388) -> Սառաֆան | F388: սառաֆան | G388: =VLOOKUP(E388,subcategory!A:B,2,0) -> #N/A | H388: նորածին աղջկա | I388: =VLOOKUP(H388,gender!A:B,2,0) -> #N/A | J388: 155 | K388: 155 | L388: 1 | M388: CHICCO | N388: =VLOOKUP(M388,brand!A:B,2,0) -> 608 | O388: =UPPER(Q388) -> INDIA | P388: =VLOOKUP(O388,country!A:B,2,0) -> 7505 | Q388: INDIA | R388: =PROPER(S388) -> Բամբակ | S388: բամբակ | T388: =VLOOKUP(R388,material!A:B,2,0) -> 9 | U388: chicco | W388: 12ամիս | X388: =VLOOKUP(W388,SIZE!A:B,2,0) -> #N/A | Y388: 27,99 | Z388: կապույտ | AA388: =VLOOKUP(Z388,COLOR!A:B,2,0) -> 5
A389: 388 | B389: 60000001968 | C389: 61112090000 | D389: ՏՂԱ ԵՐԵԽԱՅԻ ՏԱԲԱՏՆԵՐ ԲԱՄԲԱԿԵ ՄԱՆՎԱԾՔԻՑ ՄԻՆՉԵՎ 86 ՍՄ ՀԱՍԱԿ ՈՒՆԵՑՈՂ | E389: =PROPER(F389) -> Տաբատներ | F389: տաբատներ | G389: =VLOOKUP(E389,subcategory!A:B,2,0) -> 93 | H389: նորածին տղա | I389: =VLOOKUP(H389,gender!A:B,2,0) -> 7 | J389: 35 | K389: 35 | L389: 1 | M389: CHICCO | N389: =VLOOKUP(M389,brand!A:B,2,0) -> 608 | O389: =UPPER(Q389) -> CHINA | P389: =VLOOKUP(O389,country!A:B,2,0) -> 7497 | Q389: CHINA | R389: =PROPER(S389) -> Բամբակ | S389: բամբակ | T389: =VLOOKUP(R389,material!A:B,2,0) -> 9 | U389: chicco | W389: 1ամիս | X389: =VLOOKUP(W389,SIZE!A:B,2,0) -> #N/A | Y389: - | Z389: բաց կապույտ | AA389: =VLOOKUP(Z389,COLOR!A:B,2,0) -> 29
A390: 389 | B390: 60000001967 | C390: 61112090000 | D390: ՏՂԱ ԵՐԵԽԱՅԻ ՇՈՐՏԵՐ ԲԱՄԲԱԿԵ ՄԱՆՎԱԾՔԻՑ ՄԻՆՉԵՎ 86 ՍՄ ՀԱՍԱԿ ՈՒՆԵՑՈՂ | E390: =PROPER(F390) -> Շորտ | F390: շորտ | G390: =VLOOKUP(E390,subcategory!A:B,2,0) -> 24 | H390: նորածին տղա | I390: =VLOOKUP(H390,gender!A:B,2,0) -> 7 | J390: 30 | K390: 30 | L390: 1 | M390: CHICCO | N390: =VLOOKUP(M390,brand!A:B,2,0) -> 608 | O390: =UPPER(Q390) -> CHINA | P390: =VLOOKUP(O390,country!A:B,2,0) -> 7497 | Q390: CHINA | R390: =PROPER(S390) -> Բամբակ | S390: բամբակ | T390: =VLOOKUP(R390,material!A:B,2,0) -> 9 | U390: chicco | W390: 1ամիս | X390: =VLOOKUP(W390,SIZE!A:B,2,0) -> #N/A | Y390: - | Z390: բաց կապույտ | AA390: =VLOOKUP(Z390,COLOR!A:B,2,0) -> 29
A391: 390 | B391: 60000001966 | C391: 61034200090 | D391: ՏՂԱՅԻ ՇՈՐՏԵՐ ԲԱՄԲԱԿԵ ՄԱՆՎԱԾՔԻՑ | E391: =PROPER(F391) -> Շորտ | F391: շորտ | G391: =VLOOKUP(E391,subcategory!A:B,2,0) -> 24 | H391: տղա | I391: =VLOOKUP(H391,gender!A:B,2,0) -> #N/A | J391: 70 | K391: 70 | L391: 1 | M391: CHICCO | N391: =VLOOKUP(M391,brand!A:B,2,0) -> 608 | O391: =UPPER(Q391) -> INDIA | P391: =VLOOKUP(O391,country!A:B,2,0) -> 7505 | Q391: INDIA | R391: =PROPER(S391) -> Բամբակ | S391: բամբակ | T391: =VLOOKUP(R391,material!A:B,2,0) -> 9 | U391: chicco | W391: 18ամիս | X391: =VLOOKUP(W391,SIZE!A:B,2,0) -> #N/A | Y391: 22,99 | Z391: կապույտ | AA391: =VLOOKUP(Z391,COLOR!A:B,2,0) -> 5
A392: 391 | B392: 60000001965 | C392: 61112090000 | D392: ՏՂԱ ԵՐԵԽԱՅԻ ԿԱՄԲԻՆԻԶՈՆ ԲԱՄԲԱԿԵ ՄԱՆՎԱԾՔԻՑ ՄԻՆՉԵՎ 86 ՍՄ ՀԱՍԱԿ ՈՒՆԵՑՈՂ | E392: =PROPER(F392) -> Կոմբինեզոն | F392: կոմբինեզոն | G392: =VLOOKUP(E392,subcategory!A:B,2,0) -> 54 | H392: նորածին տղա | I392: =VLOOKUP(H392,gender!A:B,2,0) -> 7 | J392: 90 | K392: 90 | L392: 1 | M392: CHICCO | N392: =VLOOKUP(M392,brand!A:B,2,0) -> 608 | O392: =UPPER(Q392) -> CHINA | P392: =VLOOKUP(O392,country!A:B,2,0) -> 7497 | Q392: CHINA | R392: =PROPER(S392) -> Բամբակ | S392: բամբակ | T392: =VLOOKUP(R392,material!A:B,2,0) -> 9 | U392: chicco | W392: 6ամիս | X392: =VLOOKUP(W392,SIZE!A:B,2,0) -> #N/A | Y392: 35,99 | Z392: կապույտ | AA392: =VLOOKUP(Z392,COLOR!A:B,2,0) -> 5
A393: 392 | B393: 60000001964 | C393: 61112090000 | D393: ՏՂԱ ԵՐԵԽԱՅԻ ԲՈԴԻՆԵՐ ԲԱՄԲԱԿԵ ՄԱՆՎԱԾՔԻՑ ՄԻՆՉԵՎ 86 ՍՄ ՀԱՍԱԿ ՈՒՆԵՑՈՂ | E393: =PROPER(F393) -> Բոդի | F393: բոդի | G393: =VLOOKUP(E393,subcategory!A:B,2,0) -> 15 | H393: նորածին տղա | I393: =VLOOKUP(H393,gender!A:B,2,0) -> 7 | J393: 100 | K393: 100 | L393: 1 | M393: CHICCO | N393: =VLOOKUP(M393,brand!A:B,2,0) -> 608 | O393: =UPPER(Q393) -> CHINA | P393: =VLOOKUP(O393,country!A:B,2,0) -> 7497 | Q393: CHINA | R393: =PROPER(S393) -> Բամբակ | S393: բամբակ | T393: =VLOOKUP(R393,material!A:B,2,0) -> 9 | U393: chicco | W393: 1ամիս | X393: =VLOOKUP(W393,SIZE!A:B,2,0) -> #N/A | Y393: - | Z393: սպիտակ | AA393: =VLOOKUP(Z393,COLOR!A:B,2,0) -> 12
A394: 393 | B394: 60000001963 | C394: 61112090000 | D394: ԱՂՋԻԿ ԵՐԵԽԱՅԻ ԲՈԴԻՆԵՐ ԲԱՄԲԱԿԵ ՄԱՆՎԱԾՔԻՑ ՄԻՆՉԵՎ 86 ՍՄ ՀԱՍԱԿ ՈՒՆԵՑՈՂ | E394: =PROPER(F394) -> Բոդի | F394: բոդի | G394: =VLOOKUP(E394,subcategory!A:B,2,0) -> 15 | H394: նորածին աղջկա | I394: =VLOOKUP(H394,gender!A:B,2,0) -> #N/A | J394: 95 | K394: 95 | L394: 1 | M394: CHICCO | N394: =VLOOKUP(M394,brand!A:B,2,0) -> 608 | O394: =UPPER(Q394) -> CHINA | P394: =VLOOKUP(O394,country!A:B,2,0) -> 7497 | Q394: CHINA | R394: =PROPER(S394) -> Բամբակ | S394: բամբակ | T394: =VLOOKUP(R394,material!A:B,2,0) -> 9 | U394: chicco | W394: 1ամիս | X394: =VLOOKUP(W394,SIZE!A:B,2,0) -> #N/A | Y394: - | Z394: սպիտակ | AA394: =VLOOKUP(Z394,COLOR!A:B,2,0) -> 12
A395: 394 | B395: 60000001962 | C395: 61051000000 | D395: ՏՂԱՅԻ ՎԵՐՆԱՇԱՊԻԿՆԵՐ ԲԱՄԲԱԿԵ ՄԱՆՎԱԾՔԻՑ | E395: =PROPER(F395) -> Վերնաշապիկ | F395: վերնաշապիկ | G395: =VLOOKUP(E395,subcategory!A:B,2,0) -> 82 | H395: տղա | I395: =VLOOKUP(H395,gender!A:B,2,0) -> #N/A | J395: 180 | K395: 180 | L395: 1 | M395: CHICCO | N395: =VLOOKUP(M395,brand!A:B,2,0) -> 608 | O395: =UPPER(Q395) -> INDIA | P395: =VLOOKUP(O395,country!A:B,2,0) -> 7505 | Q395: INDIA | R395: =PROPER(S395) -> Բամբակ | S395: բամբակ | T395: =VLOOKUP(R395,material!A:B,2,0) -> 9 | U395: chicco | W395: 5տ. | X395: =VLOOKUP(W395,SIZE!A:B,2,0) -> #N/A | Y395: 37,99 | Z395: սպիտակ | AA395: =VLOOKUP(Z395,COLOR!A:B,2,0) -> 12
A396: 395 | B396: 60000001961 | C396: 61112090000 | D396: ՏՂԱ ԵՐԵԽԱՅԻ ՎԵՐՆԱՇԱՊԻԿՆԵՐ ԲԱՄԲԱԿԵ ՄԱՆՎԱԾՔԻՑ ՄԻՆՉԵՎ 86 ՍՄ ՀԱՍԱԿ ՈՒՆԵՑՈՂ ՀԱՎԱՔԱԾՈՒ 2 ՀԱՏԻՑ | E396: =PROPER(F396) -> Վերնաշապիկ | F396: վերնաշապիկ | G396: =VLOOKUP(E396,subcategory!A:B,2,0) -> 82 | H396: նորածին տղա | I396: =VLOOKUP(H396,gender!A:B,2,0) -> 7 | J396: 75 | K396: 75 | L396: 1 | M396: CHICCO | N396: =VLOOKUP(M396,brand!A:B,2,0) -> 608 | O396: =UPPER(Q396) -> INDIA | P396: =VLOOKUP(O396,country!A:B,2,0) -> 7505 | Q396: INDIA | R396: =PROPER(S396) -> Բամբակ | S396: բամբակ | T396: =VLOOKUP(R396,material!A:B,2,0) -> 9 | U396: chicco | W396: 6ամիս | X396: =VLOOKUP(W396,SIZE!A:B,2,0) -> #N/A | Y396: 29,99 | Z396: սպիտակ | AA396: =VLOOKUP(Z396,COLOR!A:B,2,0) -> 12
A397: 396 | B397: 60000001960 | C397: 61051000000 | D397: ՏՂԱՅԻ ՎԵՐՆԱՇԱՊԻԿՆԵՐ ԲԱՄԲԱԿԵ ՄԱՆՎԱԾՔԻՑ | E397: =PROPER(F397) -> Վերնաշապիկ | F397: վերնաշապիկ | G397: =VLOOKUP(E397,subcategory!A:B,2,0) -> 82 | H397: տղա | I397: =VLOOKUP(H397,gender!A:B,2,0) -> #N/A | J397: 85 | K397: 85 | L397: 1 | M397: CHICCO | N397: =VLOOKUP(M397,brand!A:B,2,0) -> 608 | O397: =UPPER(Q397) -> CHINA | P397: =VLOOKUP(O397,country!A:B,2,0) -> 7497 | Q397: CHINA | R397: =PROPER(S397) -> Բամբակ | S397: բամբակ | T397: =VLOOKUP(R397,material!A:B,2,0) -> 9 | U397: chicco | W397: 18ամիս | X397: =VLOOKUP(W397,SIZE!A:B,2,0) -> #N/A | Y397: - | Z397: սպիտակ | AA397: =VLOOKUP(Z397,COLOR!A:B,2,0) -> 12
A398: 397 | B398: 60000001959 | C398: 61112090000 | D398: ԱՂՋԻԿ ԵՐԵԽԱՅԻ ՇՐՋԱԶԳԵՍՏՆԵՐ ԲԱՄԲԱԿԵ ՄԱՆՎԱԾՔԻՑ ՄԻՆՉԵՎ 86 ՍՄ ՀԱՍԱԿ ՈՒՆԵՑՈՂ | E398: =PROPER(F398) -> Զգեստ | F398: զգեստ | G398: =VLOOKUP(E398,subcategory!A:B,2,0) -> 43 | H398: նորածին աղջկա | I398: =VLOOKUP(H398,gender!A:B,2,0) -> #N/A | J398: 120 | K398: 120 | L398: 1 | M398: CHICCO | N398: =VLOOKUP(M398,brand!A:B,2,0) -> 608 | O398: =UPPER(Q398) -> CHINA | P398: =VLOOKUP(O398,country!A:B,2,0) -> 7497 | Q398: CHINA | R398: =PROPER(S398) -> Բամբակ | S398: բամբակ | T398: =VLOOKUP(R398,material!A:B,2,0) -> 9 | U398: chicco | W398: 6ամիս | X398: =VLOOKUP(W398,SIZE!A:B,2,0) -> #N/A | Y398: 37,99 | Z398: վարդագույն | AA398: =VLOOKUP(Z398,COLOR!A:B,2,0) -> 13
... A424: 423 | B424: 60000001927 | C424: 64029991000 | D424: ՏՂԱՅԻ ԿՈՇԻԿ ԱՐՀԵՍՏԱԿԱՆ ԿԱՇՎԵ ԵՎ ՏԵՔՍՏԻԼԵ ԵՐԵՍԱՄԱՍՈՎ , ՌԵՏԻՆԵ ԿՈՇԿԱՏԱԿՈՎ ՄԻՆՉԵՎ 24ՍՄ ՆԵՐԲԱՆԻ ԵՐԿԱՐՈՒԹՅԱՄԲ | E424: =PROPER(F424) -> Կոշիկ | F424: կոշիկ | G424: =VLOOKUP(E424,subcategory!A:B,2,0) -> 55 | H424: տղա | I424: =VLOOKUP(H424,gender!A:B,2,0) -> #N/A | J424: 100 | K424: 100 | L424: 1 | M424: CHICCO | N424: =VLOOKUP(M424,brand!A:B,2,0) -> 608 | O424: =UPPER(Q424) -> CHINA | P424: =VLOOKUP(O424,country!A:B,2,0) -> 7497 | Q424: CHINA | R424: =PROPER(S424) -> Արհ. Կաշի, Տեքստիլ | S424: արհ. կաշի, տեքստիլ | T424: =VLOOKUP(R424,material!A:B,2,0) -> #N/A | U424: chicco | W424: 18ամիս | X424: =VLOOKUP(W424,SIZE!A:B,2,0) -> #N/A | Y424: 14,99 | Z424: կապույտ | AA424: =VLOOKUP(Z424,COLOR!A:B,2,0) -> 5
A425: 424 | B425: 60000001926 | C425: 64052099000 | D425: ԱՂՋԿԱ ԿՈՇԻԿ ՏԵՔՍՏԻԼԵ | E425: =PROPER(F425) -> Կոշիկ | F425: կոշիկ | G425: =VLOOKUP(E425,subcategory!A:B,2,0) -> 55 | H425: աղջկա | I425: =VLOOKUP(H425,gender!A:B,2,0) -> #N/A | J425: 95 | K425: 95 | L425: 1 | M425: CHICCO | N425: =VLOOKUP(M425,brand!A:B,2,0) -> 608 | O425: =UPPER(Q425) -> CHINA | P425: =VLOOKUP(O425,country!A:B,2,0) -> 7497 | Q425: CHINA | R425: =PROPER(S425) -> Կտոր, Տեքստիլ | S425: կտոր, տեքստիլ | T425: =VLOOKUP(R425,material!A:B,2,0) -> #N/A | U425: chicco | W425: 18 | X425: =VLOOKUP(W425,SIZE!A:B,2,0) -> 2 | Y425: 14,99 | Z425: սպիտակ | AA425: =VLOOKUP(Z425,COLOR!A:B,2,0) -> 12
A426: 425 | B426: 60000001925 | C426: 64029991000 | D426: ԱՂՋԿԱ ԿՈՇԻԿՆԵՐ ԱՐՀԵՍՏԱԿԱՆ ԿԱՇՎԵ ԵՎ ՏԵՔՍՏԻԼԵ ԵՐԵՍԱՄԱՍՈՎ, ՌԵՏԻՆԵ ԿՈՇԿԱՏԱԿՈՎ ՄԻՆՉԵՎ 24ՍՄ ՆԵՐԲԱՆԻ ԵՐԿԱՐՈՒԹՅԱՄԲ | E426: =PROPER(F426) -> Կոշիկ | F426: կոշիկ | G426: =VLOOKUP(E426,subcategory!A:B,2,0) -> 55 | H426: աղջկա | I426: =VLOOKUP(H426,gender!A:B,2,0) -> #N/A | J426: 85 | K426: 85 | L426: 1 | M426: CHICCO | N426: =VLOOKUP(M426,brand!A:B,2,0) -> 608 | O426: =UPPER(Q426) -> CHINA | P426: =VLOOKUP(O426,country!A:B,2,0) -> 7497 | Q426: CHINA | R426: =PROPER(S426) -> Արհ. Կաշի, Տեքստիլ | S426: արհ. կաշի, տեքստիլ | T426: =VLOOKUP(R426,material!A:B,2,0) -> #N/A | U426: chicco | W426: 16 | X426: =VLOOKUP(W426,SIZE!A:B,2,0) -> 9 | Y426: 19,99 | Z426: ոսկեգույն | AA426: =VLOOKUP(Z426,COLOR!A:B,2,0) -> 21
A427: 426 | B427: 60000001934 | C427: 61112090000 | D427: ՏՂԱ ԵՐԵԽԱՅԻ ԿԱՄԲԻՆԻԶՈՆՆԵՐ ԲԱՄԲԱԿԵ ՄԱՆՎԱԾՔԻՑ ՄԻՆՉԵՎ 86 ՍՄ ՀԱՍԱԿ ՈՒՆԵՑՈՂ | E427: =PROPER(F427) -> Կոմբինեզոն | F427: կոմբինեզոն | G427: =VLOOKUP(E427,subcategory!A:B,2,0) -> 54 | H427: նորածին տղա | I427: =VLOOKUP(H427,gender!A:B,2,0) -> 7 | J427: 170 | K427: 170 | L427: 1 | M427: CHICCO | N427: =VLOOKUP(M427,brand!A:B,2,0) -> 608 | O427: =UPPER(Q427) -> PORTUGAL | P427: =VLOOKUP(O427,country!A:B,2,0) -> 1810 | Q427: PORTUGAL | R427: =PROPER(S427) -> Բամբակ/Մոդալ | S427: բամբակ/մոդալ | T427: =VLOOKUP(R427,material!A:B,2,0) -> 9-57 | U427: chicco | W427: 1ամիս | X427: =VLOOKUP(W427,SIZE!A:B,2,0) -> #N/A | Y427: 59,99 | Z427: սպիտակ | AA427: =VLOOKUP(Z427,COLOR!A:B,2,0) -> 12
A428: 427 | B428: 60000001932 | C428: 61112090000 | D428: ԱՂՋԻԿ ԵՐԵԽԱՅԻ ԳԼԽԱՐԿ, ԳՈԳՆՈՑ ԿԱՄԲԻՆԻԶՈՆ ԲԱՄԲԱԿԵ ՄԱՆՎԱԾՔԻՑ ՄԻՆՉԵՎ 86 ՍՄ ՀԱՍԱԿ ՈՒՆԵՑՈՂ | E428: =PROPER(F428) -> Գլխարկ+Գոգնոց+Կոմբինեզոն | F428: գլխարկ+գոգնոց+կոմբինեզոն | G428: =VLOOKUP(E428,subcategory!A:B,2,0) -> #N/A | H428: նորածին աղջկա | I428: =VLOOKUP(H428,gender!A:B,2,0) -> #N/A | J428: 285 | K428: 285 | L428: 1 | M428: CHICCO | N428: =VLOOKUP(M428,brand!A:B,2,0) -> 608 | O428: =UPPER(Q428) -> CHINA | P428: =VLOOKUP(O428,country!A:B,2,0) -> 7497 | Q428: CHINA | R428: =PROPER(S428) -> Բամբակ | S428: բամբակ | T428: =VLOOKUP(R428,material!A:B,2,0) -> 9 | U428: chicco | W428: 3ամիս | X428: =VLOOKUP(W428,SIZE!A:B,2,0) -> #N/A | Y428: - | Z428: վարդագույն | AA428: =VLOOKUP(Z428,COLOR!A:B,2,0) -> 13
A429: 428 | B429: 60000001931 | C429: 61178080090 | D429: ԱՂՋԿԱ ԳԼԽԱԴԻՐ (ԱԲԱԴՈԿ) ՏԵՔՍՏԻԼԵ | E429: =PROPER(F429) -> Աբադոկ | F429: աբադոկ | G429: =VLOOKUP(E429,subcategory!A:B,2,0) -> 168 | H429: աղջկա | I429: =VLOOKUP(H429,gender!A:B,2,0) -> #N/A | J429: 15 | K429: 15 | L429: 1 | M429: CHICCO | N429: =VLOOKUP(M429,brand!A:B,2,0) -> 608 | O429: =UPPER(Q429) -> CHINA | P429: =VLOOKUP(O429,country!A:B,2,0) -> 7497 | Q429: CHINA | R429: =PROPER(S429) -> Մետակ. Կտորից Ծածկույթ | S429: մետակ. կտորից ծածկույթ | T429: =VLOOKUP(R429,material!A:B,2,0) -> #N/A | U429: chicco | W429: one size | X429: =VLOOKUP(W429,SIZE!A:B,2,0) -> 311 | Y429: 7,99 | Z429: վարդագույն | AA429: =VLOOKUP(Z429,COLOR!A:B,2,0) -> 13
A430: 429 | B430: 60000001930 | C430: 96159000000 | D430: ԱՂՋԿԱ ՄԱԶԱԿԱԼ | E430: =PROPER(F430) -> Մազակալ | F430: մազակալ | G430: =VLOOKUP(E430,subcategory!A:B,2,0) -> 34 | H430: աղջկա | I430: =VLOOKUP(H430,gender!A:B,2,0) -> #N/A | J430: 10 | K430: 10 | L430: 1 | M430: CHICCO | N430: =VLOOKUP(M430,brand!A:B,2,0) -> 608 | O430: =UPPER(Q430) -> CHINA | P430: =VLOOKUP(O430,country!A:B,2,0) -> 7497 | Q430: CHINA | R430: =PROPER(S430) -> Պոլիեսթեր-Երկարթ | S430: պոլիեսթեր-երկարթ | T430: =VLOOKUP(R430,material!A:B,2,0) -> #N/A | U430: chicco | W430: one size | X430: =VLOOKUP(W430,SIZE!A:B,2,0) -> 311 | Y430: 4,99 | Z430: սպիտակ | AA430: =VLOOKUP(Z430,COLOR!A:B,2,0) -> 12
A431: 430 | B431: 60000001929 | C431: 61159500000 | D431: ԱՂՋԿԱ ԳՈՒԼՊԱՆԵՐ ԲԱՄԲԱԿԵ ՄԱՆՎԱԾՔԻՑ | E431: =PROPER(F431) -> Գուլպա | F431: գուլպա | G431: =VLOOKUP(E431,subcategory!A:B,2,0) -> #N/A | H431: աղջկա | I431: =VLOOKUP(H431,gender!A:B,2,0) -> #N/A | J431: 15 | K431: 15 | L431: 1 | M431: CHICCO | N431: =VLOOKUP(M431,brand!A:B,2,0) -> 608 | O431: =UPPER(Q431) -> ITALY | P431: =VLOOKUP(O431,country!A:B,2,0) -> 1760 | Q431: ITALY | R431: =PROPER(S431) -> Բամբակ | S431: բամբակ | T431: =VLOOKUP(R431,material!A:B,2,0) -> 9 | U431: chicco | W431: 18ամիս | X431: =VLOOKUP(W431,SIZE!A:B,2,0) -> #N/A | Y431: 6,99 | Z431: սպիտակ | AA431: =VLOOKUP(Z431,COLOR!A:B,2,0) -> 12
...

Sheet ALL Exp-Asos
A1: N | B1: Code | C1: HS code | D1: name | E1: Sub-category | F1: Sub-category id | G1: Gender | H1: Gender id | I1: Netto | J1: pc | K1: Brutto | L1: Brand | M1: Brand id | N1: Country | O1: Country id | P1: Material | Q1: Material id | R1: Package | S1: Package Id | T1: Size | U1: Size id | V1: Original price | W1: Color | X1: Color id
A2: 1 | B2: 40000001111 | C2: 61102091000 | D2: ՏՂԱՄԱՐԴՈՒ ՀՈՒԴԻՆԵՐ ԲԱՄԲԱԿԵ ՄԱՆՎԱԾՔԻՑ | E2: Հուդի | F2: 18 | G2: Տղամարդկանց | H2: 1 | I2: 0.055 | J2: 1 | K2: 0.055 | L2: PETROL | M2: 881 | N2: BANGLADESH | O2: 7485 | P2: Բամբակ/Պոլիեսթեր | Q2: 9-37 | R2: Mix Brand | S2: 1000320 | T2: S | U2: 122 | V2: 0 | W2: Կապույտ | X2: 5
A3: 2 | B3: 40000001112 | C3: 61103091000 | D3: ՏՂԱՄԱՐԴՈՒ ՍՎԻՏՐԵՐ ՔԻՄԻԱԿԱՆ ԹԵԼԵՐԻՑ | E3: Սվիտրեր | F3: 88 | G3: Տղամարդկանց | H3: 1 | I3: 0.334 | J3: 1 | K3: 0.334 | L3: PETROL | M3: 881 | N3: BANGLADESH | O3: 7485 | P3: Բամբակ/Ակրիլ | Q3: 9-2 | R3: Mix Brand | S3: 1000320 | T3: S | U3: 122 | V3: 0 | W3: Կապույտ | X3: 5
A4: 3 | B4: 40000001113 | C4: 64041990000 | D4: ՏՂԱՄԱՐԴՈՒ ԿՈՇԻԿ ՏԵՔՏՍԻԼԵ ԵՐԵՍԱՄԱՍՈՎ ՌԵՏԻՆԵ ԿՈՇԿԱՏԱԿՈՎ | E4: Կոշիկ | F4: 55 | G4: Տղամարդկանց | H4: 1 | I4: 1.086 | J4: 1 | K4: 1.086 | L4: REGATTA | M4: 254 | N4: CHINA | O4: 7497 | P4: Տակացու Ռետին, Վրան Կտոր | Q4: 102-25 | R4: Mix Brand | S4: 1000320 | T4: 43 | U4: 289 | V4: 0 | W4: Կապույտ | X4: 5
A5: 4 | B5: 40000001114 | C5: 64041990000 | D5: ԿԱՆԱՑԻ ԿՈՇԻԿՆԵՐ ՏԵՔՏՍԻԼԵ ԵՐԵՍԱՄԱՍՈՎ ՌԵՏԻՆԵ ԿՈՇԿԱՏԱԿՈՎ | E5: Կոշիկ | F5: 55 | G5: Կանանց | H5: 2 | I5: 0.042 | J5: 1 | K5: 0.042 | L5: UNKNOWN | M5: 880 | N5: CHINA | O5: 7497 | P5: Տակացու Ռետին, Վրան Կտոր | Q5: 102-25 | R5: Mix Brand | S5: 1000320 | T5: 38 | U5: 64 | V5: 0 | W5: Սպիտակ | X5: 12
A6: 5 | B6: 40000001110 | C6: 62034235000 | D6: ՏՂԱՅԻ ՏԱԲԱՏՆԵՐ ԲԱՄԲԱԿԵ ՄԱՆՎԱԾՔԻՑ | E6: Տաբատներ | F6: 93 | G6: Տղաների | H6: 4 | I6: 0.304 | J6: 1 | K6: 0.304 | L6: S. OLIVER | M6: 17 | N6: BANGLADESH | O6: 7485 | P6: Բամբակ | Q6: 9 | R6: Mix Brand | S6: 1000320 | T6: US 12-13 | U6: 633 | V6: EUR 40 | W6: Կանաչ | X6: 4
A7: 6 | B7: 40000001109 | C7: 64039998000 | D7: ԿԱՆԱՑԻ ԿՈՇԻԿ ԲՆԱԿԱՆ ԿԱՇՎԵ ԵՐԵՍԱՄԱՍՈՎ , ՊՈԼԻՄԵՐԱՅԻՆ ԿՈՇԿԱՏԱԿՈՎ | E7: Կոշիկ | F7: 55 | G7: Կանանց | H7: 2 | I7: 0.85 | J7: 1 | K7: 1.418 | L7: RAGE AGE | M7: 882 | N7: POLAND | O7: 1805 | P7: Տակացու Պոլիմեր, Վրան Զամշ | Q7: 101-79 | R7: Mix Brand | S7: 1000320 | T7: 39 | U7: 275 | V7: 0 | W7: Կարմիր | X7: 1
A8: 7 | B8: 40000001108 | C8: 64041910000 | D8: ՏՂԱՄԱՐԴՈՒ ՀՈՂԱԹԱՓ ՏԵՔՍՏԻԼԵ ԵՐԵՍԱՄԱՍՈՎ , ՊՈԼԻՄԵՐԱՅԻՆ ԿՈՇԿԱՏՈՎ | E8: Հողաթափ | F8: 310 | G8: Unisex | H8: 5 | I8: 0.388 | J8: 1 | K8: 0.582 | L8: UGG | M8: 296 | N8: VIETNAM | O8: 7579 | P8: Բուրդ/Լիոսել | Q8: 11-54 | R8: Mix Brand | S8: 1000320 | T8: 41 | U8: 288 | V8: 0 | W8: Շագանակագույն | X8: 10
A9: 8 | B9: 40000001107 | C9: 62024000010 | D9: ԿԱՆԱՑԻ ՎԵՐԱՐԿՈՒՆԵՐ ՔԻՄԻԱԿԱՆ ԹԵԼԵՐԻՑ | E9: Վերարկու | F9: 92 | G9: Կանանց | H9: 2 | I9: 1.102 | J9: 1 | K9: 1.102 | L9: TOM TAILOR | M9: 5 | N9: VIETNAM | O9: 7579 | P9: Պոլիեսթեր | Q9: 37 | R9: Mix Brand | S9: 1000320 | T9: L | U9: 3 | V9: EUR 100 | W9: Վարդագույն | X9: 13
A10: 9 | B10: 40000001106 | C10: 61102091000 | D10: ՏՂԱՄԱՐԴՈՒ ԵՎ ՏՂԱՅԻ ՍՎԻՏՐԵՐ ԲԱՄԲԱԿԵ ՄԱՆՎԱԾՔԻՑ | E10: Սվիտրեր | F10: 88 | G10: Տղամարդկանց | H10: 1 | I10: 0.344 | J10: 1 | K10: 0.344 | L10: PETROL | M10: 881 | N10: BANGLADESH | O10: 7485 | P10: Բամբակ/Ակրիլ | Q10: 9-2 | R10: Mix Brand | S10: 1000320 | T10: M | U10: 119 | V10: EUR 60 | W10: Կանաչ | X10: 4
A11: 10 | B11: 40000001105 | C11: 62014000000 | D11: ՏՂԱՄԱՐԴՈՒ ՎԵՐԱՐԿՈՒՆԵՐ ՔԻՄԻԱԿԱՆ ԹԵԼԵՐԻՑ | E11: Վերարկու | F11: 92 | G11: Տղամարդկանց | H11: 1 | I11: 1.136 | J11: 1 | K11: 1.136 | L11: PETROL | M11: 881 | N11: CHINA | O11: 7497 | P11: Պոլիեսթեր | Q11: 37 | R11: Mix Brand | S11: 1000320 | T11: XL | U11: 124 | V11: EUR 120 | W11: Սև | X11: 20
A12: 11 | B12: 40000001104 | C12: 62014000000 | D12: ՏՂԱՄԱՐԴՈՒ ՎԵՐԱՐԿՈՒՆԵՐ ՔԻՄԻԱԿԱՆ ԹԵԼԵՐԻՑ | E12: Վերարկու | F12: 92 | G12: Տղամարդկանց | H12: 1 | I12: 1.194 | J12: 1 | K12: 1.194 | L12: PETROL | M12: 881 | N12: CHINA | O12: 7497 | P12: Պոլիեսթեր | Q12: 37 | R12: Mix Brand | S12: 1000320 | T12: L | U12: 3 | V12: EUR 120 | W12: Սև | X12: 20
A13: 12 | B13: 40000001103 | C13: 62014000000 | D13: ՏՂԱՄԱՐԴՈՒ ՎԵՐԱՐԿՈՒՆԵՐ ՔԻՄԻԱԿԱՆ ԹԵԼԵՐԻՑ | E13: Վերարկու | F13: 92 | G13: Տղամարդկանց | H13: 1 | I13: 1.076 | J13: 1 | K13: 1.076 | L13: PETROL | M13: 881 | N13: CHINA | O13: 7497 | P13: Պոլիեսթեր | Q13: 37 | R13: Mix Brand | S13: 1000320 | T13: L | U13: 3 | V13: EUR 120 | W13: Կապույտ | X13: 5
A14: 13 | B14: 40000001102 | C14: 62014000000 | D14: ՏՂԱՄԱՐԴՈՒ ՎԵՐԱՐԿՈՒՆԵՐ ՔԻՄԻԱԿԱՆ ԹԵԼԵՐԻՑ | E14: Վերարկու | F14: 92 | G14: Տղամարդկանց | H14: 1 | I14: 1.038 | J14: 1 | K14: 1.038 | L14: PETROL | M14: 881 | N14: CHINA | O14: 7497 | P14: Պոլիեսթեր | Q14: 37 | R14: Mix Brand | S14: 1000320 | T14: M | U14: 119 | V14: EUR 120 | W14: Սև | X14: 20
A15: 14 | B15: 40000001101 | C15: 62024000010 | D15: ԿԱՆԱՑԻ ՎԵՐԱՐԿՈՒՆԵՐ ՔԻՄԻԱԿԱՆ ԹԵԼԵՐԻՑ | E15: Վերարկու | F15: 92 | G15: Կանանց | H15: 2 | I15: 1.06 | J15: 1 | K15: 1.06 | L15: TOM TAILOR | M15: 5 | N15: VIETNAM | O15: 7579 | P15: Պոլիեսթեր | Q15: 37 | R15: Mix Brand | S15: 1000320 | T15: L | U15: 3 | V15: EUR 100 | W15: Վարդագույն | X15: 13
A16: 15 | B16: 40000001100 | C16: 61102091000 | D16: ՏՂԱՄԱՐԴՈՒ ՀՈՒԴԻՆԵՐ ԲԱՄԲԱԿԵ ՄԱՆՎԱԾՔԻՑ | E16: Հուդի | F16: 18 | G16: Տղամարդկանց | H16: 1 | I16: 0.926 | J16: 1 | K16: 0.926 | L16: CARHARTT | M16: 791 | N16: PAKISTAN | O16: 7550 | P16: Բամբակ/Պոլիեսթեր | Q16: 9-37 | R16: Mix Brand | S16: 1000320 | T16: XL | U16: 124 | V16: 0 | W16: Կանաչ | X16: 4
A17: 16 | B17: 40000001099 | C17: 61102091000 | D17: ՏՂԱՄԱՐԴՈՒ ՀՈՒԴԻՆԵՐ ԲԱՄԲԱԿԵ ՄԱՆՎԱԾՔԻՑ | E17: Հուդի | F17: 18 | G17: Տղամարդկանց | H17: 1 | I17: 0.854 | J17: 1 | K17: 0.854 | L17: CARHARTT | M17: 791 | N17: PAKISTAN | O17: 7550 | P17: Բամբակ/Պոլիեսթեր | Q17: 9-37 | R17: Mix Brand | S17: 1000320 | T17: M | U17: 119 | V17: 0 | W17: Կանաչ | X17: 4
A18: 17 | B18: 40000001098 | C18: 61102091000 | D18: ՏՂԱՄԱՐԴՈՒ ԵՎ ՏՂԱՅԻ ՍՎԻՏՐԵՐ ԲԱՄԲԱԿԵ ՄԱՆՎԱԾՔԻՑ | E18: Սվիտրեր | F18: 88 | G18: Տղամարդկանց | H18: 1 | I18: 0.402 | J18: 1 | K18: 0.402 | L18: PETROL | M18: 881 | N18: BANGLADESH | O18: 7485 | P18: Բամբակ/Ակրիլ | Q18: 9-2 | R18: Mix Brand | S18: 1000320 | T18: XL | U18: 124 | V18: EUR 60 | W18: Կապույտ | X18: 5
A19: 18 | B19: 40000001097 | C19: 62013000000 | D19: ՏՂԱՄԱՐԴՈՒ ՎԵՐԱՐԿՈՒՆԵՐ ԲԱՄԲԱԿԵ ՄԱՆՎԱԾՔԻՑ | E19: Վերարկու | F19: 92 | G19: Տղամարդկանց | H19: 1 | I19: 0.556 | J19: 1 | K19: 0.556 | L19: PETROL | M19: 881 | N19: CHINA | O19: 7497 | P19: Բամբակ/Պոլիեսթեր | Q19: 9-37 | R19: Mix Brand | S19: 1000320 | T19: M | U19: 119 | V19: EUR 90 | W19: Սև | X19: 20
A20: 19 | B20: 40000001096 | C20: 62013000000 | D20: ՏՂԱՄԱՐԴՈՒ ՎԵՐԱՐԿՈՒ ԲԱՄԲԱԿԵ ՄԱՆՎԱԾՔԻՑ | E20: Վերարկու | F20: 92 | G20: Տղամարդկանց | H20: 1 | I20: 0.466 | J20: 1 | K20: 0.466 | L20: PETROL | M20: 881 | N20: BANGLADESH | O20: 7485 | P20: Բամբակ/Ակրիլ | Q20: 9-2 | R20: Mix Brand | S20: 1000320 | T20: XL | U20: 124 | V20: EUR 70 | W20: Սև | X20: 20
A21: 20 | B21: 40000001095 | C21: 64039991000 | D21: ՏՂԱՅԻ ԿՈՇԻԿ ԲՆԱԿԱՆ ԶԱՄՇԵ ԵՐԵՍԱՄԱՍՈՎ , ՊՈԼԻՄԵՐԱՅԻՆ ԿՈՇԿԱՏԱԿՈՎ ՄԻՆՉԵՎ 24ՍՄ ՆԵՐԲԱՆԻ ԵՐԿԱՐՈՒԹՅԱՄԲ | E21: Կոշիկ | F21: 55 | G21: Տղաների | H21: 4 | I21: 0.348 | J21: 1 | K21: 0.526 | L21: GEOX | M21: 883 | N21: ITALY | O21: 1760 | P21: Տակացու Պոլիմեր, Վրան Զամշ | Q21: 101-79 | R21: Mix Brand | S21: 1000320 | T21: 31 | U21: 140 | V21: EUR 31 | W21: Կապույտ | X21: 5
A22: 21 | B22: 40000001094 | C22: 64029991000 | D22: ԱՂՋԿԱ ԲՈԿՈՏԻԿ ԱՐՀԵՍՏԱԿԱՆ ԿԱՇՎԵ ԵՐԵՍԱՄԱՍՈՎ , ՌԵՏԻՆԵ ԿՈՇԿԱՏԱԿՈՎ ՄԻՆՉԵՎ 24ՍՄ ՆԵՐԲԱՆԻ ԵՐԿԱՐՈՒԹՅԱՄԲ | E22: Սանդալ | F22: 66 | G22: Աղջիկների | H22: 3 | I22: 0.326 | J22: 1 | K22: 0.48 | L22: CHICCO | M22: 608 | N22: CHINA | O22: 7497 | P22: Պոլիուրեթան | Q22: 104 | R22: Mix Brand | S22: 1000320 | T22: 31 | U22: 140 | V22: 0 | W22: Սպիտակ | X22: 12
A23: 22 | B23: 40000001093 | C23: 61091000000 | D23: ՏՂԱՄԱՐԴՈՒ ԵՎ ՏՂԱՅԻ ՇԱՊԻԿՆԵՐ ԲԱՄԲԱԿԵ ՄԱՆՎԱԾՔԻՑ | E23: Շապիկ | F23: 73 | G23: Տղամարդկանց | H23: 1 | I23: 0.162 | J23: 1 | K23: 0.162 | L23: PETROL | M23: 881 | N23: BANGLADESH | O23: 7485 | P23: Բամբակ | Q23: 9 | R23: Mix Brand | S23: 1000320 | T23: XL | U23: 124 | V23: EUR 20 | W23: Կապույտ | X23: 5
A24: 23 | B24: 40000001092 | C24: 61102091000 | D24: ՏՂԱՄԱՐԴՈՒ ՀՈՒԴԻՆԵՐ ԲԱՄԲԱԿԵ ՄԱՆՎԱԾՔԻՑ | E24: Հուդի | F24: 18 | G24: Տղամարդկանց | H24: 1 | I24: 0.576 | J24: 1 | K24: 0.576 | L24: PETROL | M24: 881 | N24: BANGLADESH | O24: 7485 | P24: Բամբակ | Q24: 9 | R24: Mix Brand | S24: 1000320 | T24: M | U24: 119 | V24: EUR 46 | W24: Կապույտ | X24: 5
A25: 24 | B25: 40000001091 | C25: 61051000000 | D25: ՏՂԱՄԱՐԴՈՒ ՎԵՐՆԱՇԱՊԻԿՆԵՐ ԲԱՄԲԱԿԵ ՄԱՆՎԱԾՔԻՑ | E25: Վերնաշապիկ | F25: 82 | G25: Տղամարդկանց | H25: 1 | I25: 0.236 | J25: 1 | K25: 0.236 | L25: PETROL | M25: 881 | N25: BANGLADESH | O25: 7485 | P25: Բամբակ | Q25: 9 | R25: Mix Brand | S25: 1000320 | T25: L | U25: 3 | V25: EUR 60 | W25: Գույնզգույն | X25: 17
A26: 25 | B26: 40000001090 | C26: 61051000000 | D26: ՏՂԱՄԱՐԴՈՒ ԵՎ ՏՂԱՅԻ ՎԵՐՆԱՇԱՊԻԿՆԵՐ ԲԱՄԲԱԿԵ ՄԱՆՎԱԾՔԻՑ | E26: Վերնաշապիկ | F26: 82 | G26: Տղամարդկանց | H26: 1 | I26: 0.466 | J26: 1 | K26: 0.466 | L26: PETROL | M26: 881 | N26: INDIA | O26: 7505 | P26: Բամբակ | Q26: 9 | R26: Mix Brand | S26: 1000320 | T26: M | U26: 119 | V26: EUR 80 | W26: Գույնզգույն | X26: 17
A27: 26 | B27: 40000001089 | C27: 62013000000 | D27: ՏՂԱՄԱՐԴՈՒ ՎԵՐԱՐԿՈՒՆԵՐ ԲԱՄԲԱԿԵ ՄԱՆՎԱԾՔԻՑ | E27: Վերարկու | F27: 92 | G27: Տղամարդկանց | H27: 1 | I27: 0.516 | J27: 1 | K27: 0.516 | L27: PETROL | M27: 881 | N27: CHINA | O27: 7497 | P27: Բամբակ | Q27: 9 | R27: Mix Brand | S27: 1000320 | T27: S | U27: 122 | V27: EUR 90 | W27: Կաթնագույն | X27: 23
A28: 27 | B28: 40000001088 | C28: 61102091000 | D28: ՏՂԱՄԱՐԴՈՒ ՀՈՒԴԻՆԵՐ ԲԱՄԲԱԿԵ ՄԱՆՎԱԾՔԻՑ | E28: Հուդի | F28: 18 | G28: Տղամարդկանց | H28: 1 | I28: 0.62 | J28: 1 | K28: 0.62 | L28: PETROL | M28: 881 | N28: BANGLADESH | O28: 7485 | P28: Բամբակ/Ակրիլ | Q28: 9-2 | R28: Mix Brand | S28: 1000320 | T28: M | U28: 119 | V28: EUR 90 | W28: Կաթնագույն | X28: 23
A29: 28 | B29: 40000001087 | C29: 61091000000 | D29: ՏՂԱՄԱՐԴՈՒ ԵՎ ՏՂԱՅԻ ՇԱՊԻԿՆԵՐ ԲԱՄԲԱԿԵ ՄԱՆՎԱԾՔԻՑ | E29: Շապիկ | F29: 73 | G29: Տղամարդկանց | H29: 1 | I29: 0.202 | J29: 1 | K29: 0.202 | L29: PETROL | M29: 881 | N29: BANGLADESH | O29: 7485 | P29: Բամբակ | Q29: 9 | R29: Mix Brand | S29: 1000320 | T29: XL | U29: 124 | V29: EUR 28 | W29: Կաթնագույն | X29: 23
A30: 29 | B30: 40000001086 | C30: 61102091000 | D30: ՏՂԱՄԱՐԴՈՒ ԵՎ ՏՂԱՅԻ ՍՎԻՏՐԵՐ ԲԱՄԲԱԿԵ ՄԱՆՎԱԾՔԻՑ | E30: Սվիտրեր | F30: 88 | G30: Տղամարդկանց | H30: 1 | I30: 0.474 | J30: 1 | K30: 0.474 | L30: PETROL | M30: 881 | N30: BANGLADESH | O30: 7485 | P30: Բամբակ | Q30: 9 | R30: Mix Brand | S30: 1000320 | T30: L | U30: 3 | V30: EUR 50 | W30: Կաթնագույն | X30: 23
A31: 30 | B31: 40000001085 | C31: 61102091000 | D31: ՏՂԱՄԱՐԴՈՒ ՀՈՒԴԻՆԵՐ ԲԱՄԲԱԿԵ ՄԱՆՎԱԾՔԻՑ | E31: Հուդի | F31: 18 | G31: Տղամարդկանց | H31: 1 | I31: 0.634 | J31: 1 | K31: 0.634 | L31: PETROL | M31: 881 | N31: BANGLADESH | O31: 7485 | P31: Բամբակ | Q31: 9 | R31: Mix Brand | S31: 1000320 | T31: L | U31: 3 | V31: EUR 60 | W31: Կապույտ | X31: 5
A32: 31 | B32: 40000001084 | C32: 61102091000 | D32: ՏՂԱՄԱՐԴՈՒ ԵՎ ՏՂԱՅԻ ՍՎԻՏՐԵՐ ԲԱՄԲԱԿԵ ՄԱՆՎԱԾՔԻՑ | E32: Սվիտրեր | F32: 88 | G32: Տղամարդկանց | H32: 1 | I32: 0.494 | J32: 1 | K32: 0.494 | L32: PETROL | M32: 881 | N32: BANGLADESH | O32: 7485 | P32: Բամբակ | Q32: 9 | R32: Mix Brand | S32: 1000320 | T32: S | U32: 122 | V32: EUR 50 | W32: Կապույտ | X32: 5
A33: 32 | B33: 40000001083 | C33: 61045300000 | D33: ԿԱՆԱՑԻ ԵՎ ԱՂՋԿԱ ԿԻՍԱՇՐՋԱԶԳԵՍՏՆԵՐ ՍԻՆԹԵՏԻԿ ԹԵԼԵՐԻՑ | E33: Կիսաշրջազգեստ | F33: 53 | G33: Կանանց | H33: 2 | I33: 0.226 | J33: 1 | K33: 0.226 | L33: ONLY | M33: 28 | N33: CHINA | O33: 7497 | P33: Պոլիեսթեր | Q33: 37 | R33: Mix Brand | S33: 1000320 | T33: S | U33: 122 | V33: EUR 35 | W33: Սև | X33: 20
A34: 33 | B34: 40000001082 | C34: 62013000000 | D34: ՏՂԱՄԱՐԴՈՒ ՎԵՐԱՐԿՈՒ ԲԱՄԲԱԿԵ ՄԱՆՎԱԾՔԻՑ | E34: Վերարկու | F34: 92 | G34: Տղամարդկանց | H34: 1 | I34: 1.268 | J34: 1 | K34: 1.268 | L34: PETROL | M34: 881 | N34: PAKISTAN | O34: 7550 | P34: Բամբակ/Պոլիեսթեր | Q34: 9-37 | R34: Mix Brand | S34: 1000320 | T34: XL | U34: 124 | V34: EUR 100 | W34: Կանաչ | X34: 4
A35: 34 | B35: 40000001081 | C35: 62034235000 | D35: ՏՂԱՅԻ ՏԱԲԱՏՆԵՐ ԲԱՄԲԱԿԵ ՄԱՆՎԱԾՔԻՑ | E35: Տաբատներ | F35: 93 | G35: Տղաների | H35: 4 | I35: 0.424 | J35: 1 | K35: 0.424 | L35: TIMBERLAND | M35: 457 | N35: BANGLADESH | O35: 7485 | P35: Բամբակ | Q35: 9 | R35: Mix Brand | S35: 1000320 | T35: 36 | U35: 52 | V35: 0 | W35: Սև | X35: 20
A36: 35 | B36: 40000001080 | C36: 64039991000 | D36: ՏՂԱՅԻ ԲՈԿՈՏԻԿ ԲՆԱԿԱՆ ԿԱՇՎԵ ԵՐԵՍԱՄԱՍՈՎ , ՊՈԼԻՄԵՐԱՅԻՆ ԿՈՇԿԱՏԱԿՈՎ ՄԻՆՉԵՎ 24ՍՄ ՆԵՐԲԱՆԻ ԵՐԿԱՐՈՒԹՅԱՄԲ | E36: Սանդալ | F36: 66 | G36: Տղաների | H36: 4 | I36: 0.092 | J36: 1 | K36: 0.092 | L36: CHICCO | M36: 608 | N36: ITALY | O36: 1760 | P36: Տակացու Պոլիմեր, Վրան Կաշի | Q36: 101-20 | R36: Mix Brand | S36: 1000320 | T36: 18 | U36: 2 | V36: 0 | W36: Կապույտ | X36: 5
A37: 36 | B37: 40000001079 | C37: 64029991000 | D37: ԱՂՋԿԱ ԲՈԿՈՏԻԿՆԵՐ ԱՐՀԵՍՏԱԿԱՆ ԿԱՇՎԵ ԵՐԵՍԱՄԱՍՈՎ , ՌԵՏԻՆԵ ԿՈՇԿԱՏԱԿՈՎ ՄԻՆՉԵՎ 24ՍՄ ՆԵՐԲԱՆԻ ԵՐԿԱՐՈՒԹՅԱՄԲ | E37: Սանդալ | F37: 66 | G37: Կանանց | H37: 2 | I37: 0.104 | J37: 1 | K37: 0.104 | L37: CHICCO | M37: 608 | N37: ITALY | O37: 1760 | P37: Պոլիեսթեր | Q37: 37 | R37: Mix Brand | S37: 1000320 | T37: 19 | U37: 370 | V37: EUR 17 (ZEXCHOV 11) | W37: Վարդագույն | X37: 13
A38: 37 | B38: 40000001078 | C38: 64052099000 | D38: ՏՂԱՅԻ ԲՈԿՈՏԻԿՆԵՐ ՏԵՔՍՏԻԼԵ | E38: Սանդալ | F38: 66 | G38: Տղաների | H38: 4 | I38: 0.1 | J38: 1 | K38: 0.1 | L38: CHICCO | M38: 608 | N38: ITALY | O38: 1760 | P38: Բամբակ | Q38: 9 | R38: Mix Brand | S38: 1000320 | T38: 19 | U38: 370 | V38: EUR 15 | W38: Կապույտ | X38: 5
A39: 38 | B39: 40000001077 | C39: 64052099000 | D39: ՏՂԱՅԻ ԲՈԿՈՏԻԿՆԵՐ ՏԵՔՍՏԻԼԵ | E39: Սանդալ | F39: 66 | G39: Տղաների | H39: 4 | I39: 0.096 | J39: 1 | K39: 0.096 | L39: CHICCO | M39: 608 | N39: ITALY | O39: 1760 | P39: Բամբակ | Q39: 9 | R39: Mix Brand | S39: 1000320 | T39: 18 | U39: 2 | V39: EUR 15 | W39: Կապույտ | X39: 5
A40: 39 | B40: 40000001076 | C40: 64029991000 | D40: ԱՂՋԿԱ ԲՈԿՈՏԻԿՆԵՐ ԱՐՀԵՍՏԱԿԱՆ ԿԱՇՎԵ ԵՐԵՍԱՄԱՍՈՎ , ՌԵՏԻՆԵ ԿՈՇԿԱՏԱԿՈՎ ՄԻՆՉԵՎ 24ՍՄ ՆԵՐԲԱՆԻ ԵՐԿԱՐՈՒԹՅԱՄԲ | E40: Սանդալ | F40: 66 | G40: Կանանց | H40: 2 | I40: 0.088 | J40: 1 | K40: 0.088 | L40: CHICCO | M40: 608 | N40: ITALY | O40: 1760 | P40: Պոլիեսթեր | Q40: 37 | R40: Mix Brand | S40: 1000320 | T40: 18 | U40: 2 | V40: EUR 20 | W40: Արծաթագույն | X40: 22
A41: 40 | B41: 40000001075 | C41: 64052099000 | D41: ԱՂՋԿԱ ԿՈՇԻԿ ՏԵՔՍՏԻԼԵ | E41: Կոշիկ | F41: 55 | G41: Աղջիկների | H41: 3 | I41: 0.078 | J41: 1 | K41: 0.078 | L41: CHICCO | M41: 608 | N41: ITALY | O41: 1760 | P41: Բամբակ/Տակացու Տեքստիլ | Q41: 9-69 | R41: Mix Brand | S41: 1000320 | T41: 18 | U41: 2 | V41: EUR 15 | W41: Սպիտակ | X41: 12
A42: 41 | B42: 40000001074 | C42: 64039991000 | D42: ԱՂՋԿԱ ԿՈՇԻԿ ԲՆԱԿԱՆ ԿԱՇՎԵ ԵՐԵՍԱՄԱՍՈՎ , ՊՈԼԻՄԵՐԱՅԻՆ ԿՈՇԿԱՏԱԿՈՎ ՄԻՆՉԵՎ 24ՍՄ ՆԵՐԲԱՆԻ ԵՐԿԱՐՈՒԹՅԱՄԲ | E42: Կոշիկ | F42: 55 | G42: Աղջիկների | H42: 3 | I42: 0.182 | J42: 1 | K42: 0.182 | L42: CHICCO | M42: 608 | N42: ITALY | O42: 1760 | P42: Տակացու Պոլիմեր, Վրան Կաշի | Q42: 101-20 | R42: Mix Brand | S42: 1000320 | T42: 19 | U42: 370 | V42: 0 | W42: Արծաթագույն | X42: 22
A43: 42 | B43: 40000001073 | C43: 61091000000 | D43: ԿԱՆԱՑԻ ԵՎ ԱՂՋԿԱ ՇԱՊԻԿՆԵՐ ԲԱՄԲԱԿԵ ՄԱՆՎԱԾՔԻՑ | E43: Շապիկ | F43: 73 | G43: Կանանց | H43: 2 | I43: 0.134 | J43: 1 | K43: 0.134 | L43: CAVALLI | M43: 767 | N43: BANGLADESH | O43: 7485 | P43: Բամբակ | Q43: 9 | R43: Mix Brand | S43: 1000320 | T43: L | U43: 3 | V43: 0 | W43: Սև | X43: 20
A44: 43 | B44: 40000001072 | C44: 61051000000 | D44: ՏՂԱՄԱՐԴՈՒ ԵՎ ՏՂԱՅԻ ՎԵՐՆԱՇԱՊԻԿՆԵՐ ԲԱՄԲԱԿԵ ՄԱՆՎԱԾՔԻՑ | E44: Վերնաշապիկ | F44: 82 | G44: Տղամարդկանց | H44: 1 | I44: 0.328 | J44: 1 | K44: 0.328 | L44: PETROL | M44: 881 | N44: INDIA | O44: 7505 | P44: Բամբակ | Q44: 9 | R44: Mix Brand | S44: 1000320 | T44: M | U44: 119 | V44: EUR 70 | W44: Կապույտ | X44: 5
A45: 44 | B45: 40000001071 | C45: 61091000000 | D45: ԿԱՆԱՑԻ ԵՎ ԱՂՋԿԱ ՇԱՊԻԿՆԵՐ ԲԱՄԲԱԿԵ ՄԱՆՎԱԾՔԻՑ | E45: Շապիկ | F45: 73 | G45: Կանանց | H45: 2 | I45: 0.132 | J45: 1 | K45: 0.132 | L45: CAVALLI | M45: 767 | N45: BANGLADESH | O45: 7485 | P45: Բամբակ | Q45: 9 | R45: Mix Brand | S45: 1000320 | T45: L | U45: 3 | V45: 0 | W45: Սև | X45: 20
A46: 45 | B46: 40000001070 | C46: 61091000000 | D46: ԿԱՆԱՑԻ ԵՎ ԱՂՋԿԱ ՇԱՊԻԿՆԵՐ ԲԱՄԲԱԿԵ ՄԱՆՎԱԾՔԻՑ | E46: Շապիկ | F46: 73 | G46: Կանանց | H46: 2 | I46: 0.114 | J46: 1 | K46: 0.114 | L46: CAVALLI | M46: 767 | N46: BANGLADESH | O46: 7485 | P46: Բամբակ | Q46: 9 | R46: Mix Brand | S46: 1000320 | T46: M | U46: 119 | V46: 0 | W46: Սպիտակ | X46: 12
A47: 46 | B47: 40000001069 | C47: 61091000000 | D47: ԿԱՆԱՑԻ ԵՎ ԱՂՋԿԱ ՇԱՊԻԿՆԵՐ ԲԱՄԲԱԿԵ ՄԱՆՎԱԾՔԻՑ | E47: Շապիկ | F47: 73 | G47: Կանանց | H47: 2 | I47: 0.134 | J47: 1 | K47: 0.134 | L47: CAVALLI | M47: 767 | N47: BANGLADESH | O47: 7485 | P47: Բամբակ | Q47: 9 | R47: Mix Brand | S47: 1000320 | T47: L | U47: 3 | V47: 0 | W47: Սպիտակ | X47: 12
A48: 47 | B48: 40000001068 | C48: 61091000000 | D48: ԿԱՆԱՑԻ ԵՎ ԱՂՋԿԱ ՇԱՊԻԿՆԵՐ ԲԱՄԲԱԿԵ ՄԱՆՎԱԾՔԻՑ | E48: Շապիկ | F48: 73 | G48: Կանանց | H48: 2 | I48: 0.142 | J48: 1 | K48: 0.142 | L48: CAVALLI | M48: 767 | N48: BANGLADESH | O48: 7485 | P48: Բամբակ | Q48: 9 | R48: Mix Brand | S48: 1000320 | T48: XL | U48: 124 | V48: 0 | W48: Սպիտակ | X48: 12
A49: 48 | B49: 40000001067 | C49: 61091000000 | D49: ԿԱՆԱՑԻ ԵՎ ԱՂՋԿԱ ՇԱՊԻԿՆԵՐ ԲԱՄԲԱԿԵ ՄԱՆՎԱԾՔԻՑ | E49: Շապիկ | F49: 73 | G49: Կանանց | H49: 2 | I49: 0.142 | J49: 1 | K49: 0.142 | L49: CAVALLI | M49: 767 | N49: BANGLADESH | O49: 7485 | P49: Բամբակ | Q49: 9 | R49: Mix Brand | S49: 1000320 | T49: L | U49: 3 | V49: 0 | W49: Սպիտակ | X49: 12
A50: 49 | B50: 40000001066 | C50: 61091000000 | D50: ԿԱՆԱՑԻ ԵՎ ԱՂՋԿԱ ՇԱՊԻԿՆԵՐ ԲԱՄԲԱԿԵ ՄԱՆՎԱԾՔԻՑ | E50: Շապիկ | F50: 73 | G50: Կանանց | H50: 2 | I50: 0.108 | J50: 1 | K50: 0.108 | L50: CAVALLI | M50: 767 | N50: BANGLADESH | O50: 7485 | P50: Բամբակ | Q50: 9 | R50: Mix Brand | S50: 1000320 | T50: S | U50: 122 | V50: 0 | W50: Սպիտակ | X50: 12
A51: 50 | B51: 40000001065 | C51: 61091000000 | D51: ԿԱՆԱՑԻ ԵՎ ԱՂՋԿԱ ՇԱՊԻԿՆԵՐ ԲԱՄԲԱԿԵ ՄԱՆՎԱԾՔԻՑ | E51: Շապիկ | F51: 73 | G51: Կանանց | H51: 2 | I51: 0.152 | J51: 1 | K51: 0.152 | L51: CAVALLI | M51: 767 | N51: BANGLADESH | O51: 7485 | P51: Բամբակ | Q51: 9 | R51: Mix Brand | S51: 1000320 | T51: XS | U51: 1 | V51: 0 | W51: Կապույտ | X51: 5
A52: 51 | B52: 40000001064 | C52: 61091000000 | D52: ՏՂԱՄԱՐԴՈՒ ԵՎ ՏՂԱՅԻ ՇԱՊԻԿՆԵՐ ԲԱՄԲԱԿԵ ՄԱՆՎԱԾՔԻՑ | E52: Շապիկ | F52: 73 | G52: Տղամարդկանց | H52: 1 | I52: 0.176 | J52: 1 | K52: 0.176 | L52: PETROL | M52: 881 | N52: BANGLADESH | O52: 7485 | P52: Բամբակ | Q52: 9 | R52: Mix Brand | S52: 1000320 | T52: M | U52: 119 | V52: EUR 28 | W52: Կապույտ | X52: 5
A53: 52 | B53: 40000001063 | C53: 62034235000 | D53: ՏՂԱՄԱՐԴՈՒ ԵՎ ՏՂԱՅԻ ՏԱԲԱՏՆԵՐ ԲԱՄԲԱԿԵ ՄԱՆՎԱԾՔԻՑ | E53: Տաբատներ | F53: 93 | G53: Տղաների | H53: 4 | I53: 0.634 | J53: 1 | K53: 0.634 | L53: PETROL | M53: 881 | N53: PAKISTAN | O53: 7550 | P53: Բամբակ | Q53: 9 | R53: Mix Brand | S53: 1000320 | T53: 29 L32 | U53: 648 | V53: EUR 70 | W53: Կապույտ | X53: 5
A54: 53 | B54: 40000001062 | C54: 61033300000 | D54: ՏՂԱՄԱՐԴՈՒ ԺԱԿԵՏ ՍԻՆԹԵՏԻԿ ԹԵԼԵՐԻՑ | E54: Ժակետ | F54: 466 | G54: Տղամարդկանց | H54: 1 | I54: 0.476 | J54: 1 | K54: 0.476 | L54: PATAGONIA | M54: 898 | N54: NICARAGUA | O54: 5315 | P54: Պոլիեսթեր | Q54: 37 | R54: Mix Brand | S54: 1000320 | T54: M | U54: 119 | V54: 0 | W54: Մոխրագույն | X54: 8
A55: 54 | B55: 40000001061 | C55: 61103099000 | D55: ԿԱՆԱՑԻ ՍՎԻՏՐԵՐ ՔԻՄԱԿԱՆ ԹԵԼԵՐԻՑ | E55: Սվիտրեր | F55: 88 | G55: Կանանց | H55: 2 | I55: 0.344 | J55: 1 | K55: 0.344 | L55: TOM TAILOR | M55: 5 | N55: CHINA | O55: 7497 | P55: Պոլիակրիլ | Q55: 107 | R55: Mix Brand | S55: 1000320 | T55: XL | U55: 124 | V55: EUR 50 | W55: Սպիտակ | X55: 12
A56: 55 | B56: 40000001060 | C56: 62024000090 | D56: ԿԱՆԱՑԻ ԲԱՃԿՈՆ ՔԻՄԻԱԿԱՆ ԹԵԼԵՐԻՑ | E56: Բաճկոն | F56: 14 | G56: Կանանց | H56: 2 | I56: 0.848 | J56: 1 | K56: 0.848 | L56: TOM TAILOR | M56: 5 | N56: VIETNAM | O56: 7579 | P56: Պոլիեսթեր | Q56: 37 | R56: Mix Brand | S56: 1000320 | T56: XL | U56: 124 | V56: EUR 90 | W56: Սպիտակ | X56: 12
A57: 56 | B57: 40000001059 | C57: 62013000000 | D57: ՏՂԱՄԱՐԴՈՒ ԲԱՃԿՈՆ ԲԱՄԲԱԿԵ ՄԱՆՎԱԾՔԻՑ | E57: Բաճկոն | F57: 14 | G57: Տղամարդկանց | H57: 1 | I57: 0.944 | J57: 1 | K57: 0.944 | L57: PETROL | M57: 881 | N57: BANGLADESH | O57: 7485 | P57: Բամբակ | Q57: 9 | R57: Mix Brand | S57: 1000320 | T57: L | U57: 3 | V57: EUR 90 | W57: Կապույտ | X57: 5
A58: 57 | B58: 40000001058 | C58: 62034235000 | D58: ՏՂԱՅԻ ՏԱԲԱՏՆԵՐ ԲԱՄԲԱԿԵ ՄԱՆՎԱԾՔԻՑ | E58: Տաբատներ | F58: 93 | G58: Տղաների | H58: 4 | I58: 0.772 | J58: 1 | K58: 0.772 | L58: PETROL | M58: 881 | N58: BANGLADESH | O58: 7485 | P58: Բամբակ | Q58: 9 | R58: Mix Brand | S58: 1000320 | T58: 33 L34 | U58: 649 | V58: EUR 60 | W58: Կապույտ | X58: 5
A59: 58 | B59: 40000001057 | C59: 62034235000 | D59: ՏՂԱՅԻ ՏԱԲԱՏ ԲԱՄԲԱԿԵ ՄԱՆՎԱԾՔԻՑ | E59: Տաբատներ | F59: 93 | G59: Տղաների | H59: 4 | I59: 0.644 | J59: 1 | K59: 0.644 | L59: PETROL | M59: 881 | N59: TUNISIA | O59: 2185 | P59: Բամբակ | Q59: 9 | R59: Mix Brand | S59: 1000320 | T59: 30 L32 | U59: 650 | V59: EUR 70 | W59: Կապույտ | X59: 5
A60: 59 | B60: 40000001056 | C60: 61051000000 | D60: ՏՂԱՄԱՐԴՈՒ ԵՎ ՏՂԱՅԻ ՎԵՐՆԱՇԱՊԻԿՆԵՐ ԲԱՄԲԱԿԵ ՄԱՆՎԱԾՔԻՑ | E60: Վերնաշապիկ | F60: 82 | G60: Տղամարդկանց | H60: 1 | I60: 0.538 | J60: 1 | K60: 0.538 | L60: PETROL | M60: 881 | N60: INDIA | O60: 7505 | P60: Բամբակ | Q60: 9 | R60: Mix Brand | S60: 1000320 | T60: L | U60: 3 | V60: EUR 80 | W60: Գույնզգույն | X60: 17
A61: 60 | B61: 40000001055 | C61: 61033200000 | D61: ՏՂԱՄԱՐԴՈՒ ԺԱԿԵՏՆԵՐ ԲԱՄԲԱԿԵ ՄԱՆՎԱԾՔԻՑ | E61: Ժակետ | F61: 466 | G61: Տղամարդկանց | H61: 1 | I61: 0.712 | J61: 1 | K61: 0.712 | L61: S. OLIVER | M61: 17 | N61: BANGLADESH | O61: 7485 | P61: Բամբակ | Q61: 9 | R61: Mix Brand | S61: 1000320 | T61: US XL | U61: 651 | V61: EUR 70 | W61: Կապույտ | X61: 5
A62: 61 | B62: 40000001054 | C62: 61044200000 | D62: ԿԱՆԱՑԻ ԵՎ ԱՂՋԿԱ ՇՐՋԱԶԳԵՍՏՆԵՐ ԲԱՄԲԱԿԵ ՄԱՆՎԱԾՔԻՑ | E62: Զգեստ | F62: 43 | G62: Կանանց | H62: 2 | I62: 0.444 | J62: 1 | K62: 0.444 | L62: TOM TAILOR | M62: 5 | N62: BANGLADESH | O62: 7485 | P62: Բամբակ | Q62: 9 | R62: Mix Brand | S62: 1000320 | T62: XL | U62: 124 | V62: EUR 50 | W62: Սև | X62: 20
A63: 62 | B63: 40000001053 | C63: 61091000000 | D63: ՏՂԱՄԱՐԴՈՒ ԵՎ ՏՂԱՅԻ ՇԱՊԻԿՆԵՐ ԲԱՄԲԱԿԵ ՄԱՆՎԱԾՔԻՑ | E63: Շապիկ | F63: 73 | G63: Տղամարդկանց | H63: 1 | I63: 0.254 | J63: 1 | K63: 0.254 | L63: S. OLIVER | M63: 17 | N63: BANGLADESH | O63: 7485 | P63: Բամբակ | Q63: 9 | R63: Mix Brand | S63: 1000320 | T63: L | U63: 3 | V63: EUR 36 | W63: Մոխրագույն | X63: 8
A64: 63 | B64: 40000001052 | C64: 61091000000 | D64: ԿԱՆԱՑԻ ԵՎ ԱՂՋԿԱ ՇԱՊԻԿՆԵՐ ԲԱՄԲԱԿԵ ՄԱՆՎԱԾՔԻՑ | E64: Շապիկ | F64: 73 | G64: Կանանց | H64: 2 | I64: 0.16 | J64: 1 | K64: 0.16 | L64: S. OLIVER | M64: 17 | N64: BANGLADESH | O64: 7485 | P64: Բամբակ | Q64: 9 | R64: Mix Brand | S64: 1000320 | T64: 44 | U64: 95 | V64: EUR 20 | W64: Կարմիր | X64: 1
A65: 64 | B65: 40000001051 | C65: 62034235000 | D65: ՏՂԱՄԱՐԴՈՒ ԵՎ ՏՂԱՅԻ ՏԱԲԱՏՆԵՐ ԲԱՄԲԱԿԵ ՄԱՆՎԱԾՔԻՑ | E65: Տաբատներ | F65: 93 | G65: Տղաների | H65: 4 | I65: 0.582 | J65: 1 | K65: 0.582 | L65: PETROL | M65: 881 | N65: PAKISTAN | O65: 7550 | P65: Բամբակ | Q65: 9 | R65: Mix Brand | S65: 1000320 | T65: 32 L32 | U65: 652 | V65: EUR 70 | W65: Կապույտ | X65: 5
A66: 65 | B66: 40000001050 | C66: 61091000000 | D66: ՏՂԱՄԱՐԴՈՒ ԵՎ ՏՂԱՅԻ ՇԱՊԻԿՆԵՐ ԲԱՄԲԱԿԵ ՄԱՆՎԱԾՔԻՑ | E66: Շապիկ | F66: 73 | G66: Տղամարդկանց | H66: 1 | I66: 0.264 | J66: 1 | K66: 0.264 | L66: FRED PERRY | M66: 790 | N66: CHINA | O66: 7497 | P66: Բամբակ | Q66: 9 | R66: Mix Brand | S66: 1000320 | T66: L | U66: 3 | V66: 0 | W66: Սև | X66: 20
A67: 66 | B67: 40000001049 | C67: 61043300000 | D67: ԿԱՆԱՑԻ ԺԱԿԵՏՆԵՐ ՍԻՆԹԵՏԻԿ ԹԵԼԵՐԻՑ | E67: Ժակետ | F67: 466 | G67: Կանանց | H67: 2 | I67: 0.174 | J67: 1 | K67: 0.174 | L67: TOM TAILOR | M67: 5 | N67: CHINA | O67: 7497 | P67: Պոլիեսթեր | Q67: 37 | R67: Mix Brand | S67: 1000320 | T67: XL | U67: 124 | V67: EUR 50 | W67: Մոխրագույն | X67: 8
A68: 67 | B68: 40000001048 | C68: 62013000000 | D68: ՏՂԱՄԱՐԴՈՒ ԲԱՃԿՈՆ ԲԱՄԲԱԿԵ ՄԱՆՎԱԾՔԻՑ | E68: Բաճկոն | F68: 14 | G68: Տղամարդկանց | H68: 1 | I68: 0.562 | J68: 1 | K68: 0.562 | L68: PETROL | M68: 881 | N68: CHINA | O68: 7497 | P68: Բամբակ | Q68: 9 | R68: Mix Brand | S68: 1000320 | T68: M | U68: 119 | V68: EUR 90 | W68: Սև | X68: 20
A69: 68 | B69: 40000001047 | C69: 61043300000 | D69: ԿԱՆԱՑԻ ԺԱԿԵՏՆԵՐ ՍԻՆԹԵՏԻԿ ԹԵԼԵՐԻՑ | E69: Ժակետ | F69: 466 | G69: Կանանց | H69: 2 | I69: 0.384 | J69: 1 | K69: 0.384 | L69: TOM TAILOR | M69: 5 | N69: CHINA | O69: 7497 | P69: Պոլիեսթեր | Q69: 37 | R69: Mix Brand | S69: 1000320 | T69: 36 | U69: 52 | V69: EUR 80 | W69: Սև | X69: 20
A70: 69 | B70: 40000001046 | C70: 61099020000 | D70: ԿԱՆԱՑԻ ՇԱՊԻԿՆԵՐ ՔԻՄԻԱԿԱՆ ԹԵԼԵՐԻՑ | E70: Շապիկ | F70: 73 | G70: Կանանց | H70: 2 | I70: 0.154 | J70: 1 | K70: 0.154 | L70: TOM TAILOR | M70: 5 | N70: TURKEY | O70: 1840 | P70: Պոլիեսթեր | Q70: 37 | R70: Mix Brand | S70: 1000320 | T70: XL | U70: 124 | V70: EUR 30 | W70: Կանաչ | X70: 4
A71: 70 | B71: 40000001045 | C71: 61091000000 | D71: ԿԱՆԱՑԻ ԵՎ ԱՂՋԿԱ ՇԱՊԻԿՆԵՐ ԲԱՄԲԱԿԵ ՄԱՆՎԱԾՔԻՑ | E71: Շապիկ | F71: 73 | G71: Կանանց | H71: 2 | I71: 0.14 | J71: 1 | K71: 0.14 | L71: CAVALLI | M71: 767 | N71: BANGLADESH | O71: 7485 | P71: Բամբակ | Q71: 9 | R71: Mix Brand | S71: 1000320 | T71: XL | U71: 124 | V71: 0 | W71: Սև | X71: 20
A72: 71 | B72: 40000001044 | C72: 61043300000 | D72: ԿԱՆԱՑԻ ԺԱԿԵՏՆԵՐ ՍԻՆԹԵՏԻԿ ԹԵԼԵՐԻՑ | E72: Ժակետ | F72: 466 | G72: Կանանց | H72: 2 | I72: 0.416 | J72: 1 | K72: 0.416 | L72: PATAGONIA | M72: 898 | N72: SRI LANKA | O72: 7565 | P72: Պոլիեսթեր | Q72: 37 | R72: Mix Brand | S72: 1000320 | T72: S | U72: 122 | V72: 0 | W72: Կաթնագույն | X72: 23
A73: 72 | B73: 40000001043 | C73: 61091000000 | D73: ՏՂԱՄԱՐԴՈՒ ԵՎ ՏՂԱՅԻ ՇԱՊԻԿՆԵՐ ԲԱՄԲԱԿԵ ՄԱՆՎԱԾՔԻՑ | E73: Շապիկ | F73: 73 | G73: Տղամարդկանց | H73: 1 | I73: 0.282 | J73: 1 | K73: 0.282 | L73: S. OLIVER | M73: 17 | N73: BANGLADESH | O73: 7485 | P73: Բամբակ | Q73: 9 | R73: Mix Brand | S73: 1000320 | T73: XL | U73: 124 | V73: EUR 36 | W73: Մոխրագույն | X73: 8
A74: 73 | B74: 40000001042 | C74: 62046239000 | D74: ԿԱՆԱՑԻ ԵՎ ԱՂՋԿԱ ՏԱԲԱՏՆԵՐ ԲԱՄԲԱԿԵ ՄԱՆՎԱԾՔԻՑ | E74: Տաբատներ | F74: 93 | G74: Կանանց | H74: 2 | I74: 0.292 | J74: 1 | K74: 0.292 | L74: S. OLIVER | M74: 17 | N74: BANGLADESH | O74: 7485 | P74: Բամբակ | Q74: 9 | R74: Mix Brand | S74: 1000320 | T74: 146 | U74: 181 | V74: EUR 40 | W74: Սև | X74: 20
A75: 74 | B75: 40000001041 | C75: 62046239000 | D75: ԿԱՆԱՑԻ ԵՎ ԱՂՋԿԱ ՏԱԲԱՏՆԵՐ ԲԱՄԲԱԿԵ ՄԱՆՎԱԾՔԻՑ | E75: Տաբատներ | F75: 93 | G75: Կանանց | H75: 2 | I75: 0.26 | J75: 1 | K75: 0.26 | L75: S. OLIVER | M75: 17 | N75: BANGLADESH | O75: 7485 | P75: Բամբակ | Q75: 9 | R75: Mix Brand | S75: 1000320 | T75: 134 | U75: 164 | V75: EUR 40 | W75: Սև | X75: 20
A76: 75 | B76: 40000001040 | C76: 62034235000 | D76: ՏՂԱՅԻ ՏԱԲԱՏՆԵՐ ԲԱՄԲԱԿԵ ՄԱՆՎԱԾՔԻՑ | E76: Տաբատներ | F76: 93 | G76: Տղաների | H76: 4 | I76: 0.71 | J76: 1 | K76: 0.71 | L76: PETROL | M76: 881 | N76: BANGLADESH | O76: 7485 | P76: Բամբակ | Q76: 9 | R76: Mix Brand | S76: 1000320 | T76: 34 L34 | U76: 653 | V76: EUR 80 | W76: Կաթնագույն | X76: 23
A77: 76 | B77: 40000001039 | C77: 61033200000 | D77: ՏՂԱՄԱՐԴՈՒ ԺԱԿԵՏՆԵՐ ԲԱՄԲԱԿԵ ՄԱՆՎԱԾՔԻՑ | E77: Ժակետ | F77: 466 | G77: Տղամարդկանց | H77: 1 | I77: 0.394 | J77: 1 | K77: 0.394 | L77: PETROL | M77: 881 | N77: BANGLADESH | O77: 7485 | P77: Բամբակ/Ակրիլ | Q77: 9-2 | R77: Mix Brand | S77: 1000320 | T77: S | U77: 122 | V77: EUR 70 | W77: Կաթնագույն | X77: 23
A78: 77 | B78: 40000001038 | C78: 62013000000 | D78: ՏՂԱՄԱՐԴՈՒ ԲԱՃԿՈՆՆԵՐ ԲԱՄԲԱԿԵ ՄԱՆՎԱԾՔԻՑ | E78: Բաճկոն | F78: 14 | G78: Տղամարդկանց | H78: 1 | I78: 1.128 | J78: 1 | K78: 1.128 | L78: PETROL | M78: 881 | N78: PAKISTAN | O78: 7550 | P78: Բամբակ | Q78: 9 | R78: Mix Brand | S78: 1000320 | T78: M | U78: 119 | V78: EUR 100 | W78: Կանաչ | X78: 4
A79: 78 | B79: 40000001037 | C79: 62046318000 | D79: ԿԱՆԱՑԻ ՏԱԲԱՏՆԵՐ ՍԻՆԹԵՏԻԿ ԹԵԼԵՐԻՑ | E79: Տաբատներ | F79: 93 | G79: Կանանց | H79: 2 | I79: 0.642 | J79: 1 | K79: 0.642 | L79: S. OLIVER | M79: 17 | N79: CHINA | O79: 7497 | P79: Մոդալ/Պոլիեսթեր | Q79: 57-37 | R79: Mix Brand | S79: 1000320 | T79: 44 | U79: 95 | V79: EUR 80 | W79: Կաթնագույն | X79: 23
A80: 79 | B80: 40000001036 | C80: 61091000000 | D80: ԿԱՆԱՑԻ ԵՎ ԱՂՋԿԱ ՇԱՊԻԿՆԵՐ ԲԱՄԲԱԿԵ ՄԱՆՎԱԾՔԻՑ | E80: Շապիկ | F80: 73 | G80: Կանանց | H80: 2 | I80: 0.096 | J80: 1 | K80: 0.096 | L80: S. OLIVER | M80: 17 | N80: BANGLADESH | O80: 7485 | P80: Բամբակ | Q80: 9 | R80: Mix Brand | S80: 1000320 | T80: 128/134 | U80: 654 | V80: EUR 14 | W80: Սպիտակ | X80: 12
A81: 80 | B81: 40000001035 | C81: 61091000000 | D81: ՏՂԱՄԱՐԴՈՒ ԵՎ ՏՂԱՅԻ ՇԱՊԻԿՆԵՐ ԲԱՄԲԱԿԵ ՄԱՆՎԱԾՔԻՑ | E81: Շապիկ | F81: 73 | G81: Տղամարդկանց | H81: 1 | I81: 0.17 | J81: 1 | K81: 0.17 | L81: PETROL | M81: 881 | N81: BANGLADESH | O81: 7485 | P81: Բամբակ | Q81: 9 | R81: Mix Brand | S81: 1000320 | T81: XL | U81: 124 | V81: EUR 20 | W81: Կաթնագույն | X81: 23
A82: 81 | B82: 40000001034 | C82: 61091000000 | D82: ԿԱՆԱՑԻ ԵՎ ԱՂՋԿԱ ՇԱՊԻԿՆԵՐ ԲԱՄԲԱԿԵ ՄԱՆՎԱԾՔԻՑ | E82: Շապիկ | F82: 73 | G82: Կանանց | H82: 2 | I82: 0.092 | J82: 1 | K82: 0.092 | L82: S. OLIVER | M82: 17 | N82: BANGLADESH | O82: 7485 | P82: Բամբակ | Q82: 9 | R82: Mix Brand | S82: 1000320 | T82: 104/110 | U82: 655 | V82: EUR 30 | W82: Կապույտ | X82: 5
A83: 82 | B83: 40000001033 | C83: 61034200090 | D83: ՏՂԱՅԻ ՇՈՐՏԵՐ ԲԱՄԲԱԿԵ ՄԱՆՎԱԾՔԻՑ | E83: Շորտ | F83: 24 | G83: Տղաների | H83: 4 | I83: 0.36 | J83: 1 | K83: 0.36 | L83: S. OLIVER | M83: 17 | N83: BANGLADESH | O83: 7485 | P83: Բամբակ/Լիոսել | Q83: 9-54 | R83: Mix Brand | S83: 1000320 | T83: 158/BIG | U83: 656 | V83: EUR 36 | W83: Կապույտ | X83: 5
A84: 83 | B84: 40000001032 | C84: 61103091000 | D84: ՏՂԱՄԱՐԴՈՒ ՀՈՒԴԻ ՔԻՄԻԱԿԱՆ ԹԵԼԵՐԻՑ | E84: Հուդի | F84: 18 | G84: Unisex | H84: 5 | I84: 0.75 | J84: 1 | K84: 0.75 | L84: PATAGONIA | M84: 898 | N84: MEXICO | O84: 3220 | P84: Պոլիեսթեր/Բամբակ | Q84: 37-9 | R84: Mix Brand | S84: 1000320 | T84: w XL m L | U84: 657 | V84: 0 | W84: Կանաչ | X84: 4
A85: 84 | B85: 40000001031 | C85: 61091000000 | D85: ԿԱՆԱՑԻ ԵՎ ԱՂՋԿԱ ՇԱՊԻԿՆԵՐ ԲԱՄԲԱԿԵ ՄԱՆՎԱԾՔԻՑ | E85: Շապիկ | F85: 73 | G85: Կանանց | H85: 2 | I85: 0.118 | J85: 1 | K85: 0.118 | L85: S. OLIVER | M85: 17 | N85: BANGLADESH | O85: 7485 | P85: Բամբակ | Q85: 9 | R85: Mix Brand | S85: 1000320 | T85: 140 | U85: 162 | V85: EUR 30 | W85: Կապույտ | X85: 5
A86: 85 | B86: 40000001030 | C86: 65050090000 | D86: ՏՂԱՄԱՐԴՈՒ ԳԼԽԱՐԿՆԵՐ ՔԻՄԻԱԿԱՆ ԹԵԼԵՐԻՑ | E86: Գլխարկ | F86: 5 | G86: Տղամարդկանց | H86: 1 | I86: 0.172 | J86: 1 | K86: 0.172 | L86: PATAGONIA | M86: 898 | N86: VIETNAM | O86: 7579 | P86: Պոլիեսթեր | Q86: 37 | R86: Mix Brand | S86: 1000320 | T86: 0 | U86: 4 | V86: 0 | W86: Կապույտ | X86: 5
A87: 86 | B87: 40000001029 | C87: 61102091000 | D87: ՏՂԱՄԱՐԴՈՒ ՀՈՒԴԻՆԵՐ ԲԱՄԲԱԿԵ ՄԱՆՎԱԾՔԻՑ | E87: Հուդի | F87: 18 | G87: Տղամարդկանց | H87: 1 | I87: 0.726 | J87: 1 | K87: 0.726 | L87: PETROL | M87: 881 | N87: PAKISTAN | O87: 7550 | P87: Բամբակ | Q87: 9 | R87: Mix Brand | S87: 1000320 | T87: L | U87: 3 | V87: EUR 70 | W87: Կաթնագույն | X87: 23
A88: 87 | B88: 40000001028 | C88: 64029996000 | D88: ՏՂԱՄԱՐԴՈՒ ՍՊՈՐՏԱՅԻՆ ՈՃԻ ԿՈՇԻԿ ԱՐՀԵՍՏԱԿԱՆ ԿԱՇՎԵ ԵՐԵՍԱՄԱՍՈՎ , ՊՈԼԻՄԵՐԱՅԻՆ ԿՈՇԿԱՏԱԿՈՎ | E88: Սպորտային Կոշիկ | F88: 67 | G88: Տղամարդկանց | H88: 1 | I88: 0.698 | J88: 1 | K88: 0.906 | L88: 4F | M88: 884 | N88: CHINA | O88: 7497 | P88: Տակացու Պոլիմեր, Վրան Արհեստական Կաշի | Q88: 101-7 | R88: Mix Brand | S88: 1000320 | T88: 44 | U88: 95 | V88: 0 | W88: Կարմիր | X88: 1
A89: 88 | B89: 40000001027 | C89: 64029998000 | D89: ԿԱՆԱՑԻ ՍՊՈՐՏԱՅԻՆ ՈՃԻ ԿՈՇԻԿ ԱՐՀԵՍՏԱԿԱՆ ԿԱՇՎԵ ԵՐԵՍԱՄԱՍՈՎ , ՌԵՏԻՆԵ ԿՈՇԿԱՏԱԿՈՎ | E89: Սպորտային Կոշիկ | F89: 67 | G89: Կանանց | H89: 2 | I89: 0.546 | J89: 1 | K89: 0.72 | L89: ONLY | M89: 28 | N89: CHINA | O89: 7497 | P89: Տակացու Ռետին, Վրան Արհեստական Կաշի | Q89: 102-7 | R89: Mix Brand | S89: 1000320 | T89: 37 | U89: 282 | V89: 0 | W89: Վարդագույն | X89: 13
A90: 89 | B90: 40000001026 | C90: 64029998000 | D90: ԿԱՆԱՑԻ ՍՊՈՐՏԱՅԻՆ ՈՃԻ ԿՈՇԻԿՆԵՐ ԱՐՀԵՍՏԱԿԱՆ ԿԱՇՎԵ ԵՐԵՍԱՄԱՍՈՎ , ՊՈԼԻՄԵՐԱՅԻՆ ԿՈՇԿԱՏԱԿՈՎ | E90: Սպորտային Կոշիկ | F90: 67 | G90: Կանանց | H90: 2 | I90: 0.73 | J90: 1 | K90: 0.926 | L90: JENNY FAIRY | M90: 893 | N90: CHINA | O90: 7497 | P90: Տակացու Պոլիմեր, Վրան Արհեստական Կաշի | Q90: 101-7 | R90: Mix Brand | S90: 1000320 | T90: 37 | U90: 282 | V90: 0 | W90: Վարդագույն | X90: 13
A91: 90 | B91: 40000001025 | C91: 64041990000 | D91: ԿԱՆԱՑԻ ՃՏՔԱՎՈՐ ԿՈՇԻԿ ԲՐԴԵ ԵՐԵՍԱՄԱՍՈՎ ՌԵՏԻՆԵ ԿՈՇԿԱՏԱԿՈՎ | E91: Երկարաճիտ Կոշիկ | F91: 59 | G91: Կանանց | H91: 2 | I91: 0.79 | J91: 1 | K91: 1.214 | L91: EMU AUSTRALIA | M91: 890 | N91: AUSTRALIA | O91: 8625 | P91: Տակացու Ռետին, Վրան Բուրդ | Q91: 102-11 | R91: Mix Brand | S91: 1000320 | T91: 41 | U91: 288 | V91: 0 | W91: Շագանակագույն | X91: 10
A92: 91 | B92: 40000001024 | C92: 64039991000 | D92: ԱՂՋԿԱ ԲՈԿՈՏԻԿՆԵՐ ԲՆԱԿԱՆ ԿԱՇՎԵ ԵՐԵՍԱՄԱՍՈՎ , ՊՈԼԻՄԵՐԱՅԻՆ ԿՈՇԿԱՏԱԿՈՎ ՄԻՆՉԵՎ 24ՍՄ ՆԵՐԲԱՆԻ ԵՐԿԱՐՈՒԹՅԱՄԲ | E92: Սանդալ | F92: 66 | G92: Աղջիկների | H92: 3 | I92: 0.384 | J92: 1 | K92: 0.51 | L92: HI-TEC | M92: 892 | N92: CHINA | O92: 7497 | P92: Տակացու Պոլիմեր, Վրան Կաշի | Q92: 101-20 | R92: Mix Brand | S92: 1000320 | T92: 31 | U92: 140 | V92: 0 | W92: Վարդագույն | X92: 13
A93: 92 | B93: 40000001023 | C93: 64041990000 | D93: ՏՂԱՄԱՐԴՈՒ ՍՊՈՐՏԱՅԻՆ ՈՃԻ ԿՈՇԻԿՆԵՐ ՏԵՔՏՍԻԼԵ ԵՐԵՍԱՄԱՍՈՎ ՌԵՏԻՆԵ ԿՈՇԿԱՏԱԿՈՎ | E93: Սպորտային Կոշիկ | F93: 67 | G93: Տղամարդկանց | H93: 1 | I93: 0.716 | J93: 1 | K93: 0.9 | L93: MERRELL | M93: 895 | N93: VIETNAM | O93: 7579 | P93: Տակացու Ռետին, Վրան Կտոր | Q93: 102-25 | R93: Mix Brand | S93: 1000320 | T93: 40.5 | U93: 658 | V93: 0 | W93: Մոխրագույն | X93: 8
A94: 93 | B94: 40000001022 | C94: 64029991000 | D94: ԱՂՋԿԱ ԿԻՍԱՃՏՔԱՎՈՐ ԿՈՇԻԿ ԱՐՀԵՍՏԱԿԱՆ ԿԱՇՎԵ ԵՐԵՍԱՄԱՍՈՎ , ՊՈԼԻՄԵՐԱՅԻՆ ԿՈՇԿԱՏԱԿՈՎ ՄԻՆՉԵՎ 24ՍՄ ՆԵՐԲԱՆԻ ԵՐԿԱՐՈՒԹՅԱՄԲ | E94: Կիսաճտքավոր Կոշիկ | F94: 470 | G94: Աղջիկների | H94: 3 | I94: 0.598 | J94: 1 | K94: 0.784 | L94: NELLI | M94: 896 | N94: CHINA | O94: 7497 | P94: Տակացու Պոլիմեր, Վրան Արհեստական Կաշի | Q94: 101-7 | R94: Mix Brand | S94: 1000320 | T94: 30 | U94: 22 | V94: 0 | W94: Շագանակագույն | X94: 10
A95: 94 | B95: 40000001021 | C95: 64039118000 | D95: ԿԱՆԱՑԻ ԿԻՍԱՃՏՔԱՎՈՐ ԿՈՇԻԿ ԲՆԱԿԱՆ ԿԱՇՎԵ ԵՐԵՍԱՄԱՍՈՎ ՌԵՏԻՆԵ ԿՈՇԿԱՏԱԿՈՎ | E95: Կիսաճտքավոր Կոշիկ | F95: 470 | G95: Տղամարդկանց | H95: 1 | I95: 0.676 | J95: 1 | K95: 0.904 | L95: HELLYHANSE | M95: 891 | N95: VIETNAM | O95: 7579 | P95: Տակացու Ռետին, Վրան Կաշի | Q95: 102-20 | R95: Mix Brand | S95: 1000320 | T95: 37.5 | U95: 287 | V95: 0 | W95: Կանաչ | X95: 4
A96: 95 | B96: 40000001020 | C96: 64039118000 | D96: ԿԱՆԱՑԻ ԿԻՍԱՃՏՔԱՎՈՐ ԿՈՇԻԿ ԲՆԱԿԱՆ ԿԱՇՎԵ ԵՐԵՍԱՄԱՍՈՎ ՌԵՏԻՆԵ ԿՈՇԿԱՏԱԿՈՎ | E96: Կիսաճտքավոր Կոշիկ | F96: 470 | G96: Կանանց | H96: 2 | I96: 0.916 | J96: 1 | K96: 1.414 | L96: RAGE AGE | M96: 882 | N96: BANGLADESH | O96: 7485 | P96: Տակացու Ռետին, Վրան Կաշի | Q96: 102-20 | R96: Mix Brand | S96: 1000320 | T96: 39 | U96: 275 | V96: 0 | W96: Կաթնագույն | X96: 23
A97: 96 | B97: 40000001019 | C97: 64041990000 | D97: ԿԱՆԱՑԻ ԵՎ ԱՂՋԿԱ ՍՊՈՐՏԱՅԻՆ ՈՃԻ ԿՈՇԻԿՆԵՐ ՏԵՔՏՍԻԼԵ ԵՐԵՍԱՄԱՍՈՎ ՌԵՏԻՆԵ ԿՈՇԿԱՏԱԿՈՎ | E97: Սպորտային Կոշիկ | F97: 67 | G97: Կանանց | H97: 2 | I97: 0.522 | J97: 1 | K97: 0.666 | L97: BIG STAR | M97: 885 | N97: CHINA | O97: 7497 | P97: Տակացու Ռետին, Վրան Կտոր | Q97: 102-25 | R97: Mix Brand | S97: 1000320 | T97: 38 | U97: 64 | V97: 0 | W97: Կարմիր | X97: 1
A98: 97 | B98: 40000001018 | C98: 64041990000 | D98: ՏՂԱՄԱՐԴՈՒ ՍՊՈՐՏԱՅԻՆ ՈՃԻ ԿՈՇԻԿՆԵՐ ՏԵՔՏՍԻԼԵ ԵՐԵՍԱՄԱՍՈՎ ՌԵՏԻՆԵ ԿՈՇԿԱՏԱԿՈՎ | E98: Սպորտային Կոշիկ | F98: 67 | G98: Տղամարդկանց | H98: 1 | I98: 0.792 | J98: 1 | K98: 0.958 | L98: BROOKS | M98: 886 | N98: VIETNAM | O98: 7579 | P98: Տակացու Ռետին, Վրան Կտոր | Q98: 102-25 | R98: Mix Brand | S98: 1000320 | T98: 45 | U98: 283 | V98: 0 | W98: Կապույտ | X98: 5
A99: 98 | B99: 40000001017 | C99: 64041990000 | D99: ԿԱՆԱՑԻ ԵՎ ԱՂՋԿԱ ՍՊՈՐՏԱՅԻՆ ՈՃԻ ԿՈՇԻԿՆԵՐ ՏԵՔՏՍԻԼԵ ԵՐԵՍԱՄԱՍՈՎ ՌԵՏԻՆԵ ԿՈՇԿԱՏԱԿՈՎ | E99: Սպորտային Կոշիկ | F99: 67 | G99: Կանանց | H99: 2 | I99: 0.818 | J99: 1 | K99: 0.946 | L99: BIG STAR | M99: 885 | N99: CHINA | O99: 7497 | P99: Տակացու Ռետին, Վրան Կտոր | Q99: 102-25 | R99: Mix Brand | S99: 1000320 | T99: 39 | U99: 275 | V99: 0 | W99: Սպիտակ | X99: 12
... A101: 100 | B101: 40000001015 | C101: 64029991000 | D101: ԱՂՋԿԱ ԿՈՇԻԿ ԱՐՀԵՍՏԱԿԱՆ ԿԱՇՎԵ ԵՐԵՍԱՄԱՍՈՎ , ՌԵՏԻՆԵ ԿՈՇԿԱՏԱԿՈՎ ՄԻՆՉԵՎ 24ՍՄ ՆԵՐԲԱՆԻ ԵՐԿԱՐՈՒԹՅԱՄԲ | E101: Կոշիկ | F101: 55 | G101: Աղջիկների | H101: 3 | I101: 0.162 | J101: 1 | K101: 0.262 | L101: CHICCO | M101: 608 | N101: CHINA | O101: 7497 | P101: Տակացու Ռետին, Վրան Արհեստական Կաշի | Q101: 102-7 | R101: Mix Brand | S101: 1000320 | T101: 19 | U101: 370 | V101: 0 | W101: Վարդագույն | X101: 13
...

Sheet Other
A1: N | B1: Code | C1: HS code | D1: name | E1: Sub-category | F1: Sub-category id | G1: Gender | H1: Gender id | I1: Netto | J1: pc | K1: Brutto | L1: Brand | M1: Brand id | N1: Country | O1: Country id | P1: Material | Q1: Material id | R1: Package | S1: Package Id | T1: Size | U1: Size id | V1: Original price | W1: Color | X1: Color id
A2: 1 | B2: 40000001111 | C2: 61102091000 | D2: ՏՂԱՄԱՐԴՈՒ ՀՈՒԴԻՆԵՐ ԲԱՄԲԱԿԵ ՄԱՆՎԱԾՔԻՑ | E2: Հուդի | F2: 18 | G2: Տղամարդկանց | H2: 1 | I2: 0.055 | J2: 1 | K2: 0.055 | L2: PETROL | M2: 881 | N2: BANGLADESH | O2: 7485 | P2: Բամբակ/Պոլիեսթեր | Q2: 9-37 | R2: Mix Brand | S2: 1000320 | T2: S | U2: 122 | V2: 0 | W2: Կապույտ | X2: 5
A3: 2 | B3: 40000001112 | C3: 61103091000 | D3: ՏՂԱՄԱՐԴՈՒ ՍՎԻՏՐԵՐ ՔԻՄԻԱԿԱՆ ԹԵԼԵՐԻՑ | E3: Սվիտրեր | F3: 88 | G3: Տղամարդկանց | H3: 1 | I3: 0.334 | J3: 1 | K3: 0.334 | L3: PETROL | M3: 881 | N3: BANGLADESH | O3: 7485 | P3: Բամբակ/Ակրիլ | Q3: 9-2 | R3: Mix Brand | S3: 1000320 | T3: S | U3: 122 | V3: 0 | W3: Կապույտ | X3: 5
A4: 3 | B4: 40000001113 | C4: 64041990000 | D4: ՏՂԱՄԱՐԴՈՒ ԿՈՇԻԿ ՏԵՔՏՍԻԼԵ ԵՐԵՍԱՄԱՍՈՎ ՌԵՏԻՆԵ ԿՈՇԿԱՏԱԿՈՎ | E4: Կոշիկ | F4: 55 | G4: Տղամարդկանց | H4: 1 | I4: 1.086 | J4: 1 | K4: 1.086 | L4: REGATTA | M4: 254 | N4: CHINA | O4: 7497 | P4: Տակացու Ռետին, Վրան Կտոր | Q4: 102-25 | R4: Mix Brand | S4: 1000320 | T4: 43 | U4: 289 | V4: 0 | W4: Կապույտ | X4: 5
A5: 4 | B5: 40000001114 | C5: 64041990000 | D5: ԿԱՆԱՑԻ ԿՈՇԻԿՆԵՐ ՏԵՔՏՍԻԼԵ ԵՐԵՍԱՄԱՍՈՎ ՌԵՏԻՆԵ ԿՈՇԿԱՏԱԿՈՎ | E5: Կոշիկ | F5: 55 | G5: Կանանց | H5: 2 | I5: 0.042 | J5: 1 | K5: 0.042 | L5: UNKNOWN | M5: 880 | N5: CHINA | O5: 7497 | P5: Տակացու Ռետին, Վրան Կտոր | Q5: 102-25 | R5: Mix Brand | S5: 1000320 | T5: 38 | U5: 64 | V5: 0 | W5: Սպիտակ | X5: 12
A6: 5 | B6: 40000001110 | C6: 62034235000 | D6: ՏՂԱՅԻ ՏԱԲԱՏՆԵՐ ԲԱՄԲԱԿԵ ՄԱՆՎԱԾՔԻՑ | E6: Տաբատներ | F6: 93 | G6: Տղաների | H6: 4 | I6: 0.304 | J6: 1 | K6: 0.304 | L6: S. OLIVER | M6: 17 | N6: BANGLADESH | O6: 7485 | P6: Բամբակ | Q6: 9 | R6: Mix Brand | S6: 1000320 | T6: US 12-13 | U6: 633 | V6: EUR 40 | W6: Կանաչ | X6: 4
A7: 6 | B7: 40000001109 | C7: 64039998000 | D7: ԿԱՆԱՑԻ ԿՈՇԻԿ ԲՆԱԿԱՆ ԿԱՇՎԵ ԵՐԵՍԱՄԱՍՈՎ , ՊՈԼԻՄԵՐԱՅԻՆ ԿՈՇԿԱՏԱԿՈՎ | E7: Կոշիկ | F7: 55 | G7: Կանանց | H7: 2 | I7: 0.85 | J7: 1 | K7: 1.418 | L7: RAGE AGE | M7: 882 | N7: POLAND | O7: 1805 | P7: Տակացու Պոլիմեր, Վրան Զամշ | Q7: 101-79 | R7: Mix Brand | S7: 1000320 | T7: 39 | U7: 275 | V7: 0 | W7: Կարմիր | X7: 1
A8: 7 | B8: 40000001108 | C8: 64041910000 | D8: ՏՂԱՄԱՐԴՈՒ ՀՈՂԱԹԱՓ ՏԵՔՍՏԻԼԵ ԵՐԵՍԱՄԱՍՈՎ , ՊՈԼԻՄԵՐԱՅԻՆ ԿՈՇԿԱՏՈՎ | E8: Հողաթափ | F8: 310 | G8: Unisex | H8: 5 | I8: 0.388 | J8: 1 | K8: 0.582 | L8: UGG | M8: 296 | N8: VIETNAM | O8: 7579 | P8: Բուրդ/Լիոսել | Q8: 11-54 | R8: Mix Brand | S8: 1000320 | T8: 41 | U8: 288 | V8: 0 | W8: Շագանակագույն | X8: 10
A9: 8 | B9: 40000001107 | C9: 62024000010 | D9: ԿԱՆԱՑԻ ՎԵՐԱՐԿՈՒՆԵՐ ՔԻՄԻԱԿԱՆ ԹԵԼԵՐԻՑ | E9: Վերարկու | F9: 92 | G9: Կանանց | H9: 2 | I9: 1.102 | J9: 1 | K9: 1.102 | L9: TOM TAILOR | M9: 5 | N9: VIETNAM | O9: 7579 | P9: Պոլիեսթեր | Q9: 37 | R9: Mix Brand | S9: 1000320 | T9: L | U9: 3 | V9: EUR 100 | W9: Վարդագույն | X9: 13
A10: 9 | B10: 40000001106 | C10: 61102091000 | D10: ՏՂԱՄԱՐԴՈՒ ԵՎ ՏՂԱՅԻ ՍՎԻՏՐԵՐ ԲԱՄԲԱԿԵ ՄԱՆՎԱԾՔԻՑ | E10: Սվիտրեր | F10: 88 | G10: Տղամարդկանց | H10: 1 | I10: 0.344 | J10: 1 | K10: 0.344 | L10: PETROL | M10: 881 | N10: BANGLADESH | O10: 7485 | P10: Բամբակ/Ակրիլ | Q10: 9-2 | R10: Mix Brand | S10: 1000320 | T10: M | U10: 119 | V10: EUR 60 | W10: Կանաչ | X10: 4
A11: 10 | B11: 40000001105 | C11: 62014000000 | D11: ՏՂԱՄԱՐԴՈՒ ՎԵՐԱՐԿՈՒՆԵՐ ՔԻՄԻԱԿԱՆ ԹԵԼԵՐԻՑ | E11: Վերարկու | F11: 92 | G11: Տղամարդկանց | H11: 1 | I11: 1.136 | J11: 1 | K11: 1.136 | L11: PETROL | M11: 881 | N11: CHINA | O11: 7497 | P11: Պոլիեսթեր | Q11: 37 | R11: Mix Brand | S11: 1000320 | T11: XL | U11: 124 | V11: EUR 120 | W11: Սև | X11: 20
A12: 11 | B12: 40000001104 | C12: 62014000000 | D12: ՏՂԱՄԱՐԴՈՒ ՎԵՐԱՐԿՈՒՆԵՐ ՔԻՄԻԱԿԱՆ ԹԵԼԵՐԻՑ | E12: Վերարկու | F12: 92 | G12: Տղամարդկանց | H12: 1 | I12: 1.194 | J12: 1 | K12: 1.194 | L12: PETROL | M12: 881 | N12: CHINA | O12: 7497 | P12: Պոլիեսթեր | Q12: 37 | R12: Mix Brand | S12: 1000320 | T12: L | U12: 3 | V12: EUR 120 | W12: Սև | X12: 20
A13: 12 | B13: 40000001103 | C13: 62014000000 | D13: ՏՂԱՄԱՐԴՈՒ ՎԵՐԱՐԿՈՒՆԵՐ ՔԻՄԻԱԿԱՆ ԹԵԼԵՐԻՑ | E13: Վերարկու | F13: 92 | G13: Տղամարդկանց | H13: 1 | I13: 1.076 | J13: 1 | K13: 1.076 | L13: PETROL | M13: 881 | N13: CHINA | O13: 7497 | P13: Պոլիեսթեր | Q13: 37 | R13: Mix Brand | S13: 1000320 | T13: L | U13: 3 | V13: EUR 120 | W13: Կապույտ | X13: 5
A14: 13 | B14: 40000001102 | C14: 62014000000 | D14: ՏՂԱՄԱՐԴՈՒ ՎԵՐԱՐԿՈՒՆԵՐ ՔԻՄԻԱԿԱՆ ԹԵԼԵՐԻՑ | E14: Վերարկու | F14: 92 | G14: Տղամարդկանց | H14: 1 | I14: 1.038 | J14: 1 | K14: 1.038 | L14: PETROL | M14: 881 | N14: CHINA | O14: 7497 | P14: Պոլիեսթեր | Q14: 37 | R14: Mix Brand | S14: 1000320 | T14: M | U14: 119 | V14: EUR 120 | W14: Սև | X14: 20
A15: 14 | B15: 40000001101 | C15: 62024000010 | D15: ԿԱՆԱՑԻ ՎԵՐԱՐԿՈՒՆԵՐ ՔԻՄԻԱԿԱՆ ԹԵԼԵՐԻՑ | E15: Վերարկու | F15: 92 | G15: Կանանց | H15: 2 | I15: 1.06 | J15: 1 | K15: 1.06 | L15: TOM TAILOR | M15: 5 | N15: VIETNAM | O15: 7579 | P15: Պոլիեսթեր | Q15: 37 | R15: Mix Brand | S15: 1000320 | T15: L | U15: 3 | V15: EUR 100 | W15: Վարդագույն | X15: 13
A16: 15 | B16: 40000001100 | C16: 61102091000 | D16: ՏՂԱՄԱՐԴՈՒ ՀՈՒԴԻՆԵՐ ԲԱՄԲԱԿԵ ՄԱՆՎԱԾՔԻՑ | E16: Հուդի | F16: 18 | G16: Տղամարդկանց | H16: 1 | I16: 0.926 | J16: 1 | K16: 0.926 | L16: CARHARTT | M16: 791 | N16: PAKISTAN | O16: 7550 | P16: Բամբակ/Պոլիեսթեր | Q16: 9-37 | R16: Mix Brand | S16: 1000320 | T16: XL | U16: 124 | V16: 0 | W16: Կանաչ | X16: 4
A17: 16 | B17: 40000001099 | C17: 61102091000 | D17: ՏՂԱՄԱՐԴՈՒ ՀՈՒԴԻՆԵՐ ԲԱՄԲԱԿԵ ՄԱՆՎԱԾՔԻՑ | E17: Հուդի | F17: 18 | G17: Տղամարդկանց | H17: 1 | I17: 0.854 | J17: 1 | K17: 0.854 | L17: CARHARTT | M17: 791 | N17: PAKISTAN | O17: 7550 | P17: Բամբակ/Պոլիեսթեր | Q17: 9-37 | R17: Mix Brand | S17: 1000320 | T17: M | U17: 119 | V17: 0 | W17: Կանաչ | X17: 4
A18: 17 | B18: 40000001098 | C18: 61102091000 | D18: ՏՂԱՄԱՐԴՈՒ ԵՎ ՏՂԱՅԻ ՍՎԻՏՐԵՐ ԲԱՄԲԱԿԵ ՄԱՆՎԱԾՔԻՑ | E18: Սվիտրեր | F18: 88 | G18: Տղամարդկանց | H18: 1 | I18: 0.402 | J18: 1 | K18: 0.402 | L18: PETROL | M18: 881 | N18: BANGLADESH | O18: 7485 | P18: Բամբակ/Ակրիլ | Q18: 9-2 | R18: Mix Brand | S18: 1000320 | T18: XL | U18: 124 | V18: EUR 60 | W18: Կապույտ | X18: 5
A19: 18 | B19: 40000001097 | C19: 62013000000 | D19: ՏՂԱՄԱՐԴՈՒ ՎԵՐԱՐԿՈՒՆԵՐ ԲԱՄԲԱԿԵ ՄԱՆՎԱԾՔԻՑ | E19: Վերարկու | F19: 92 | G19: Տղամարդկանց | H19: 1 | I19: 0.556 | J19: 1 | K19: 0.556 | L19: PETROL | M19: 881 | N19: CHINA | O19: 7497 | P19: Բամբակ/Պոլիեսթեր | Q19: 9-37 | R19: Mix Brand | S19: 1000320 | T19: M | U19: 119 | V19: EUR 90 | W19: Սև | X19: 20
A20: 19 | B20: 40000001096 | C20: 62013000000 | D20: ՏՂԱՄԱՐԴՈՒ ՎԵՐԱՐԿՈՒ ԲԱՄԲԱԿԵ ՄԱՆՎԱԾՔԻՑ | E20: Վերարկու | F20: 92 | G20: Տղամարդկանց | H20: 1 | I20: 0.466 | J20: 1 | K20: 0.466 | L20: PETROL | M20: 881 | N20: BANGLADESH | O20: 7485 | P20: Բամբակ/Ակրիլ | Q20: 9-2 | R20: Mix Brand | S20: 1000320 | T20: XL | U20: 124 | V20: EUR 70 | W20: Սև | X20: 20
A21: 20 | B21: 40000001095 | C21: 64039991000 | D21: ՏՂԱՅԻ ԿՈՇԻԿ ԲՆԱԿԱՆ ԶԱՄՇԵ ԵՐԵՍԱՄԱՍՈՎ , ՊՈԼԻՄԵՐԱՅԻՆ ԿՈՇԿԱՏԱԿՈՎ ՄԻՆՉԵՎ 24ՍՄ ՆԵՐԲԱՆԻ ԵՐԿԱՐՈՒԹՅԱՄԲ | E21: Կոշիկ | F21: 55 | G21: Տղաների | H21: 4 | I21: 0.348 | J21: 1 | K21: 0.526 | L21: GEOX | M21: 883 | N21: ITALY | O21: 1760 | P21: Տակացու Պոլիմեր, Վրան Զամշ | Q21: 101-79 | R21: Mix Brand | S21: 1000320 | T21: 31 | U21: 140 | V21: EUR 31 | W21: Կապույտ | X21: 5
A22: 21 | B22: 40000001094 | C22: 64029991000 | D22: ԱՂՋԿԱ ԲՈԿՈՏԻԿ ԱՐՀԵՍՏԱԿԱՆ ԿԱՇՎԵ ԵՐԵՍԱՄԱՍՈՎ , ՌԵՏԻՆԵ ԿՈՇԿԱՏԱԿՈՎ ՄԻՆՉԵՎ 24ՍՄ ՆԵՐԲԱՆԻ ԵՐԿԱՐՈՒԹՅԱՄԲ | E22: Սանդալ | F22: 66 | G22: Աղջիկների | H22: 3 | I22: 0.326 | J22: 1 | K22: 0.48 | L22: CHICCO | M22: 608 | N22: CHINA | O22: 7497 | P22: Պոլիուրեթան | Q22: 104 | R22: Mix Brand | S22: 1000320 | T22: 31 | U22: 140 | V22: 0 | W22: Սպիտակ | X22: 12
A23: 22 | B23: 40000001093 | C23: 61091000000 | D23: ՏՂԱՄԱՐԴՈՒ ԵՎ ՏՂԱՅԻ ՇԱՊԻԿՆԵՐ ԲԱՄԲԱԿԵ ՄԱՆՎԱԾՔԻՑ | E23: Շապիկ | F23: 73 | G23: Տղամարդկանց | H23: 1 | I23: 0.162 | J23: 1 | K23: 0.162 | L23: PETROL | M23: 881 | N23: BANGLADESH | O23: 7485 | P23: Բամբակ | Q23: 9 | R23: Mix Brand | S23: 1000320 | T23: XL | U23: 124 | V23: EUR 20 | W23: Կապույտ | X23: 5
A24: 23 | B24: 40000001092 | C24: 61102091000 | D24: ՏՂԱՄԱՐԴՈՒ ՀՈՒԴԻՆԵՐ ԲԱՄԲԱԿԵ ՄԱՆՎԱԾՔԻՑ | E24: Հուդի | F24: 18 | G24: Տղամարդկանց | H24: 1 | I24: 0.576 | J24: 1 | K24: 0.576 | L24: PETROL | M24: 881 | N24: BANGLADESH | O24: 7485 | P24: Բամբակ | Q24: 9 | R24: Mix Brand | S24: 1000320 | T24: M | U24: 119 | V24: EUR 46 | W24: Կապույտ | X24: 5
A25: 24 | B25: 40000001091 | C25: 61051000000 | D25: ՏՂԱՄԱՐԴՈՒ ՎԵՐՆԱՇԱՊԻԿՆԵՐ ԲԱՄԲԱԿԵ ՄԱՆՎԱԾՔԻՑ | E25: Վերնաշապիկ | F25: 82 | G25: Տղամարդկանց | H25: 1 | I25: 0.236 | J25: 1 | K25: 0.236 | L25: PETROL | M25: 881 | N25: BANGLADESH | O25: 7485 | P25: Բամբակ | Q25: 9 | R25: Mix Brand | S25: 1000320 | T25: L | U25: 3 | V25: EUR 60 | W25: Գույնզգույն | X25: 17
A26: 25 | B26: 40000001090 | C26: 61051000000 | D26: ՏՂԱՄԱՐԴՈՒ ԵՎ ՏՂԱՅԻ ՎԵՐՆԱՇԱՊԻԿՆԵՐ ԲԱՄԲԱԿԵ ՄԱՆՎԱԾՔԻՑ | E26: Վերնաշապիկ | F26: 82 | G26: Տղամարդկանց | H26: 1 | I26: 0.466 | J26: 1 | K26: 0.466 | L26: PETROL | M26: 881 | N26: INDIA | O26: 7505 | P26: Բամբակ | Q26: 9 | R26: Mix Brand | S26: 1000320 | T26: M | U26: 119 | V26: EUR 80 | W26: Գույնզգույն | X26: 17
A27: 26 | B27: 40000001089 | C27: 62013000000 | D27: ՏՂԱՄԱՐԴՈՒ ՎԵՐԱՐԿՈՒՆԵՐ ԲԱՄԲԱԿԵ ՄԱՆՎԱԾՔԻՑ | E27: Վերարկու | F27: 92 | G27: Տղամարդկանց | H27: 1 | I27: 0.516 | J27: 1 | K27: 0.516 | L27: PETROL | M27: 881 | N27: CHINA | O27: 7497 | P27: Բամբակ | Q27: 9 | R27: Mix Brand | S27: 1000320 | T27: S | U27: 122 | V27: EUR 90 | W27: Կաթնագույն | X27: 23
A28: 27 | B28: 40000001088 | C28: 61102091000 | D28: ՏՂԱՄԱՐԴՈՒ ՀՈՒԴԻՆԵՐ ԲԱՄԲԱԿԵ ՄԱՆՎԱԾՔԻՑ | E28: Հուդի | F28: 18 | G28: Տղամարդկանց | H28: 1 | I28: 0.62 | J28: 1 | K28: 0.62 | L28: PETROL | M28: 881 | N28: BANGLADESH | O28: 7485 | P28: Բամբակ/Ակրիլ | Q28: 9-2 | R28: Mix Brand | S28: 1000320 | T28: M | U28: 119 | V28: EUR 90 | W28: Կաթնագույն | X28: 23
A29: 28 | B29: 40000001087 | C29: 61091000000 | D29: ՏՂԱՄԱՐԴՈՒ ԵՎ ՏՂԱՅԻ ՇԱՊԻԿՆԵՐ ԲԱՄԲԱԿԵ ՄԱՆՎԱԾՔԻՑ | E29: Շապիկ | F29: 73 | G29: Տղամարդկանց | H29: 1 | I29: 0.202 | J29: 1 | K29: 0.202 | L29: PETROL | M29: 881 | N29: BANGLADESH | O29: 7485 | P29: Բամբակ | Q29: 9 | R29: Mix Brand | S29: 1000320 | T29: XL | U29: 124 | V29: EUR 28 | W29: Կաթնագույն | X29: 23
A30: 29 | B30: 40000001086 | C30: 61102091000 | D30: ՏՂԱՄԱՐԴՈՒ ԵՎ ՏՂԱՅԻ ՍՎԻՏՐԵՐ ԲԱՄԲԱԿԵ ՄԱՆՎԱԾՔԻՑ | E30: Սվիտրեր | F30: 88 | G30: Տղամարդկանց | H30: 1 | I30: 0.474 | J30: 1 | K30: 0.474 | L30: PETROL | M30: 881 | N30: BANGLADESH | O30: 7485 | P30: Բամբակ | Q30: 9 | R30: Mix Brand | S30: 1000320 | T30: L | U30: 3 | V30: EUR 50 | W30: Կաթնագույն | X30: 23
A31: 30 | B31: 40000001085 | C31: 61102091000 | D31: ՏՂԱՄԱՐԴՈՒ ՀՈՒԴԻՆԵՐ ԲԱՄԲԱԿԵ ՄԱՆՎԱԾՔԻՑ | E31: Հուդի | F31: 18 | G31: Տղամարդկանց | H31: 1 | I31: 0.634 | J31: 1 | K31: 0.634 | L31: PETROL | M31: 881 | N31: BANGLADESH | O31: 7485 | P31: Բամբակ | Q31: 9 | R31: Mix Brand | S31: 1000320 | T31: L | U31: 3 | V31: EUR 60 | W31: Կապույտ | X31: 5
A32: 31 | B32: 40000001084 | C32: 61102091000 | D32: ՏՂԱՄԱՐԴՈՒ ԵՎ ՏՂԱՅԻ ՍՎԻՏՐԵՐ ԲԱՄԲԱԿԵ ՄԱՆՎԱԾՔԻՑ | E32: Սվիտրեր | F32: 88 | G32: Տղամարդկանց | H32: 1 | I32: 0.494 | J32: 1 | K32: 0.494 | L32: PETROL | M32: 881 | N32: BANGLADESH | O32: 7485 | P32: Բամբակ | Q32: 9 | R32: Mix Brand | S32: 1000320 | T32: S | U32: 122 | V32: EUR 50 | W32: Կապույտ | X32: 5
A33: 32 | B33: 40000001083 | C33: 61045300000 | D33: ԿԱՆԱՑԻ ԵՎ ԱՂՋԿԱ ԿԻՍԱՇՐՋԱԶԳԵՍՏՆԵՐ ՍԻՆԹԵՏԻԿ ԹԵԼԵՐԻՑ | E33: Կիսաշրջազգեստ | F33: 53 | G33: Կանանց | H33: 2 | I33: 0.226 | J33: 1 | K33: 0.226 | L33: ONLY | M33: 28 | N33: CHINA | O33: 7497 | P33: Պոլիեսթեր | Q33: 37 | R33: Mix Brand | S33: 1000320 | T33: S | U33: 122 | V33: EUR 35 | W33: Սև | X33: 20
A34: 33 | B34: 40000001082 | C34: 62013000000 | D34: ՏՂԱՄԱՐԴՈՒ ՎԵՐԱՐԿՈՒ ԲԱՄԲԱԿԵ ՄԱՆՎԱԾՔԻՑ | E34: Վերարկու | F34: 92 | G34: Տղամարդկանց | H34: 1 | I34: 1.268 | J34: 1 | K34: 1.268 | L34: PETROL | M34: 881 | N34: PAKISTAN | O34: 7550 | P34: Բամբակ/Պոլիեսթեր | Q34: 9-37 | R34: Mix Brand | S34: 1000320 | T34: XL | U34: 124 | V34: EUR 100 | W34: Կանաչ | X34: 4
A35: 34 | B35: 40000001081 | C35: 62034235000 | D35: ՏՂԱՅԻ ՏԱԲԱՏՆԵՐ ԲԱՄԲԱԿԵ ՄԱՆՎԱԾՔԻՑ | E35: Տաբատներ | F35: 93 | G35: Տղաների | H35: 4 | I35: 0.424 | J35: 1 | K35: 0.424 | L35: TIMBERLAND | M35: 457 | N35: BANGLADESH | O35: 7485 | P35: Բամբակ | Q35: 9 | R35: Mix Brand | S35: 1000320 | T35: 36 | U35: 52 | V35: 0 | W35: Սև | X35: 20
A36: 35 | B36: 40000001080 | C36: 64039991000 | D36: ՏՂԱՅԻ ԲՈԿՈՏԻԿ ԲՆԱԿԱՆ ԿԱՇՎԵ ԵՐԵՍԱՄԱՍՈՎ , ՊՈԼԻՄԵՐԱՅԻՆ ԿՈՇԿԱՏԱԿՈՎ ՄԻՆՉԵՎ 24ՍՄ ՆԵՐԲԱՆԻ ԵՐԿԱՐՈՒԹՅԱՄԲ | E36: Սանդալ | F36: 66 | G36: Տղաների | H36: 4 | I36: 0.092 | J36: 1 | K36: 0.092 | L36: CHICCO | M36: 608 | N36: ITALY | O36: 1760 | P36: Տակացու Պոլիմեր, Վրան Կաշի | Q36: 101-20 | R36: Mix Brand | S36: 1000320 | T36: 18 | U36: 2 | V36: 0 | W36: Կապույտ | X36: 5
A37: 36 | B37: 40000001079 | C37: 64029991000 | D37: ԱՂՋԿԱ ԲՈԿՈՏԻԿՆԵՐ ԱՐՀԵՍՏԱԿԱՆ ԿԱՇՎԵ ԵՐԵՍԱՄԱՍՈՎ , ՌԵՏԻՆԵ ԿՈՇԿԱՏԱԿՈՎ ՄԻՆՉԵՎ 24ՍՄ ՆԵՐԲԱՆԻ ԵՐԿԱՐՈՒԹՅԱՄԲ | E37: Սանդալ | F37: 66 | G37: Կանանց | H37: 2 | I37: 0.104 | J37: 1 | K37: 0.104 | L37: CHICCO | M37: 608 | N37: ITALY | O37: 1760 | P37: Պոլիեսթեր | Q37: 37 | R37: Mix Brand | S37: 1000320 | T37: 19 | U37: 370 | V37: EUR 17 (ZEXCHOV 11) | W37: Վարդագույն | X37: 13
A38: 37 | B38: 40000001078 | C38: 64052099000 | D38: ՏՂԱՅԻ ԲՈԿՈՏԻԿՆԵՐ ՏԵՔՍՏԻԼԵ | E38: Սանդալ | F38: 66 | G38: Տղաների | H38: 4 | I38: 0.1 | J38: 1 | K38: 0.1 | L38: CHICCO | M38: 608 | N38: ITALY | O38: 1760 | P38: Բամբակ | Q38: 9 | R38: Mix Brand | S38: 1000320 | T38: 19 | U38: 370 | V38: EUR 15 | W38: Կապույտ | X38: 5
A39: 38 | B39: 40000001077 | C39: 64052099000 | D39: ՏՂԱՅԻ ԲՈԿՈՏԻԿՆԵՐ ՏԵՔՍՏԻԼԵ | E39: Սանդալ | F39: 66 | G39: Տղաների | H39: 4 | I39: 0.096 | J39: 1 | K39: 0.096 | L39: CHICCO | M39: 608 | N39: ITALY | O39: 1760 | P39: Բամբակ | Q39: 9 | R39: Mix Brand | S39: 1000320 | T39: 18 | U39: 2 | V39: EUR 15 | W39: Կապույտ | X39: 5
A40: 39 | B40: 40000001076 | C40: 64029991000 | D40: ԱՂՋԿԱ ԲՈԿՈՏԻԿՆԵՐ ԱՐՀԵՍՏԱԿԱՆ ԿԱՇՎԵ ԵՐԵՍԱՄԱՍՈՎ , ՌԵՏԻՆԵ ԿՈՇԿԱՏԱԿՈՎ ՄԻՆՉԵՎ 24ՍՄ ՆԵՐԲԱՆԻ ԵՐԿԱՐՈՒԹՅԱՄԲ | E40: Սանդալ | F40: 66 | G40: Կանանց | H40: 2 | I40: 0.088 | J40: 1 | K40: 0.088 | L40: CHICCO | M40: 608 | N40: ITALY | O40: 1760 | P40: Պոլիեսթեր | Q40: 37 | R40: Mix Brand | S40: 1000320 | T40: 18 | U40: 2 | V40: EUR 20 | W40: Արծաթագույն | X40: 22
A41: 40 | B41: 40000001075 | C41: 64052099000 | D41: ԱՂՋԿԱ ԿՈՇԻԿ ՏԵՔՍՏԻԼԵ | E41: Կոշիկ | F41: 55 | G41: Աղջիկների | H41: 3 | I41: 0.078 | J41: 1 | K41: 0.078 | L41: CHICCO | M41: 608 | N41: ITALY | O41: 1760 | P41: Բամբակ/Տակացու Տեքստիլ | Q41: 9-69 | R41: Mix Brand | S41: 1000320 | T41: 18 | U41: 2 | V41: EUR 15 | W41: Սպիտակ | X41: 12
A42: 41 | B42: 40000001074 | C42: 64039991000 | D42: ԱՂՋԿԱ ԿՈՇԻԿ ԲՆԱԿԱՆ ԿԱՇՎԵ ԵՐԵՍԱՄԱՍՈՎ , ՊՈԼԻՄԵՐԱՅԻՆ ԿՈՇԿԱՏԱԿՈՎ ՄԻՆՉԵՎ 24ՍՄ ՆԵՐԲԱՆԻ ԵՐԿԱՐՈՒԹՅԱՄԲ | E42: Կոշիկ | F42: 55 | G42: Աղջիկների | H42: 3 | I42: 0.182 | J42: 1 | K42: 0.182 | L42: CHICCO | M42: 608 | N42: ITALY | O42: 1760 | P42: Տակացու Պոլիմեր, Վրան Կաշի | Q42: 101-20 | R42: Mix Brand | S42: 1000320 | T42: 19 | U42: 370 | V42: 0 | W42: Արծաթագույն | X42: 22
A43: 42 | B43: 40000001073 | C43: 61091000000 | D43: ԿԱՆԱՑԻ ԵՎ ԱՂՋԿԱ ՇԱՊԻԿՆԵՐ ԲԱՄԲԱԿԵ ՄԱՆՎԱԾՔԻՑ | E43: Շապիկ | F43: 73 | G43: Կանանց | H43: 2 | I43: 0.134 | J43: 1 | K43: 0.134 | L43: CAVALLI | M43: 767 | N43: BANGLADESH | O43: 7485 | P43: Բամբակ | Q43: 9 | R43: Mix Brand | S43: 1000320 | T43: L | U43: 3 | V43: 0 | W43: Սև | X43: 20
A44: 43 | B44: 40000001072 | C44: 61051000000 | D44: ՏՂԱՄԱՐԴՈՒ ԵՎ ՏՂԱՅԻ ՎԵՐՆԱՇԱՊԻԿՆԵՐ ԲԱՄԲԱԿԵ ՄԱՆՎԱԾՔԻՑ | E44: Վերնաշապիկ | F44: 82 | G44: Տղամարդկանց | H44: 1 | I44: 0.328 | J44: 1 | K44: 0.328 | L44: PETROL | M44: 881 | N44: INDIA | O44: 7505 | P44: Բամբակ | Q44: 9 | R44: Mix Brand | S44: 1000320 | T44: M | U44: 119 | V44: EUR 70 | W44: Կապույտ | X44: 5
A45: 44 | B45: 40000001071 | C45: 61091000000 | D45: ԿԱՆԱՑԻ ԵՎ ԱՂՋԿԱ ՇԱՊԻԿՆԵՐ ԲԱՄԲԱԿԵ ՄԱՆՎԱԾՔԻՑ | E45: Շապիկ | F45: 73 | G45: Կանանց | H45: 2 | I45: 0.132 | J45: 1 | K45: 0.132 | L45: CAVALLI | M45: 767 | N45: BANGLADESH | O45: 7485 | P45: Բամբակ | Q45: 9 | R45: Mix Brand | S45: 1000320 | T45: L | U45: 3 | V45: 0 | W45: Սև | X45: 20
A46: 45 | B46: 40000001070 | C46: 61091000000 | D46: ԿԱՆԱՑԻ ԵՎ ԱՂՋԿԱ ՇԱՊԻԿՆԵՐ ԲԱՄԲԱԿԵ ՄԱՆՎԱԾՔԻՑ | E46: Շապիկ | F46: 73 | G46: Կանանց | H46: 2 | I46: 0.114 | J46: 1 | K46: 0.114 | L46: CAVALLI | M46: 767 | N46: BANGLADESH | O46: 7485 | P46: Բամբակ | Q46: 9 | R46: Mix Brand | S46: 1000320 | T46: M | U46: 119 | V46: 0 | W46: Սպիտակ | X46: 12
A47: 46 | B47: 40000001069 | C47: 61091000000 | D47: ԿԱՆԱՑԻ ԵՎ ԱՂՋԿԱ ՇԱՊԻԿՆԵՐ ԲԱՄԲԱԿԵ ՄԱՆՎԱԾՔԻՑ | E47: Շապիկ | F47: 73 | G47: Կանանց | H47: 2 | I47: 0.134 | J47: 1 | K47: 0.134 | L47: CAVALLI | M47: 767 | N47: BANGLADESH | O47: 7485 | P47: Բամբակ | Q47: 9 | R47: Mix Brand | S47: 1000320 | T47: L | U47: 3 | V47: 0 | W47: Սպիտակ | X47: 12
A48: 47 | B48: 40000001068 | C48: 61091000000 | D48: ԿԱՆԱՑԻ ԵՎ ԱՂՋԿԱ ՇԱՊԻԿՆԵՐ ԲԱՄԲԱԿԵ ՄԱՆՎԱԾՔԻՑ | E48: Շապիկ | F48: 73 | G48: Կանանց | H48: 2 | I48: 0.142 | J48: 1 | K48: 0.142 | L48: CAVALLI | M48: 767 | N48: BANGLADESH | O48: 7485 | P48: Բամբակ | Q48: 9 | R48: Mix Brand | S48: 1000320 | T48: XL | U48: 124 | V48: 0 | W48: Սպիտակ | X48: 12
A49: 48 | B49: 40000001067 | C49: 61091000000 | D49: ԿԱՆԱՑԻ ԵՎ ԱՂՋԿԱ ՇԱՊԻԿՆԵՐ ԲԱՄԲԱԿԵ ՄԱՆՎԱԾՔԻՑ | E49: Շապիկ | F49: 73 | G49: Կանանց | H49: 2 | I49: 0.142 | J49: 1 | K49: 0.142 | L49: CAVALLI | M49: 767 | N49: BANGLADESH | O49: 7485 | P49: Բամբակ | Q49: 9 | R49: Mix Brand | S49: 1000320 | T49: L | U49: 3 | V49: 0 | W49: Սպիտակ | X49: 12
A50: 49 | B50: 40000001066 | C50: 61091000000 | D50: ԿԱՆԱՑԻ ԵՎ ԱՂՋԿԱ ՇԱՊԻԿՆԵՐ ԲԱՄԲԱԿԵ ՄԱՆՎԱԾՔԻՑ | E50: Շապիկ | F50: 73 | G50: Կանանց | H50: 2 | I50: 0.108 | J50: 1 | K50: 0.108 | L50: CAVALLI | M50: 767 | N50: BANGLADESH | O50: 7485 | P50: Բամբակ | Q50: 9 | R50: Mix Brand | S50: 1000320 | T50: S | U50: 122 | V50: 0 | W50: Սպիտակ | X50: 12
A51: 50 | B51: 40000001065 | C51: 61091000000 | D51: ԿԱՆԱՑԻ ԵՎ ԱՂՋԿԱ ՇԱՊԻԿՆԵՐ ԲԱՄԲԱԿԵ ՄԱՆՎԱԾՔԻՑ | E51: Շապիկ | F51: 73 | G51: Կանանց | H51: 2 | I51: 0.152 | J51: 1 | K51: 0.152 | L51: CAVALLI | M51: 767 | N51: BANGLADESH | O51: 7485 | P51: Բամբակ | Q51: 9 | R51: Mix Brand | S51: 1000320 | T51: XS | U51: 1 | V51: 0 | W51: Կապույտ | X51: 5
A52: 51 | B52: 40000001064 | C52: 61091000000 | D52: ՏՂԱՄԱՐԴՈՒ ԵՎ ՏՂԱՅԻ ՇԱՊԻԿՆԵՐ ԲԱՄԲԱԿԵ ՄԱՆՎԱԾՔԻՑ | E52: Շապիկ | F52: 73 | G52: Տղամարդկանց | H52: 1 | I52: 0.176 | J52: 1 | K52: 0.176 | L52: PETROL | M52: 881 | N52: BANGLADESH | O52: 7485 | P52: Բամբակ | Q52: 9 | R52: Mix Brand | S52: 1000320 | T52: M | U52: 119 | V52: EUR 28 | W52: Կապույտ | X52: 5
A53: 52 | B53: 40000001063 | C53: 62034235000 | D53: ՏՂԱՄԱՐԴՈՒ ԵՎ ՏՂԱՅԻ ՏԱԲԱՏՆԵՐ ԲԱՄԲԱԿԵ ՄԱՆՎԱԾՔԻՑ | E53: Տաբատներ | F53: 93 | G53: Տղաների | H53: 4 | I53: 0.634 | J53: 1 | K53: 0.634 | L53: PETROL | M53: 881 | N53: PAKISTAN | O53: 7550 | P53: Բամբակ | Q53: 9 | R53: Mix Brand | S53: 1000320 | T53: 29 L32 | U53: 648 | V53: EUR 70 | W53: Կապույտ | X53: 5
A54: 53 | B54: 40000001062 | C54: 61033300000 | D54: ՏՂԱՄԱՐԴՈՒ ԺԱԿԵՏ ՍԻՆԹԵՏԻԿ ԹԵԼԵՐԻՑ | E54: Ժակետ | F54: 466 | G54: Տղամարդկանց | H54: 1 | I54: 0.476 | J54: 1 | K54: 0.476 | L54: PATAGONIA | M54: 898 | N54: NICARAGUA | O54: 5315 | P54: Պոլիեսթեր | Q54: 37 | R54: Mix Brand | S54: 1000320 | T54: M | U54: 119 | V54: 0 | W54: Մոխրագույն | X54: 8
A55: 54 | B55: 40000001061 | C55: 61103099000 | D55: ԿԱՆԱՑԻ ՍՎԻՏՐԵՐ ՔԻՄԱԿԱՆ ԹԵԼԵՐԻՑ | E55: Սվիտրեր | F55: 88 | G55: Կանանց | H55: 2 | I55: 0.344 | J55: 1 | K55: 0.344 | L55: TOM TAILOR | M55: 5 | N55: CHINA | O55: 7497 | P55: Պոլիակրիլ | Q55: 107 | R55: Mix Brand | S55: 1000320 | T55: XL | U55: 124 | V55: EUR 50 | W55: Սպիտակ | X55: 12
A56: 55 | B56: 40000001060 | C56: 62024000090 | D56: ԿԱՆԱՑԻ ԲԱՃԿՈՆ ՔԻՄԻԱԿԱՆ ԹԵԼԵՐԻՑ | E56: Բաճկոն | F56: 14 | G56: Կանանց | H56: 2 | I56: 0.848 | J56: 1 | K56: 0.848 | L56: TOM TAILOR | M56: 5 | N56: VIETNAM | O56: 7579 | P56: Պոլիեսթեր | Q56: 37 | R56: Mix Brand | S56: 1000320 | T56: XL | U56: 124 | V56: EUR 90 | W56: Սպիտակ | X56: 12
A57: 56 | B57: 40000001059 | C57: 62013000000 | D57: ՏՂԱՄԱՐԴՈՒ ԲԱՃԿՈՆ ԲԱՄԲԱԿԵ ՄԱՆՎԱԾՔԻՑ | E57: Բաճկոն | F57: 14 | G57: Տղամարդկանց | H57: 1 | I57: 0.944 | J57: 1 | K57: 0.944 | L57: PETROL | M57: 881 | N57: BANGLADESH | O57: 7485 | P57: Բամբակ | Q57: 9 | R57: Mix Brand | S57: 1000320 | T57: L | U57: 3 | V57: EUR 90 | W57: Կապույտ | X57: 5
A58: 57 | B58: 40000001058 | C58: 62034235000 | D58: ՏՂԱՅԻ ՏԱԲԱՏՆԵՐ ԲԱՄԲԱԿԵ ՄԱՆՎԱԾՔԻՑ | E58: Տաբատներ | F58: 93 | G58: Տղաների | H58: 4 | I58: 0.772 | J58: 1 | K58: 0.772 | L58: PETROL | M58: 881 | N58: BANGLADESH | O58: 7485 | P58: Բամբակ | Q58: 9 | R58: Mix Brand | S58: 1000320 | T58: 33 L34 | U58: 649 | V58: EUR 60 | W58: Կապույտ | X58: 5
A59: 58 | B59: 40000001057 | C59: 62034235000 | D59: ՏՂԱՅԻ ՏԱԲԱՏ ԲԱՄԲԱԿԵ ՄԱՆՎԱԾՔԻՑ | E59: Տաբատներ | F59: 93 | G59: Տղաների | H59: 4 | I59: 0.644 | J59: 1 | K59: 0.644 | L59: PETROL | M59: 881 | N59: TUNISIA | O59: 2185 | P59: Բամբակ | Q59: 9 | R59: Mix Brand | S59: 1000320 | T59: 30 L32 | U59: 650 | V59: EUR 70 | W59: Կապույտ | X59: 5
A60: 59 | B60: 40000001056 | C60: 61051000000 | D60: ՏՂԱՄԱՐԴՈՒ ԵՎ ՏՂԱՅԻ ՎԵՐՆԱՇԱՊԻԿՆԵՐ ԲԱՄԲԱԿԵ ՄԱՆՎԱԾՔԻՑ | E60: Վերնաշապիկ | F60: 82 | G60: Տղամարդկանց | H60: 1 | I60: 0.538 | J60: 1 | K60: 0.538 | L60: PETROL | M60: 881 | N60: INDIA | O60: 7505 | P60: Բամբակ | Q60: 9 | R60: Mix Brand | S60: 1000320 | T60: L | U60: 3 | V60: EUR 80 | W60: Գույնզգույն | X60: 17
A61: 60 | B61: 40000001055 | C61: 61033200000 | D61: ՏՂԱՄԱՐԴՈՒ ԺԱԿԵՏՆԵՐ ԲԱՄԲԱԿԵ ՄԱՆՎԱԾՔԻՑ | E61: Ժակետ | F61: 466 | G61: Տղամարդկանց | H61: 1 | I61: 0.712 | J61: 1 | K61: 0.712 | L61: S. OLIVER | M61: 17 | N61: BANGLADESH | O61: 7485 | P61: Բամբակ | Q61: 9 | R61: Mix Brand | S61: 1000320 | T61: US XL | U61: 651 | V61: EUR 70 | W61: Կապույտ | X61: 5
A62: 61 | B62: 40000001054 | C62: 61044200000 | D62: ԿԱՆԱՑԻ ԵՎ ԱՂՋԿԱ ՇՐՋԱԶԳԵՍՏՆԵՐ ԲԱՄԲԱԿԵ ՄԱՆՎԱԾՔԻՑ | E62: Զգեստ | F62: 43 | G62: Կանանց | H62: 2 | I62: 0.444 | J62: 1 | K62: 0.444 | L62: TOM TAILOR | M62: 5 | N62: BANGLADESH | O62: 7485 | P62: Բամբակ | Q62: 9 | R62: Mix Brand | S62: 1000320 | T62: XL | U62: 124 | V62: EUR 50 | W62: Սև | X62: 20
A63: 62 | B63: 40000001053 | C63: 61091000000 | D63: ՏՂԱՄԱՐԴՈՒ ԵՎ ՏՂԱՅԻ ՇԱՊԻԿՆԵՐ ԲԱՄԲԱԿԵ ՄԱՆՎԱԾՔԻՑ | E63: Շապիկ | F63: 73 | G63: Տղամարդկանց | H63: 1 | I63: 0.254 | J63: 1 | K63: 0.254 | L63: S. OLIVER | M63: 17 | N63: BANGLADESH | O63: 7485 | P63: Բամբակ | Q63: 9 | R63: Mix Brand | S63: 1000320 | T63: L | U63: 3 | V63: EUR 36 | W63: Մոխրագույն | X63: 8
A64: 63 | B64: 40000001052 | C64: 61091000000 | D64: ԿԱՆԱՑԻ ԵՎ ԱՂՋԿԱ ՇԱՊԻԿՆԵՐ ԲԱՄԲԱԿԵ ՄԱՆՎԱԾՔԻՑ | E64: Շապիկ | F64: 73 | G64: Կանանց | H64: 2 | I64: 0.16 | J64: 1 | K64: 0.16 | L64: S. OLIVER | M64: 17 | N64: BANGLADESH | O64: 7485 | P64: Բամբակ | Q64: 9 | R64: Mix Brand | S64: 1000320 | T64: 44 | U64: 95 | V64: EUR 20 | W64: Կարմիր | X64: 1
A65: 64 | B65: 40000001051 | C65: 62034235000 | D65: ՏՂԱՄԱՐԴՈՒ ԵՎ ՏՂԱՅԻ ՏԱԲԱՏՆԵՐ ԲԱՄԲԱԿԵ ՄԱՆՎԱԾՔԻՑ | E65: Տաբատներ | F65: 93 | G65: Տղաների | H65: 4 | I65: 0.582 | J65: 1 | K65: 0.582 | L65: PETROL | M65: 881 | N65: PAKISTAN | O65: 7550 | P65: Բամբակ | Q65: 9 | R65: Mix Brand | S65: 1000320 | T65: 32 L32 | U65: 652 | V65: EUR 70 | W65: Կապույտ | X65: 5
A66: 65 | B66: 40000001050 | C66: 61091000000 | D66: ՏՂԱՄԱՐԴՈՒ ԵՎ ՏՂԱՅԻ ՇԱՊԻԿՆԵՐ ԲԱՄԲԱԿԵ ՄԱՆՎԱԾՔԻՑ | E66: Շապիկ | F66: 73 | G66: Տղամարդկանց | H66: 1 | I66: 0.264 | J66: 1 | K66: 0.264 | L66: FRED PERRY | M66: 790 | N66: CHINA | O66: 7497 | P66: Բամբակ | Q66: 9 | R66: Mix Brand | S66: 1000320 | T66: L | U66: 3 | V66: 0 | W66: Սև | X66: 20
A67: 66 | B67: 40000001049 | C67: 61043300000 | D67: ԿԱՆԱՑԻ ԺԱԿԵՏՆԵՐ ՍԻՆԹԵՏԻԿ ԹԵԼԵՐԻՑ | E67: Ժակետ | F67: 466 | G67: Կանանց | H67: 2 | I67: 0.174 | J67: 1 | K67: 0.174 | L67: TOM TAILOR | M67: 5 | N67: CHINA | O67: 7497 | P67: Պոլիեսթեր | Q67: 37 | R67: Mix Brand | S67: 1000320 | T67: XL | U67: 124 | V67: EUR 50 | W67: Մոխրագույն | X67: 8
A68: 67 | B68: 40000001048 | C68: 62013000000 | D68: ՏՂԱՄԱՐԴՈՒ ԲԱՃԿՈՆ ԲԱՄԲԱԿԵ ՄԱՆՎԱԾՔԻՑ | E68: Բաճկոն | F68: 14 | G68: Տղամարդկանց | H68: 1 | I68: 0.562 | J68: 1 | K68: 0.562 | L68: PETROL | M68: 881 | N68: CHINA | O68: 7497 | P68: Բամբակ | Q68: 9 | R68: Mix Brand | S68: 1000320 | T68: M | U68: 119 | V68: EUR 90 | W68: Սև | X68: 20
A69: 68 | B69: 40000001047 | C69: 61043300000 | D69: ԿԱՆԱՑԻ ԺԱԿԵՏՆԵՐ ՍԻՆԹԵՏԻԿ ԹԵԼԵՐԻՑ | E69: Ժակետ | F69: 466 | G69: Կանանց | H69: 2 | I69: 0.384 | J69: 1 | K69: 0.384 | L69: TOM TAILOR | M69: 5 | N69: CHINA | O69: 7497 | P69: Պոլիեսթեր | Q69: 37 | R69: Mix Brand | S69: 1000320 | T69: 36 | U69: 52 | V69: EUR 80 | W69: Սև | X69: 20
A70: 69 | B70: 40000001046 | C70: 61099020000 | D70: ԿԱՆԱՑԻ ՇԱՊԻԿՆԵՐ ՔԻՄԻԱԿԱՆ ԹԵԼԵՐԻՑ | E70: Շապիկ | F70: 73 | G70: Կանանց | H70: 2 | I70: 0.154 | J70: 1 | K70: 0.154 | L70: TOM TAILOR | M70: 5 | N70: TURKEY | O70: 1840 | P70: Պոլիեսթեր | Q70: 37 | R70: Mix Brand | S70: 1000320 | T70: XL | U70: 124 | V70: EUR 30 | W70: Կանաչ | X70: 4
A71: 70 | B71: 40000001045 | C71: 61091000000 | D71: ԿԱՆԱՑԻ ԵՎ ԱՂՋԿԱ ՇԱՊԻԿՆԵՐ ԲԱՄԲԱԿԵ ՄԱՆՎԱԾՔԻՑ | E71: Շապիկ | F71: 73 | G71: Կանանց | H71: 2 | I71: 0.14 | J71: 1 | K71: 0.14 | L71: CAVALLI | M71: 767 | N71: BANGLADESH | O71: 7485 | P71: Բամբակ | Q71: 9 | R71: Mix Brand | S71: 1000320 | T71: XL | U71: 124 | V71: 0 | W71: Սև | X71: 20
A72: 71 | B72: 40000001044 | C72: 61043300000 | D72: ԿԱՆԱՑԻ ԺԱԿԵՏՆԵՐ ՍԻՆԹԵՏԻԿ ԹԵԼԵՐԻՑ | E72: Ժակետ | F72: 466 | G72: Կանանց | H72: 2 | I72: 0.416 | J72: 1 | K72: 0.416 | L72: PATAGONIA | M72: 898 | N72: SRI LANKA | O72: 7565 | P72: Պոլիեսթեր | Q72: 37 | R72: Mix Brand | S72: 1000320 | T72: S | U72: 122 | V72: 0 | W72: Կաթնագույն | X72: 23
A73: 72 | B73: 40000001043 | C73: 61091000000 | D73: ՏՂԱՄԱՐԴՈՒ ԵՎ ՏՂԱՅԻ ՇԱՊԻԿՆԵՐ ԲԱՄԲԱԿԵ ՄԱՆՎԱԾՔԻՑ | E73: Շապիկ | F73: 73 | G73: Տղամարդկանց | H73: 1 | I73: 0.282 | J73: 1 | K73: 0.282 | L73: S. OLIVER | M73: 17 | N73: BANGLADESH | O73: 7485 | P73: Բամբակ | Q73: 9 | R73: Mix Brand | S73: 1000320 | T73: XL | U73: 124 | V73: EUR 36 | W73: Մոխրագույն | X73: 8
A74: 73 | B74: 40000001042 | C74: 62046239000 | D74: ԿԱՆԱՑԻ ԵՎ ԱՂՋԿԱ ՏԱԲԱՏՆԵՐ ԲԱՄԲԱԿԵ ՄԱՆՎԱԾՔԻՑ | E74: Տաբատներ | F74: 93 | G74: Կանանց | H74: 2 | I74: 0.292 | J74: 1 | K74: 0.292 | L74: S. OLIVER | M74: 17 | N74: BANGLADESH | O74: 7485 | P74: Բամբակ | Q74: 9 | R74: Mix Brand | S74: 1000320 | T74: 146 | U74: 181 | V74: EUR 40 | W74: Սև | X74: 20
A75: 74 | B75: 40000001041 | C75: 62046239000 | D75: ԿԱՆԱՑԻ ԵՎ ԱՂՋԿԱ ՏԱԲԱՏՆԵՐ ԲԱՄԲԱԿԵ ՄԱՆՎԱԾՔԻՑ | E75: Տաբատներ | F75: 93 | G75: Կանանց | H75: 2 | I75: 0.26 | J75: 1 | K75: 0.26 | L75: S. OLIVER | M75: 17 | N75: BANGLADESH | O75: 7485 | P75: Բամբակ | Q75: 9 | R75: Mix Brand | S75: 1000320 | T75: 134 | U75: 164 | V75: EUR 40 | W75: Սև | X75: 20
A76: 75 | B76: 40000001040 | C76: 62034235000 | D76: ՏՂԱՅԻ ՏԱԲԱՏՆԵՐ ԲԱՄԲԱԿԵ ՄԱՆՎԱԾՔԻՑ | E76: Տաբատներ | F76: 93 | G76: Տղաների | H76: 4 | I76: 0.71 | J76: 1 | K76: 0.71 | L76: PETROL | M76: 881 | N76: BANGLADESH | O76: 7485 | P76: Բամբակ | Q76: 9 | R76: Mix Brand | S76: 1000320 | T76: 34 L34 | U76: 653 | V76: EUR 80 | W76: Կաթնագույն | X76: 23
A77: 76 | B77: 40000001039 | C77: 61033200000 | D77: ՏՂԱՄԱՐԴՈՒ ԺԱԿԵՏՆԵՐ ԲԱՄԲԱԿԵ ՄԱՆՎԱԾՔԻՑ | E77: Ժակետ | F77: 466 | G77: Տղամարդկանց | H77: 1 | I77: 0.394 | J77: 1 | K77: 0.394 | L77: PETROL | M77: 881 | N77: BANGLADESH | O77: 7485 | P77: Բամբակ/Ակրիլ | Q77: 9-2 | R77: Mix Brand | S77: 1000320 | T77: S | U77: 122 | V77: EUR 70 | W77: Կաթնագույն | X77: 23
A78: 77 | B78: 40000001038 | C78: 62013000000 | D78: ՏՂԱՄԱՐԴՈՒ ԲԱՃԿՈՆՆԵՐ ԲԱՄԲԱԿԵ ՄԱՆՎԱԾՔԻՑ | E78: Բաճկոն | F78: 14 | G78: Տղամարդկանց | H78: 1 | I78: 1.128 | J78: 1 | K78: 1.128 | L78: PETROL | M78: 881 | N78: PAKISTAN | O78: 7550 | P78: Բամբակ | Q78: 9 | R78: Mix Brand | S78: 1000320 | T78: M | U78: 119 | V78: EUR 100 | W78: Կանաչ | X78: 4
A79: 78 | B79: 40000001037 | C79: 62046318000 | D79: ԿԱՆԱՑԻ ՏԱԲԱՏՆԵՐ ՍԻՆԹԵՏԻԿ ԹԵԼԵՐԻՑ | E79: Տաբատներ | F79: 93 | G79: Կանանց | H79: 2 | I79: 0.642 | J79: 1 | K79: 0.642 | L79: S. OLIVER | M79: 17 | N79: CHINA | O79: 7497 | P79: Մոդալ/Պոլիեսթեր | Q79: 57-37 | R79: Mix Brand | S79: 1000320 | T79: 44 | U79: 95 | V79: EUR 80 | W79: Կաթնագույն | X79: 23
A80: 79 | B80: 40000001036 | C80: 61091000000 | D80: ԿԱՆԱՑԻ ԵՎ ԱՂՋԿԱ ՇԱՊԻԿՆԵՐ ԲԱՄԲԱԿԵ ՄԱՆՎԱԾՔԻՑ | E80: Շապիկ | F80: 73 | G80: Կանանց | H80: 2 | I80: 0.096 | J80: 1 | K80: 0.096 | L80: S. OLIVER | M80: 17 | N80: BANGLADESH | O80: 7485 | P80: Բամբակ | Q80: 9 | R80: Mix Brand | S80: 1000320 | T80: 128/134 | U80: 654 | V80: EUR 14 | W80: Սպիտակ | X80: 12
A81: 80 | B81: 40000001035 | C81: 61091000000 | D81: ՏՂԱՄԱՐԴՈՒ ԵՎ ՏՂԱՅԻ ՇԱՊԻԿՆԵՐ ԲԱՄԲԱԿԵ ՄԱՆՎԱԾՔԻՑ | E81: Շապիկ | F81: 73 | G81: Տղամարդկանց | H81: 1 | I81: 0.17 | J81: 1 | K81: 0.17 | L81: PETROL | M81: 881 | N81: BANGLADESH | O81: 7485 | P81: Բամբակ | Q81: 9 | R81: Mix Brand | S81: 1000320 | T81: XL | U81: 124 | V81: EUR 20 | W81: Կաթնագույն | X81: 23
A82: 81 | B82: 40000001034 | C82: 61091000000 | D82: ԿԱՆԱՑԻ ԵՎ ԱՂՋԿԱ ՇԱՊԻԿՆԵՐ ԲԱՄԲԱԿԵ ՄԱՆՎԱԾՔԻՑ | E82: Շապիկ | F82: 73 | G82: Կանանց | H82: 2 | I82: 0.092 | J82: 1 | K82: 0.092 | L82: S. OLIVER | M82: 17 | N82: BANGLADESH | O82: 7485 | P82: Բամբակ | Q82: 9 | R82: Mix Brand | S82: 1000320 | T82: 104/110 | U82: 655 | V82: EUR 30 | W82: Կապույտ | X82: 5
A83: 82 | B83: 40000001033 | C83: 61034200090 | D83: ՏՂԱՅԻ ՇՈՐՏԵՐ ԲԱՄԲԱԿԵ ՄԱՆՎԱԾՔԻՑ | E83: Շորտ | F83: 24 | G83: Տղաների | H83: 4 | I83: 0.36 | J83: 1 | K83: 0.36 | L83: S. OLIVER | M83: 17 | N83: BANGLADESH | O83: 7485 | P83: Բամբակ/Լիոսել | Q83: 9-54 | R83: Mix Brand | S83: 1000320 | T83: 158/BIG | U83: 656 | V83: EUR 36 | W83: Կապույտ | X83: 5
A84: 83 | B84: 40000001032 | C84: 61103091000 | D84: ՏՂԱՄԱՐԴՈՒ ՀՈՒԴԻ ՔԻՄԻԱԿԱՆ ԹԵԼԵՐԻՑ | E84: Հուդի | F84: 18 | G84: Unisex | H84: 5 | I84: 0.75 | J84: 1 | K84: 0.75 | L84: PATAGONIA | M84: 898 | N84: MEXICO | O84: 3220 | P84: Պոլիեսթեր/Բամբակ | Q84: 37-9 | R84: Mix Brand | S84: 1000320 | T84: w XL m L | U84: 657 | V84: 0 | W84: Կանաչ | X84: 4
A85: 84 | B85: 40000001031 | C85: 61091000000 | D85: ԿԱՆԱՑԻ ԵՎ ԱՂՋԿԱ ՇԱՊԻԿՆԵՐ ԲԱՄԲԱԿԵ ՄԱՆՎԱԾՔԻՑ | E85: Շապիկ | F85: 73 | G85: Կանանց | H85: 2 | I85: 0.118 | J85: 1 | K85: 0.118 | L85: S. OLIVER | M85: 17 | N85: BANGLADESH | O85: 7485 | P85: Բամբակ | Q85: 9 | R85: Mix Brand | S85: 1000320 | T85: 140 | U85: 162 | V85: EUR 30 | W85: Կապույտ | X85: 5
A86: 85 | B86: 40000001030 | C86: 65050090000 | D86: ՏՂԱՄԱՐԴՈՒ ԳԼԽԱՐԿՆԵՐ ՔԻՄԻԱԿԱՆ ԹԵԼԵՐԻՑ | E86: Գլխարկ | F86: 5 | G86: Տղամարդկանց | H86: 1 | I86: 0.172 | J86: 1 | K86: 0.172 | L86: PATAGONIA | M86: 898 | N86: VIETNAM | O86: 7579 | P86: Պոլիեսթեր | Q86: 37 | R86: Mix Brand | S86: 1000320 | T86: 0 | U86: 4 | V86: 0 | W86: Կապույտ | X86: 5
A87: 86 | B87: 40000001029 | C87: 61102091000 | D87: ՏՂԱՄԱՐԴՈՒ ՀՈՒԴԻՆԵՐ ԲԱՄԲԱԿԵ ՄԱՆՎԱԾՔԻՑ | E87: Հուդի | F87: 18 | G87: Տղամարդկանց | H87: 1 | I87: 0.726 | J87: 1 | K87: 0.726 | L87: PETROL | M87: 881 | N87: PAKISTAN | O87: 7550 | P87: Բամբակ | Q87: 9 | R87: Mix Brand | S87: 1000320 | T87: L | U87: 3 | V87: EUR 70 | W87: Կաթնագույն | X87: 23
A88: 87 | B88: 40000001028 | C88: 64029996000 | D88: ՏՂԱՄԱՐԴՈՒ ՍՊՈՐՏԱՅԻՆ ՈՃԻ ԿՈՇԻԿ ԱՐՀԵՍՏԱԿԱՆ ԿԱՇՎԵ ԵՐԵՍԱՄԱՍՈՎ , ՊՈԼԻՄԵՐԱՅԻՆ ԿՈՇԿԱՏԱԿՈՎ | E88: Սպորտային Կոշիկ | F88: 67 | G88: Տղամարդկանց | H88: 1 | I88: 0.698 | J88: 1 | K88: 0.906 | L88: 4F | M88: 884 | N88: CHINA | O88: 7497 | P88: Տակացու Պոլիմեր, Վրան Արհեստական Կաշի | Q88: 101-7 | R88: Mix Brand | S88: 1000320 | T88: 44 | U88: 95 | V88: 0 | W88: Կարմիր | X88: 1
A89: 88 | B89: 40000001027 | C89: 64029998000 | D89: ԿԱՆԱՑԻ ՍՊՈՐՏԱՅԻՆ ՈՃԻ ԿՈՇԻԿ ԱՐՀԵՍՏԱԿԱՆ ԿԱՇՎԵ ԵՐԵՍԱՄԱՍՈՎ , ՌԵՏԻՆԵ ԿՈՇԿԱՏԱԿՈՎ | E89: Սպորտային Կոշիկ | F89: 67 | G89: Կանանց | H89: 2 | I89: 0.546 | J89: 1 | K89: 0.72 | L89: ONLY | M89: 28 | N89: CHINA | O89: 7497 | P89: Տակացու Ռետին, Վրան Արհեստական Կաշի | Q89: 102-7 | R89: Mix Brand | S89: 1000320 | T89: 37 | U89: 282 | V89: 0 | W89: Վարդագույն | X89: 13
A90: 89 | B90: 40000001026 | C90: 64029998000 | D90: ԿԱՆԱՑԻ ՍՊՈՐՏԱՅԻՆ ՈՃԻ ԿՈՇԻԿՆԵՐ ԱՐՀԵՍՏԱԿԱՆ ԿԱՇՎԵ ԵՐԵՍԱՄԱՍՈՎ , ՊՈԼԻՄԵՐԱՅԻՆ ԿՈՇԿԱՏԱԿՈՎ | E90: Սպորտային Կոշիկ | F90: 67 | G90: Կանանց | H90: 2 | I90: 0.73 | J90: 1 | K90: 0.926 | L90: JENNY FAIRY | M90: 893 | N90: CHINA | O90: 7497 | P90: Տակացու Պոլիմեր, Վրան Արհեստական Կաշի | Q90: 101-7 | R90: Mix Brand | S90: 1000320 | T90: 37 | U90: 282 | V90: 0 | W90: Վարդագույն | X90: 13
A91: 90 | B91: 40000001025 | C91: 64041990000 | D91: ԿԱՆԱՑԻ ՃՏՔԱՎՈՐ ԿՈՇԻԿ ԲՐԴԵ ԵՐԵՍԱՄԱՍՈՎ ՌԵՏԻՆԵ ԿՈՇԿԱՏԱԿՈՎ | E91: Երկարաճիտ Կոշիկ | F91: 59 | G91: Կանանց | H91: 2 | I91: 0.79 | J91: 1 | K91: 1.214 | L91: EMU AUSTRALIA | M91: 890 | N91: AUSTRALIA | O91: 8625 | P91: Տակացու Ռետին, Վրան Բուրդ | Q91: 102-11 | R91: Mix Brand | S91: 1000320 | T91: 41 | U91: 288 | V91: 0 | W91: Շագանակագույն | X91: 10
A92: 91 | B92: 40000001024 | C92: 64039991000 | D92: ԱՂՋԿԱ ԲՈԿՈՏԻԿՆԵՐ ԲՆԱԿԱՆ ԿԱՇՎԵ ԵՐԵՍԱՄԱՍՈՎ , ՊՈԼԻՄԵՐԱՅԻՆ ԿՈՇԿԱՏԱԿՈՎ ՄԻՆՉԵՎ 24ՍՄ ՆԵՐԲԱՆԻ ԵՐԿԱՐՈՒԹՅԱՄԲ | E92: Սանդալ | F92: 66 | G92: Աղջիկների | H92: 3 | I92: 0.384 | J92: 1 | K92: 0.51 | L92: HI-TEC | M92: 892 | N92: CHINA | O92: 7497 | P92: Տակացու Պոլիմեր, Վրան Կաշի | Q92: 101-20 | R92: Mix Brand | S92: 1000320 | T92: 31 | U92: 140 | V92: 0 | W92: Վարդագույն | X92: 13
A93: 92 | B93: 40000001023 | C93: 64041990000 | D93: ՏՂԱՄԱՐԴՈՒ ՍՊՈՐՏԱՅԻՆ ՈՃԻ ԿՈՇԻԿՆԵՐ ՏԵՔՏՍԻԼԵ ԵՐԵՍԱՄԱՍՈՎ ՌԵՏԻՆԵ ԿՈՇԿԱՏԱԿՈՎ | E93: Սպորտային Կոշիկ | F93: 67 | G93: Տղամարդկանց | H93: 1 | I93: 0.716 | J93: 1 | K93: 0.9 | L93: MERRELL | M93: 895 | N93: VIETNAM | O93: 7579 | P93: Տակացու Ռետին, Վրան Կտոր | Q93: 102-25 | R93: Mix Brand | S93: 1000320 | T93: 40.5 | U93: 658 | V93: 0 | W93: Մոխրագույն | X93: 8
A94: 93 | B94: 40000001022 | C94: 64029991000 | D94: ԱՂՋԿԱ ԿԻՍԱՃՏՔԱՎՈՐ ԿՈՇԻԿ ԱՐՀԵՍՏԱԿԱՆ ԿԱՇՎԵ ԵՐԵՍԱՄԱՍՈՎ , ՊՈԼԻՄԵՐԱՅԻՆ ԿՈՇԿԱՏԱԿՈՎ ՄԻՆՉԵՎ 24ՍՄ ՆԵՐԲԱՆԻ ԵՐԿԱՐՈՒԹՅԱՄԲ | E94: Կիսաճտքավոր Կոշիկ | F94: 470 | G94: Աղջիկների | H94: 3 | I94: 0.598 | J94: 1 | K94: 0.784 | L94: NELLI | M94: 896 | N94: CHINA | O94: 7497 | P94: Տակացու Պոլիմեր, Վրան Արհեստական Կաշի | Q94: 101-7 | R94: Mix Brand | S94: 1000320 | T94: 30 | U94: 22 | V94: 0 | W94: Շագանակագույն | X94: 10
A95: 94 | B95: 40000001021 | C95: 64039118000 | D95: ԿԱՆԱՑԻ ԿԻՍԱՃՏՔԱՎՈՐ ԿՈՇԻԿ ԲՆԱԿԱՆ ԿԱՇՎԵ ԵՐԵՍԱՄԱՍՈՎ ՌԵՏԻՆԵ ԿՈՇԿԱՏԱԿՈՎ | E95: Կիսաճտքավոր Կոշիկ | F95: 470 | G95: Տղամարդկանց | H95: 1 | I95: 0.676 | J95: 1 | K95: 0.904 | L95: HELLYHANSE | M95: 891 | N95: VIETNAM | O95: 7579 | P95: Տակացու Ռետին, Վրան Կաշի | Q95: 102-20 | R95: Mix Brand | S95: 1000320 | T95: 37.5 | U95: 287 | V95: 0 | W95: Կանաչ | X95: 4
A96: 95 | B96: 40000001020 | C96: 64039118000 | D96: ԿԱՆԱՑԻ ԿԻՍԱՃՏՔԱՎՈՐ ԿՈՇԻԿ ԲՆԱԿԱՆ ԿԱՇՎԵ ԵՐԵՍԱՄԱՍՈՎ ՌԵՏԻՆԵ ԿՈՇԿԱՏԱԿՈՎ | E96: Կիսաճտքավոր Կոշիկ | F96: 470 | G96: Կանանց | H96: 2 | I96: 0.916 | J96: 1 | K96: 1.414 | L96: RAGE AGE | M96: 882 | N96: BANGLADESH | O96: 7485 | P96: Տակացու Ռետին, Վրան Կաշի | Q96: 102-20 | R96: Mix Brand | S96: 1000320 | T96: 39 | U96: 275 | V96: 0 | W96: Կաթնագույն | X96: 23
A97: 96 | B97: 40000001019 | C97: 64041990000 | D97: ԿԱՆԱՑԻ ԵՎ ԱՂՋԿԱ ՍՊՈՐՏԱՅԻՆ ՈՃԻ ԿՈՇԻԿՆԵՐ ՏԵՔՏՍԻԼԵ ԵՐԵՍԱՄԱՍՈՎ ՌԵՏԻՆԵ ԿՈՇԿԱՏԱԿՈՎ | E97: Սպորտային Կոշիկ | F97: 67 | G97: Կանանց | H97: 2 | I97: 0.522 | J97: 1 | K97: 0.666 | L97: BIG STAR | M97: 885 | N97: CHINA | O97: 7497 | P97: Տակացու Ռետին, Վրան Կտոր | Q97: 102-25 | R97: Mix Brand | S97: 1000320 | T97: 38 | U97: 64 | V97: 0 | W97: Կարմիր | X97: 1
A98: 97 | B98: 40000001018 | C98: 64041990000 | D98: ՏՂԱՄԱՐԴՈՒ ՍՊՈՐՏԱՅԻՆ ՈՃԻ ԿՈՇԻԿՆԵՐ ՏԵՔՏՍԻԼԵ ԵՐԵՍԱՄԱՍՈՎ ՌԵՏԻՆԵ ԿՈՇԿԱՏԱԿՈՎ | E98: Սպորտային Կոշիկ | F98: 67 | G98: Տղամարդկանց | H98: 1 | I98: 0.792 | J98: 1 | K98: 0.958 | L98: BROOKS | M98: 886 | N98: VIETNAM | O98: 7579 | P98: Տակացու Ռետին, Վրան Կտոր | Q98: 102-25 | R98: Mix Brand | S98: 1000320 | T98: 45 | U98: 283 | V98: 0 | W98: Կապույտ | X98: 5
A99: 98 | B99: 40000001017 | C99: 64041990000 | D99: ԿԱՆԱՑԻ ԵՎ ԱՂՋԿԱ ՍՊՈՐՏԱՅԻՆ ՈՃԻ ԿՈՇԻԿՆԵՐ ՏԵՔՏՍԻԼԵ ԵՐԵՍԱՄԱՍՈՎ ՌԵՏԻՆԵ ԿՈՇԿԱՏԱԿՈՎ | E99: Սպորտային Կոշիկ | F99: 67 | G99: Կանանց | H99: 2 | I99: 0.818 | J99: 1 | K99: 0.946 | L99: BIG STAR | M99: 885 | N99: CHINA | O99: 7497 | P99: Տակացու Ռետին, Վրան Կտոր | Q99: 102-25 | R99: Mix Brand | S99: 1000320 | T99: 39 | U99: 275 | V99: 0 | W99: Սպիտակ | X99: 12
... A101: 100 | B101: 40000001015 | C101: 64029991000 | D101: ԱՂՋԿԱ ԿՈՇԻԿ ԱՐՀԵՍՏԱԿԱՆ ԿԱՇՎԵ ԵՐԵՍԱՄԱՍՈՎ , ՌԵՏԻՆԵ ԿՈՇԿԱՏԱԿՈՎ ՄԻՆՉԵՎ 24ՍՄ ՆԵՐԲԱՆԻ ԵՐԿԱՐՈՒԹՅԱՄԲ | E101: Կոշիկ | F101: 55 | G101: Աղջիկների | H101: 3 | I101: 0.162 | J101: 1 | K101: 0.262 | L101: CHICCO | M101: 608 | N101: CHINA | O101: 7497 | P101: Տակացու Ռետին, Վրան Արհեստական Կաշի | Q101: 102-7 | R101: Mix Brand | S101: 1000320 | T101: 19 | U101: 370 | V101: 0 | W101: Վարդագույն | X101: 13
...

Sheet Rinascimento
A1: N | B1: Code | C1: HS code | D1: name | E1: Sub-category | F1: Sub-category id | G1: Gender | H1: Gender id | I1: Netto | J1: pc | K1: Brutto | L1: Brand | M1: Brand id | N1: Country | O1: Country id | P1: Material | Q1: Material id | R1: Package | S1: Package Id | T1: Size | U1: Size id | V1: Original price | W1: Color | X1: Color id
A2: 1343 | B2: 60000000693 | C2: 64029931000 | D2: ԿԱՆԱՑԻ ԲԱՐՁՐԱԿՐՈՒՆԿ ԿՈՇԻԿՆԵՐ ԱՐՀԵՍՏԱԿԱՆ ԿԱՇՎԵ ԵՐԵՍԱՄԱՍՈՎ , ՊՈԼԻՄԵՐԱՅԻՆ ԿՈՇԿԱՏԱԿՈՎ | E2: Բարձրակրունկ Կոշիկ | F2: 465 | G2: Կանանց | H2: 2 | I2: 0.414 | J2: 1 | K2: 0.77 | L2: Rinascimento | M2: 497 | N2: CHINA | O2: 7497 | P2: Տակացու Պոլիմեր, Վրան Արհեստական Կաշի | Q2: 101-7 | R2: Rinascimento | S2: 1000323 | T2: 38 | U2: 575 | V2: 91 | W2: Վարդագույն | X2: 13
A3: 1344 | B3: 60000000694 | C3: 61044300000 | D3: ԿԱՆԱՑԻ ՇՐՋԱԶԳԵՍՏՆԵՐ ՍԻՆԹԵՏԻԿ ԹԵԼԵՐԻՑ | E3: Զգեստ | F3: 43 | G3: Կանանց | H3: 2 | I3: 0.656 | J3: 1 | K3: 0.656 | L3: Rinascimento | M3: 497 | N3: ITALY | O3: 1760 | P3: Պոլիեսթեր | Q3: 37 | R3: Rinascimento | S3: 1000323 | T3: xs | U3: 1 | V3: 200 | W3: Կապույտ | X3: 5
A4: 1345 | B4: 60000000695 | C4: 61044300000 | D4: ԿԱՆԱՑԻ ՇՐՋԱԶԳԵՍՏՆԵՐ ՍԻՆԹԵՏԻԿ ԹԵԼԵՐԻՑ | E4: Զգեստ | F4: 43 | G4: Կանանց | H4: 2 | I4: 0.196 | J4: 1 | K4: 0.196 | L4: Rinascimento | M4: 497 | N4: ITALY | O4: 1760 | P4: Պոլիեսթեր | Q4: 37 | R4: Rinascimento | S4: 1000323 | T4: xs | U4: 1 | V4: 130 | W4: Շագանակագույն | X4: 10
A5: 1346 | B5: 60000000696 | C5: 61043300000 | D5: ԿԱՆԱՑԻ ՊԻՋԱԿՆԵՐ ՍԻՆԹԵՏԻԿ ԹԵԼԵՐԻՑ | E5: Պիջակ | F5: 153 | G5: Կանանց | H5: 2 | I5: 0.442 | J5: 1 | K5: 0.442 | L5: Rinascimento | M5: 497 | N5: ITALY | O5: 1760 | P5: Պոլիեսթեր | Q5: 37 | R5: Rinascimento | S5: 1000323 | T5: xs | U5: 1 | V5: 160 | W5: Կանաչ | X5: 4
A6: 1347 | B6: 60000000697 | C6: 61043300000 | D6: ԿԱՆԱՑԻ ՊԻՋԱԿՆԵՐ ՍԻՆԹԵՏԻԿ ԹԵԼԵՐԻՑ | E6: Պիջակ | F6: 153 | G6: Կանանց | H6: 2 | I6: 0.432 | J6: 1 | K6: 0.432 | L6: Rinascimento | M6: 497 | N6: ITALY | O6: 1760 | P6: Պոլիեսթեր | Q6: 37 | R6: Rinascimento | S6: 1000323 | T6: M | U6: 119 | V6: 130 | W6: Սև | X6: 20
A7: 1348 | B7: 60000000698 | C7: 61062000000 | D7: ԿԱՆԱՑԻ ԲԼՈՒԶՆԵՐ ՔԻՄԻԱԿԱՆ ԹԵԼԵՐԻՑ | E7: Բլուզ | F7: 77 | G7: Կանանց | H7: 2 | I7: 0.158 | J7: 1 | K7: 0.158 | L7: Rinascimento | M7: 497 | N7: ITALY | O7: 1760 | P7: Պոլիեսթեր | Q7: 37 | R7: Rinascimento | S7: 1000323 | T7: L | U7: 3 | V7: 70 | W7: Կարմիր | X7: 1
A8: 1349 | B8: 60000000699 | C8: 61043300000 | D8: ԿԱՆԱՑԻ ՊԻՋԱԿՆԵՐ ՍԻՆԹԵՏԻԿ ԹԵԼԵՐԻՑ | E8: Պիջակ | F8: 153 | G8: Կանանց | H8: 2 | I8: 0.35 | J8: 1 | K8: 0.35 | L8: Rinascimento | M8: 497 | N8: ITALY | O8: 1760 | P8: Պոլիեսթեր | Q8: 37 | R8: Rinascimento | S8: 1000323 | T8: 50 | U8: 576 | V8: 90 | W8: Կանաչ | X8: 4
A9: 1350 | B9: 60000000700 | C9: 61043900000 | D9: ԿԱՆԱՑԻ ԺԱԿԵՏ ԱՅԼ ՄԱՆԱԾԱԳՈՐԾԱԿԱՆ ՆՅՈՒԹԵՐԻՑ | E9: Ժակետ | F9: 466 | G9: Կանանց | H9: 2 | I9: 0.412 | J9: 1 | K9: 0.412 | L9: Rinascimento | M9: 497 | N9: ITALY | O9: 1760 | P9: Վիսկոզ | Q9: 53 | R9: Rinascimento | S9: 1000323 | T9: S | U9: 122 | V9: 110 | W9: Կանաչ | X9: 4
A10: 1351 | B10: 60000000701 | C10: 61043300000 | D10: ԿԱՆԱՑԻ ՊԻՋԱԿՆԵՐ ՍԻՆԹԵՏԻԿ ԹԵԼԵՐԻՑ | E10: Պիջակ | F10: 153 | G10: Կանանց | H10: 2 | I10: 0.162 | J10: 1 | K10: 0.162 | L10: Rinascimento | M10: 497 | N10: ITALY | O10: 1760 | P10: Պոլիեսթեր | Q10: 37 | R10: Rinascimento | S10: 1000323 | T10: M | U10: 119 | V10: 80 | W10: Կանաչ | X10: 4
A11: 1352 | B11: 60000000702 | C11: 61043300000 | D11: ԿԱՆԱՑԻ ՊԻՋԱԿՆԵՐ ՍԻՆԹԵՏԻԿ ԹԵԼԵՐԻՑ | E11: Պիջակ | F11: 153 | G11: Կանանց | H11: 2 | I11: 0.492 | J11: 1 | K11: 0.492 | L11: Rinascimento | M11: 497 | N11: ITALY | O11: 1760 | P11: Պոլիեսթեր | Q11: 37 | R11: Rinascimento | S11: 1000323 | T11: S | U11: 122 | V11: 150 | W11: Սպիտակ | X11: 12
A12: 1353 | B12: 60000000703 | C12: 61062000000 | D12: ԿԱՆԱՑԻ ԲԼՈՒԶՆԵՐ ՔԻՄԻԱԿԱՆ ԹԵԼԵՐԻՑ | E12: Բլուզ | F12: 77 | G12: Կանանց | H12: 2 | I12: 0.222 | J12: 1 | K12: 0.222 | L12: Rinascimento | M12: 497 | N12: ITALY | O12: 1760 | P12: Պոլիեսթեր | Q12: 37 | R12: Rinascimento | S12: 1000323 | T12: L | U12: 3 | V12: 70 | W12: Կաթնագույն | X12: 23
A13: 1354 | B13: 60000000704 | C13: 62046239000 | D13: ԿԱՆԱՑԻ ՏԱԲԱՏՆԵՐ ԲԱՄԲԱԿԵ ՄԱՆՎԱԾՔԻՑ | E13: Տաբատներ | F13: 93 | G13: Կանանց | H13: 2 | I13: 0.26 | J13: 1 | K13: 0.26 | L13: Rinascimento | M13: 497 | N13: ITALY | O13: 1760 | P13: Բամբակ | Q13: 9 | R13: Rinascimento | S13: 1000323 | T13: L | U13: 3 | V13: 120 | W13: Շագանակագույն | X13: 10
A14: 1355 | B14: 60000000705 | C14: 61044900000 | D14: ԿԱՆԱՑԻ ՇՐՋԱԶԳԵՍՏՆԵՐ ԱՅԼ ՄԱՆԱԾԱԳՈՐԾԱԿԱՆ ՆՅՈՒԹԵՐԻՑ | E14: Զգեստ | F14: 43 | G14: Կանանց | H14: 2 | I14: 0.404 | J14: 1 | K14: 0.404 | L14: Rinascimento | M14: 497 | N14: TURKEY | O14: 1840 | P14: Վիսկոզ | Q14: 53 | R14: Rinascimento | S14: 1000323 | T14: L | U14: 3 | V14: 90 | W14: Սպիտակ | X14: 12
A15: 1356 | B15: 60000000706 | C15: 61043300000 | D15: ԿԱՆԱՑԻ ՊԻՋԱԿՆԵՐ ՍԻՆԹԵՏԻԿ ԹԵԼԵՐԻՑ | E15: Պիջակ | F15: 153 | G15: Կանանց | H15: 2 | I15: 0.336 | J15: 1 | K15: 0.336 | L15: Rinascimento | M15: 497 | N15: ITALY | O15: 1760 | P15: Պոլիեսթեր | Q15: 37 | R15: Rinascimento | S15: 1000323 | T15: M | U15: 119 | V15: 100 | W15: Շագանակագույն | X15: 10
A16: 1357 | B16: 60000000707 | C16: 62046239000 | D16: ԿԱՆԱՑԻ ՏԱԲԱՏՆԵՐ ԲԱՄԲԱԿԵ ՄԱՆՎԱԾՔԻՑ | E16: Տաբատներ | F16: 93 | G16: Կանանց | H16: 2 | I16: 0.226 | J16: 1 | K16: 0.226 | L16: Rinascimento | M16: 497 | N16: ITALY | O16: 1760 | P16: Բամբակ | Q16: 9 | R16: Rinascimento | S16: 1000323 | T16: S | U16: 122 | V16: 90 | W16: Կապույտ | X16: 5
A17: 1358 | B17: 60000000708 | C17: 62046318000 | D17: ԿԱՆԱՑԻ ՏԱԲԱՏ ԻՐ ԳՈՏՈՎ ՍԻՆԹԵՏԻԿ ԹԵԼԵՐԻՑ | E17: Տաբատներ | F17: 93 | G17: Կանանց | H17: 2 | I17: 0.298 | J17: 1 | K17: 0.298 | L17: Rinascimento | M17: 497 | N17: ITALY | O17: 1760 | P17: Լյոսել | Q17: 54 | R17: Rinascimento | S17: 1000323 | T17: xs | U17: 1 | V17: 70 | W17: Կապույտ | X17: 5
A18: 1359 | B18: 60000000709 | C18: 62046318000 | D18: ԿԱՆԱՑԻ ԵՎ ԱՂՋԿԱ ՏԱԲԱՏՆԵՐ ՍԻՆԹԵՏԻԿ ԹԵԼԵՐԻՑ | E18: Տաբատներ | F18: 93 | G18: Կանանց | H18: 2 | I18: 0.174 | J18: 1 | K18: 0.174 | L18: Rinascimento | M18: 497 | N18: TURKEY | O18: 1840 | P18: Մոդալ | Q18: 57 | R18: Rinascimento | S18: 1000323 | T18: xs | U18: 1 | V18: 70 | W18: Շագանակագույն | X18: 10
A19: 1360 | B19: 60000000710 | C19: 61044300000 | D19: ԿԱՆԱՑԻ ՇՐՋԱԶԳԵՍՏՆԵՐ ՍԻՆԹԵՏԻԿ ԹԵԼԵՐԻՑ | E19: Զգեստ | F19: 43 | G19: Կանանց | H19: 2 | I19: 0.372 | J19: 1 | K19: 0.372 | L19: Rinascimento | M19: 497 | N19: ITALY | O19: 1760 | P19: Պոլիեսթեր | Q19: 37 | R19: Rinascimento | S19: 1000323 | T19: M | U19: 119 | V19: 170 | W19: Վարդագույն | X19: 13
A20: 1361 | B20: 60000000711 | C20: 61062000000 | D20: ԿԱՆԱՑԻ ԲԼՈՒԶՆԵՐ ՔԻՄԻԱԿԱՆ ԹԵԼԵՐԻՑ | E20: Բլուզ | F20: 77 | G20: Կանանց | H20: 2 | I20: 0.13 | J20: 1 | K20: 0.13 | L20: Rinascimento | M20: 497 | N20: ITALY | O20: 1760 | P20: Պոլիեսթեր | Q20: 37 | R20: Rinascimento | S20: 1000323 | T20: 46 | U20: 577 | V20: 90 | W20: Գույնզգույն | X20: 17
A21: 1362 | B21: 60000000712 | C21: 61062000000 | D21: ԿԱՆԱՑԻ ԲԼՈՒԶՆԵՐ ՔԻՄԻԱԿԱՆ ԹԵԼԵՐԻՑ | E21: Բլուզ | F21: 77 | G21: Կանանց | H21: 2 | I21: 0.156 | J21: 1 | K21: 0.156 | L21: Rinascimento | M21: 497 | N21: ITALY | O21: 1760 | P21: Պոլիեսթեր | Q21: 37 | R21: Rinascimento | S21: 1000323 | T21: M | U21: 119 | V21: 60 | W21: Սպիտակ | X21: 12
A22: 1363 | B22: 60000000713 | C22: 61062000000 | D22: ԿԱՆԱՑԻ ԲԼՈՒԶՆԵՐ ՔԻՄԻԱԿԱՆ ԹԵԼԵՐԻՑ | E22: Բլուզ | F22: 77 | G22: Կանանց | H22: 2 | I22: 0.102 | J22: 1 | K22: 0.102 | L22: Rinascimento | M22: 497 | N22: ITALY | O22: 1760 | P22: Պոլիեսթեր | Q22: 37 | R22: Rinascimento | S22: 1000323 | T22: S | U22: 122 | V22: 60 | W22: Կանաչ | X22: 4
A23: 1364 | B23: 60000000714 | C23: 61062000000 | D23: ԿԱՆԱՑԻ ԲԼՈՒԶՆԵՐ ՔԻՄԻԱԿԱՆ ԹԵԼԵՐԻՑ | E23: Բլուզ | F23: 77 | G23: Կանանց | H23: 2 | I23: 0.102 | J23: 1 | K23: 0.102 | L23: Rinascimento | M23: 497 | N23: ITALY | O23: 1760 | P23: Պոլիեսթեր | Q23: 37 | R23: Rinascimento | S23: 1000323 | T23: S | U23: 122 | V23: 60 | W23: Կանաչ | X23: 4
A24: 1365 | B24: 60000000715 | C24: 61044300000 | D24: ԿԱՆԱՑԻ ՇՐՋԱԶԳԵՍՏՆԵՐ ՍԻՆԹԵՏԻԿ ԹԵԼԵՐԻՑ | E24: Զգեստ | F24: 43 | G24: Կանանց | H24: 2 | I24: 0.508 | J24: 1 | K24: 0.508 | L24: Rinascimento | M24: 497 | N24: ITALY | O24: 1760 | P24: Պոլիեսթեր | Q24: 37 | R24: Rinascimento | S24: 1000323 | T24: xs | U24: 1 | V24: 200 | W24: Մանուշակագույն | X24: 7
A25: 1366 | B25: 60000000716 | C25: 61061000000 | D25: ԿԱՆԱՑԻ ԲԼՈՒԶՆԵՐ ԲԱՄԲԱԿԵ ՄԱՆՎԱԾՔԻՑ | E25: Բլուզ | F25: 77 | G25: Կանանց | H25: 2 | I25: 0.074 | J25: 1 | K25: 0.074 | L25: Rinascimento | M25: 497 | N25: ITALY | O25: 1760 | P25: Բամբակ | Q25: 9 | R25: Rinascimento | S25: 1000323 | T25: xs | U25: 1 | V25: 80 | W25: Վարդագույն | X25: 13
A26: 1367 | B26: 60000000717 | C26: 61044900000 | D26: ԿԱՆԱՑԻ ՇՐՋԱԶԳԵՍՏՆԵՐ ԱՅԼ ՄԱՆԱԾԱԳՈՐԾԱԿԱՆ ՆՅՈՒԹԵՐԻՑ | E26: Զգեստ | F26: 43 | G26: Կանանց | H26: 2 | I26: 0.304 | J26: 1 | K26: 0.304 | L26: Rinascimento | M26: 497 | N26: TURKEY | O26: 1840 | P26: Վիսկոզ | Q26: 53 | R26: Rinascimento | S26: 1000323 | T26: M | U26: 119 | V26: 90 | W26: Սպիտակ | X26: 12
A27: 1368 | B27: 60000000718 | C27: 61062000000 | D27: ԿԱՆԱՑԻ ԲԼՈՒԶՆԵՐ ՔԻՄԻԱԿԱՆ ԹԵԼԵՐԻՑ | E27: Բլուզ | F27: 77 | G27: Կանանց | H27: 2 | I27: 0.124 | J27: 1 | K27: 0.124 | L27: Rinascimento | M27: 497 | N27: ITALY | O27: 1760 | P27: Պոլիեսթեր | Q27: 37 | R27: Rinascimento | S27: 1000323 | T27: xs | U27: 1 | V27: 50 | W27: Մանուշակագույն | X27: 7
A28: 1369 | B28: 60000000719 | C28: 61046300000 | D28: ԿԱՆԱՑԻ ԿԱՄԲԻՆԻԶՈՆՆԵՐ ՍԻՆԹԵՏԻԿ ԹԵԼԵՐԻՑ | E28: Կոմբինեզոն | F28: 54 | G28: Կանանց | H28: 2 | I28: 0.434 | J28: 1 | K28: 0.434 | L28: Rinascimento | M28: 497 | N28: ITALY | O28: 1760 | P28: Պոլիեսթեր | Q28: 37 | R28: Rinascimento | S28: 1000323 | T28: xs | U28: 1 | V28: 160 | W28: Կապույտ | X28: 5
A29: 1370 | B29: 60000000720 | C29: 61043300000 | D29: ԿԱՆԱՑԻ ՊԻՋԱԿՆԵՐ ՍԻՆԹԵՏԻԿ ԹԵԼԵՐԻՑ | E29: Պիջակ | F29: 153 | G29: Կանանց | H29: 2 | I29: 0.21 | J29: 1 | K29: 0.21 | L29: Rinascimento | M29: 497 | N29: ITALY | O29: 1760 | P29: Պոլիեսթեր | Q29: 37 | R29: Rinascimento | S29: 1000323 | T29: xs | U29: 1 | V29: 90 | W29: Կապույտ | X29: 5
A30: 1371 | B30: 60000000721 | C30: 61044300000 | D30: ԿԱՆԱՑԻ ՇՐՋԱԶԳԵՍՏՆԵՐ ՍԻՆԹԵՏԻԿ ԹԵԼԵՐԻՑ | E30: Զգեստ | F30: 43 | G30: Կանանց | H30: 2 | I30: 0.508 | J30: 1 | K30: 0.508 | L30: Rinascimento | M30: 497 | N30: TURKEY | O30: 1840 | P30: Պոլիեսթեր | Q30: 37 | R30: Rinascimento | S30: 1000323 | T30: XL | U30: 124 | V30: 80 | W30: Կրեմագույն | X30: 16
A31: 1372 | B31: 60000000722 | C31: 61044300000 | D31: ԿԱՆԱՑԻ ՇՐՋԱԶԳԵՍՏՆԵՐ ՍԻՆԹԵՏԻԿ ԹԵԼԵՐԻՑ | E31: Զգեստ | F31: 43 | G31: Կանանց | H31: 2 | I31: 0.566 | J31: 1 | K31: 0.566 | L31: Rinascimento | M31: 497 | N31: ITALY | O31: 1760 | P31: Պոլիեսթեր | Q31: 37 | R31: Rinascimento | S31: 1000323 | T31: S | U31: 122 | V31: 220 | W31: Կանաչ | X31: 4
A32: 1373 | B32: 60000000723 | C32: 61062000000 | D32: ԿԱՆԱՑԻ ԲԼՈՒԶՆԵՐ ՔԻՄԻԱԿԱՆ ԹԵԼԵՐԻՑ | E32: Բլուզ | F32: 77 | G32: Կանանց | H32: 2 | I32: 0.102 | J32: 1 | K32: 0.102 | L32: Rinascimento | M32: 497 | N32: ITALY | O32: 1760 | P32: Պոլիեսթեր | Q32: 37 | R32: Rinascimento | S32: 1000323 | T32: S | U32: 122 | V32: 70 | W32: Վարդագույն | X32: 13
... A41: 1382 | B41: 60000000732 | C41: 61062000000 | D41: ԿԱՆԱՑԻ ԵՎ ԱՂՋԿԱ ԲԼՈՒԶՆԵՐ ՔԻՄԻԱԿԱՆ ԹԵԼԵՐԻՑ | E41: Բլուզ | F41: 77 | G41: Կանանց | H41: 2 | I41: 0.202 | J41: 1 | K41: 0.202 | L41: Rinascimento | M41: 497 | N41: TURKEY | O41: 1840 | P41: Մոդալ | Q41: 57 | R41: Rinascimento | S41: 1000323 | T41: L | U41: 3 | V41: 36 | W41: Սպիտակ | X41: 12
A42: 1383 | B42: 60000000733 | C42: 61044200000 | D42: ԿԱՆԱՑԻ ՇՐՋԱԶԳԵՍՏՆԵՐ ԲԱՄԲԱԿԵ ՄԱՆՎԱԾՔԻՑ | E42: Զգեստ | F42: 43 | G42: Կանանց | H42: 2 | I42: 0.298 | J42: 1 | K42: 0.298 | L42: Rinascimento | M42: 497 | N42: TURKEY | O42: 1840 | P42: Բամբակ/Պոլիեսթեր | Q42: 9-37 | R42: Rinascimento | S42: 1000323 | T42: xs | U42: 1 | V42: 80 | W42: Դեղին | X42: 3
A43: 1384 | B43: 60000000734 | C43: 61046300000 | D43: ԿԱՆԱՑԻ ՇՈՐՏԵՐ ՍԻՆԹԵՏԻԿ ԹԵԼԵՐԻՑ | E43: Շորտ | F43: 24 | G43: Կանանց | H43: 2 | I43: 0.276 | J43: 1 | K43: 0.276 | L43: Rinascimento | M43: 497 | N43: ITALY | O43: 1760 | P43: Պոլիեսթեր | Q43: 37 | R43: Rinascimento | S43: 1000323 | T43: L | U43: 3 | V43: 90 | W43: Կապույտ | X43: 5
A44: 1385 | B44: 60000000735 | C44: 61044900000 | D44: ԿԱՆԱՑԻ ՇՐՋԱԶԳԵՍՏՆԵՐ ԱՅԼ ՄԱՆԱԾԱԳՈՐԾԱԿԱՆ ՆՅՈՒԹԵՐԻՑ | E44: Զգեստ | F44: 43 | G44: Կանանց | H44: 2 | I44: 0.284 | J44: 1 | K44: 0.284 | L44: Rinascimento | M44: 497 | N44: TURKEY | O44: 1840 | P44: Վիսկոզ | Q44: 53 | R44: Rinascimento | S44: 1000323 | T44: xs | U44: 1 | V44: 90 | W44: Սև | X44: 20
A45: 1386 | B45: 60000000736 | C45: 61044300000 | D45: ԿԱՆԱՑԻ ՇՐՋԱԶԳԵՍՏՆԵՐ ՍԻՆԹԵՏԻԿ ԹԵԼԵՐԻՑ | E45: Զգեստ | F45: 43 | G45: Կանանց | H45: 2 | I45: 0.326 | J45: 1 | K45: 0.326 | L45: Rinascimento | M45: 497 | N45: ITALY | O45: 1760 | P45: Պոլիեսթեր | Q45: 37 | R45: Rinascimento | S45: 1000323 | T45: L | U45: 3 | V45: 140 | W45: Վարդագույն | X45: 13
A46: 1387 | B46: 60000000737 | C46: 61043300000 | D46: ԿԱՆԱՑԻ ՊԻՋԱԿՆԵՐ ՍԻՆԹԵՏԻԿ ԹԵԼԵՐԻՑ | E46: Պիջակ | F46: 153 | G46: Կանանց | H46: 2 | I46: 0.154 | J46: 1 | K46: 0.154 | L46: Rinascimento | M46: 497 | N46: ITALY | O46: 1760 | P46: Պոլիեսթեր | Q46: 37 | R46: Rinascimento | S46: 1000323 | T46: xs | U46: 1 | V46: 80 | W46: Վարդագույն | X46: 13
A47: 1388 | B47: 60000000738 | C47: 61044300000 | D47: ԿԱՆԱՑԻ ՇՐՋԱԶԳԵՍՏՆԵՐ ՍԻՆԹԵՏԻԿ ԹԵԼԵՐԻՑ | E47: Զգեստ | F47: 43 | G47: Կանանց | H47: 2 | I47: 0.384 | J47: 1 | K47: 0.384 | L47: Rinascimento | M47: 497 | N47: ITALY | O47: 1760 | P47: Պոլիեսթեր | Q47: 37 | R47: Rinascimento | S47: 1000323 | T47: xs | U47: 1 | V47: 110 | W47: Վարդագույն | X47: 13
A48: 1389 | B48: 60000000739 | C48: 61043300000 | D48: ԿԱՆԱՑԻ ՊԻՋԱԿՆԵՐ ՍԻՆԹԵՏԻԿ ԹԵԼԵՐԻՑ | E48: Պիջակ | F48: 153 | G48: Կանանց | H48: 2 | I48: 0.294 | J48: 1 | K48: 0.294 | L48: Rinascimento | M48: 497 | N48: ITALY | O48: 1760 | P48: Պոլիեսթեր | Q48: 37 | R48: Rinascimento | S48: 1000323 | T48: 48 | U48: 578 | V48: 112 | W48: Կաթնագույն | X48: 23
A49: 1390 | B49: 60000000740 | C49: 61044300000 | D49: ԿԱՆԱՑԻ ՇՐՋԱԶԳԵՍՏՆԵՐ ՍԻՆԹԵՏԻԿ ԹԵԼԵՐԻՑ | E49: Զգեստ | F49: 43 | G49: Կանանց | H49: 2 | I49: 0.396 | J49: 1 | K49: 0.396 | L49: Rinascimento | M49: 497 | N49: ITALY | O49: 1760 | P49: Պոլիեսթեր | Q49: 37 | R49: Rinascimento | S49: 1000323 | T49: xs | U49: 1 | V49: 156 | W49: Գույնզգույն | X49: 17
A50: 1391 | B50: 60000000741 | C50: 62046990000 | D50: ԿԱՆԱՑԻ ՏԱԲԱՏՆԵՐ ԱՅԼ ՄԱՆԱԾԱԳՈՐԾԱԿԱՆ ՆՅՈՒԹԵՐԻՑ | E50: Տաբատներ | F50: 93 | G50: Կանանց | H50: 2 | I50: 0.298 | J50: 1 | K50: 0.298 | L50: Rinascimento | M50: 497 | N50: ITALY | O50: 1760 | P50: Վիսկոզ | Q50: 53 | R50: Rinascimento | S50: 1000323 | T50: xs | U50: 1 | V50: 90 | W50: Նարնջագույն | X50: 9
A51: 1392 | B51: 60000000742 | C51: 61043300000 | D51: ԿԱՆԱՑԻ ՊԻՋԱԿՆԵՐ ՍԻՆԹԵՏԻԿ ԹԵԼԵՐԻՑ | E51: Պիջակ | F51: 153 | G51: Կանանց | H51: 2 | I51: 0.432 | J51: 1 | K51: 0.432 | L51: Rinascimento | M51: 497 | N51: ITALY | O51: 1760 | P51: Պոլիեսթեր | Q51: 37 | R51: Rinascimento | S51: 1000323 | T51: L | U51: 3 | V51: 90 | W51: Կաթնագույն | X51: 23
A52: 1393 | B52: 60000000743 | C52: 61044300000 | D52: ԿԱՆԱՑԻ ՇՐՋԱԶԳԵՍՏՆԵՐ ՍԻՆԹԵՏԻԿ ԹԵԼԵՐԻՑ | E52: Զգեստ | F52: 43 | G52: Կանանց | H52: 2 | I52: 0.366 | J52: 1 | K52: 0.366 | L52: Rinascimento | M52: 497 | N52: ITALY | O52: 1760 | P52: Պոլիեսթեր | Q52: 37 | R52: Rinascimento | S52: 1000323 | T52: S | U52: 122 | V52: 31 | W52: Գույնզգույն | X52: 17
A53: 1394 | B53: 60000000744 | C53: 61061000000 | D53: ԿԱՆԱՑԻ ԵՎ ԱՂՋԿԱ ԲԼՈՒԶՆԵՐ ԲԱՄԲԱԿԵ ՄԱՆՎԱԾՔԻՑ | E53: Բլուզ | F53: 77 | G53: Կանանց | H53: 2 | I53: 0.192 | J53: 1 | K53: 0.192 | L53: Rinascimento | M53: 497 | N53: TURKEY | O53: 1840 | P53: Բամբակ | Q53: 9 | R53: Rinascimento | S53: 1000323 | T53: L | U53: 3 | V53: 60 | W53: Կապույտ | X53: 5
A54: 1395 | B54: 60000000745 | C54: 61046300000 | D54: ԿԱՆԱՑԻ ԿԱՄԲԻՆԻԶՈՆՆԵՐ ՍԻՆԹԵՏԻԿ ԹԵԼԵՐԻՑ | E54: Կոմբինեզոն | F54: 54 | G54: Կանանց | H54: 2 | I54: 0.456 | J54: 1 | K54: 0.456 | L54: Rinascimento | M54: 497 | N54: ITALY | O54: 1760 | P54: Պոլիեսթեր | Q54: 37 | R54: Rinascimento | S54: 1000323 | T54: xs | U54: 1 | V54: 140 | W54: Սև | X54: 20
A55: 1396 | B55: 60000000746 | C55: 61044300000 | D55: ԿԱՆԱՑԻ ՇՐՋԱԶԳԵՍՏՆԵՐ ՍԻՆԹԵՏԻԿ ԹԵԼԵՐԻՑ | E55: Զգեստ | F55: 43 | G55: Կանանց | H55: 2 | I55: 0.538 | J55: 1 | K55: 0.538 | L55: Rinascimento | M55: 497 | N55: ITALY | O55: 1760 | P55: Պոլիեսթեր | Q55: 37 | R55: Rinascimento | S55: 1000323 | T55: S | U55: 122 | V55: 170 | W55: Վարդագույն | X55: 13
A56: 1397 | B56: 60000000747 | C56: 61044300000 | D56: ԿԱՆԱՑԻ ՇՐՋԱԶԳԵՍՏՆԵՐ ՍԻՆԹԵՏԻԿ ԹԵԼԵՐԻՑ | E56: Երեկոյան Զգեստ | F56: 467 | G56: Կանանց | H56: 2 | I56: 0.506 | J56: 1 | K56: 0.506 | L56: Rinascimento | M56: 497 | N56: ITALY | O56: 1760 | P56: Պոլիեսթեր | Q56: 37 | R56: Rinascimento | S56: 1000323 | T56: xs | U56: 1 | V56: 220 | W56: Կապույտ | X56: 5
A57: 1398 | B57: 60000000748 | C57: 61044300000 | D57: ԿԱՆԱՑԻ ՇՐՋԱԶԳԵՍՏՆԵՐ ՍԻՆԹԵՏԻԿ ԹԵԼԵՐԻՑ | E57: Զգեստ | F57: 43 | G57: Կանանց | H57: 2 | I57: 0.274 | J57: 1 | K57: 0.274 | L57: Rinascimento | M57: 497 | N57: ITALY | O57: 1760 | P57: Պոլիեսթեր | Q57: 37 | R57: Rinascimento | S57: 1000323 | T57: XL | U57: 124 | V57: 140 | W57: Կապույտ | X57: 5
A58: 1399 | B58: 60000000749 | C58: 61043300000 | D58: ԿԱՆԱՑԻ ՊԻՋԱԿՆԵՐ ՍԻՆԹԵՏԻԿ ԹԵԼԵՐԻՑ | E58: Պիջակ | F58: 153 | G58: Կանանց | H58: 2 | I58: 0.436 | J58: 1 | K58: 0.436 | L58: Rinascimento | M58: 497 | N58: ITALY | O58: 1760 | P58: Պոլիեսթեր | Q58: 37 | R58: Rinascimento | S58: 1000323 | T58: M | U58: 119 | V58: 160 | W58: Ոսկեգույն | X58: 21
A59: 1400 | B59: 60000000750 | C59: 61046300000 | D59: ԿԱՆԱՑԻ ԿԱՄԲԻՆԻԶՈՆՆԵՐ ՍԻՆԹԵՏԻԿ ԹԵԼԵՐԻՑ | E59: Կոմբինեզոն | F59: 54 | G59: Կանանց | H59: 2 | I59: 0.546 | J59: 1 | K59: 0.546 | L59: Rinascimento | M59: 497 | N59: ITALY | O59: 1760 | P59: Պոլիեսթեր | Q59: 37 | R59: Rinascimento | S59: 1000323 | T59: xs | U59: 1 | V59: 140 | W59: Վարդագույն | X59: 13
A60: 1401 | B60: 60000000751 | C60: 61044900000 | D60: ԿԱՆԱՑԻ ՇՐՋԱԶԳԵՍՏՆԵՐ ԱՅԼ ՄԱՆԱԾԱԳՈՐԾԱԿԱՆ ՆՅՈՒԹԵՐԻՑ | E60: Զգեստ | F60: 43 | G60: Կանանց | H60: 2 | I60: 0.414 | J60: 1 | K60: 0.414 | L60: Rinascimento | M60: 497 | N60: ITALY | O60: 1760 | P60: Վիսկոզ | Q60: 53 | R60: Rinascimento | S60: 1000323 | T60: xs | U60: 1 | V60: 110 | W60: Վարդագույն | X60: 13
... A62: 1403 | B62: 60000000753 | C62: 62046318000 | D62: ԿԱՆԱՑԻ ԵՎ ԱՂՋԿԱ ՏԱԲԱՏՆԵՐ ՍԻՆԹԵՏԻԿ ԹԵԼԵՐԻՑ | E62: Տաբատներ | F62: 93 | G62: Կանանց | H62: 2 | I62: 0.284 | J62: 1 | K62: 0.284 | L62: Rinascimento | M62: 497 | N62: TURKEY | O62: 1840 | P62: Պոլիեսթեր | Q62: 37 | R62: Rinascimento | S62: 1000323 | T62: xs | U62: 1 | V62: 70 | W62: Սև | X62: 20
A63: 1404 | B63: 60000000754 | C63: 61044200000 | D63: ԿԱՆԱՑԻ ՇՐՋԱԶԳԵՍՏՆԵՐ ԲԱՄԲԱԿԵ ՄԱՆՎԱԾՔԻՑ | E63: Զգեստ | F63: 43 | G63: Կանանց | H63: 2 | I63: 0.26 | J63: 1 | K63: 0.26 | L63: Rinascimento | M63: 497 | N63: ITALY | O63: 1760 | P63: Բամբակ | Q63: 9 | R63: Rinascimento | S63: 1000323 | T63: 46 | U63: 577 | V63: 130 | W63: Շագանակագույն | X63: 10
A64: 1405 | B64: 60000000755 | C64: 61044200000 | D64: ԿԱՆԱՑԻ ՇՐՋԱԶԳԵՍՏՆԵՐ ԲԱՄԲԱԿԵ ՄԱՆՎԱԾՔԻՑ | E64: Զգեստ | F64: 43 | G64: Կանանց | H64: 2 | I64: 0.35 | J64: 1 | K64: 0.35 | L64: Rinascimento | M64: 497 | N64: ITALY | O64: 1760 | P64: Բամբակ | Q64: 9 | R64: Rinascimento | S64: 1000323 | T64: XL | U64: 124 | V64: 150 | W64: Սև | X64: 20
